{"id":577316,"name":"Mírová pod Kozákovem","nuts":"CZ0514","okres":5104,"kraj":5100,"volby":{"prezident":[{"year":2018,"round1":{"votes":932,"voters":1340,"attended":937,"candidates":[{"id":1,"name":["Ing.","Mirek","Topolánek",""],"votes":47,"pct":5.04},{"id":2,"name":["Mgr.","Michal","Horáček","Ph.D."],"votes":103,"pct":11.05},{"id":3,"name":["Mgr.","Pavel","Fischer",""],"votes":90,"pct":9.66},{"id":4,"name":["RNDr.","Jiří","Hynek",""],"votes":24,"pct":2.58},{"id":5,"name":["Mgr.","Petr","Hannig",""],"votes":3,"pct":0.32},{"id":6,"name":["Ing.","Vratislav","Kulhánek","Dr. h. c."],"votes":6,"pct":0.64},{"id":7,"name":["Ing.","Miloš","Zeman",""],"votes":280,"pct":30.04},{"id":8,"name":["MUDr. Bc.","Marek","Hilšer","Ph.D."],"votes":109,"pct":11.7},{"id":9,"name":["prof. Ing.","Jiří","Drahoš","DrSc., dr. h. c."],"votes":270,"pct":28.97}]},"round2":{"votes":987,"voters":1339,"attended":989,"candidates":[{"id":7,"name":["Ing.","Miloš","Zeman",""],"votes":401,"pct":40.63},{"id":9,"name":["prof. Ing.","Jiří","Drahoš","DrSc., dr. h. c."],"votes":586,"pct":59.37}]},"winner":[]},{"year":2013,"round1":{"votes":949,"voters":1309,"attended":951,"candidates":[{"id":1,"name":["MUDr.","Zuzana","Roithová","MBA"],"votes":45,"pct":4.74},{"id":2,"name":["Ing.","Jan","Fischer","CSc."],"votes":137,"pct":14.44},{"id":3,"name":["Ing.","Jana","Bobošíková",""],"votes":29,"pct":3.06},{"id":4,"name":["","Taťana","Fischerová",""],"votes":47,"pct":4.95},{"id":5,"name":["MUDr.","Přemysl","Sobotka",""],"votes":38,"pct":4},{"id":6,"name":["Ing.","Miloš","Zeman",""],"votes":189,"pct":19.92},{"id":7,"name":["Prof. JUDr.","Vladimír","Franz",""],"votes":73,"pct":7.69},{"id":8,"name":["","Jiří","Dienstbier",""],"votes":135,"pct":14.23},{"id":9,"name":["","Karel","Schwarzenberg",""],"votes":256,"pct":26.98}]},"round2":{"votes":868,"voters":1303,"attended":871,"candidates":[{"id":6,"name":["Ing.","Miloš","Zeman",""],"votes":432,"pct":49.77},{"id":9,"name":["","Karel","Schwarzenberg",""],"votes":436,"pct":50.23}]}}],"snemovna":[{"year":2017,"stats":{"voters":1340,"pct":70.37},"result":[{"id":1,"votes":108,"pct":11.5,"reg":53,"name":"Občanská demokratická strana"},{"id":2,"votes":4,"pct":0.42,"reg":769,"name":"Řád národa - Vlastenecká unie"},{"id":3,"votes":1,"pct":0.1,"reg":1177,"name":"CESTA ODPOVĚDNÉ SPOLEČNOSTI"},{"id":4,"votes":47,"pct":5,"reg":7,"name":"Česká strana sociálně demokratická"},{"id":7,"votes":184,"pct":19.59,"reg":166,"name":"STAROSTOVÉ A NEZÁVISLÍ"},{"id":8,"votes":49,"pct":5.21,"reg":47,"name":"Komunistická strana Čech a Moravy"},{"id":9,"votes":12,"pct":1.27,"reg":5,"name":"Strana zelených"},{"id":10,"votes":9,"pct":0.95,"reg":137,"name":"ROZUMNÍ - stop migraci a diktátu EU - peníze naim občanům, důchodcům, dětem, zdravotně postieným..."},{"id":12,"votes":9,"pct":0.95,"reg":714,"name":"Strana svobodných občanů"},{"id":14,"votes":1,"pct":0.1,"reg":1173,"name":"Občanská demokratická aliance"},{"id":15,"votes":113,"pct":12.03,"reg":720,"name":"Česká pirátská strana"},{"id":19,"votes":2,"pct":0.21,"reg":1178,"name":"Referendum o Evropské unii"},{"id":20,"votes":62,"pct":6.6,"reg":721,"name":"TOP 09"},{"id":21,"votes":207,"pct":22.04,"reg":768,"name":"ANO 2011"},{"id":23,"votes":3,"pct":0.31,"reg":1125,"name":"Sdruení pro republiku - Republikánská strana Československa Miroslava Sládka"},{"id":24,"votes":30,"pct":3.19,"reg":1,"name":"Křesanská a demokratická unie - Československá strana lidová"},{"id":26,"votes":8,"pct":0.85,"reg":1176,"name":"REALISTÉ"},{"id":27,"votes":2,"pct":0.21,"reg":1182,"name":"SPORTOVCI"},{"id":28,"votes":2,"pct":0.21,"reg":156,"name":"Dělnická strana sociální spravedlnosti"},{"id":29,"votes":79,"pct":8.41,"reg":1114,"name":"Svoboda a přímá demokracie - Tomio Okamura (SPD)"},{"id":30,"votes":7,"pct":0.74,"reg":724,"name":"Strana Práv Občanů"}]},{"year":2006,"stats":{"voters":1252,"pct":72.84},"result":[{"id":1,"votes":13,"pct":1.43,"reg":137,"name":"ROZUMNÍ"},{"id":3,"votes":1,"pct":0.11,"reg":140,"name":"Balbínova poetická strana"},{"id":6,"votes":2,"pct":0.22,"reg":88,"name":"NEZÁVISLÍ"},{"id":9,"votes":404,"pct":44.44,"reg":53,"name":"Občanská demokratická strana"},{"id":10,"votes":219,"pct":24.09,"reg":7,"name":"Česká strana sociálně demokratická"},{"id":11,"votes":31,"pct":3.41,"reg":129,"name":"SNK Evropští demokraté"},{"id":12,"votes":12,"pct":1.32,"reg":102,"name":"Unie svobody - Demokratická unie"},{"id":14,"votes":4,"pct":0.44,"reg":98,"name":"Volte Pravý Blok-stranu za ODVOLAT.polit.,NÍZKÉ daně,VYROVN.rozp.,MIN.byrokr.,SPRAV.just.,PŘÍMOU demokr. WWW.CIBULKA.NET"},{"id":18,"votes":65,"pct":7.15,"reg":5,"name":"Strana zelených"},{"id":20,"votes":66,"pct":7.26,"reg":47,"name":"Komunistická strana Čech a Moravy"},{"id":21,"votes":1,"pct":0.11,"reg":338,"name":"Koalice pro Českou republiku"},{"id":22,"votes":4,"pct":0.44,"reg":152,"name":"Národní strana"},{"id":24,"votes":61,"pct":6.71,"reg":1,"name":"Křesťanská a demokratická unie - Československá strana lidová"},{"id":25,"votes":20,"pct":2.2,"reg":172,"name":"NEZÁVISLÍ DEMOKRATÉ"},{"id":26,"votes":6,"pct":0.66,"reg":171,"name":"STRANA ROVNOST ŠANCÍ"}]},{"year":2010,"stats":{"voters":1270,"pct":69.53},"result":[{"id":4,"votes":115,"pct":13.09,"reg":144,"name":"Věci veřejné"},{"id":5,"votes":4,"pct":0.45,"reg":24,"name":"Konzervativní strana"},{"id":6,"votes":50,"pct":5.69,"reg":47,"name":"Komunistická strana Čech a Moravy"},{"id":9,"votes":134,"pct":15.26,"reg":7,"name":"Česká strana sociálně demokratická"},{"id":11,"votes":5,"pct":0.56,"reg":11,"name":"Sdružení pro republiku-Republikánská strana Československa"},{"id":13,"votes":37,"pct":4.21,"reg":724,"name":"Strana Práv Občanů ZEMANOVCI"},{"id":15,"votes":211,"pct":24.03,"reg":721,"name":"TOP 09"},{"id":17,"votes":18,"pct":2.05,"reg":1,"name":"Křesťanská a demokratická unie - Československá strana lidová"},{"id":18,"votes":4,"pct":0.45,"reg":98,"name":"Volte Pravý Blok-stranu za ODVOLAT.polit.,NÍZKÉ daně,VYROVN.rozp.,MIN.byrokr.,SPRAV.just.,PŘÍMOU demokr. WWW.CIBULKA.NET"},{"id":20,"votes":31,"pct":3.53,"reg":5,"name":"Strana zelených"},{"id":21,"votes":21,"pct":2.39,"reg":137,"name":"ROZUMNÍ"},{"id":23,"votes":7,"pct":0.79,"reg":720,"name":"Česká pirátská strana"},{"id":24,"votes":9,"pct":1.02,"reg":156,"name":"Dělnická strana sociální spravedlnosti"},{"id":25,"votes":14,"pct":1.59,"reg":714,"name":"Svobodní"},{"id":26,"votes":218,"pct":24.82,"reg":53,"name":"Občanská demokratická strana"}]},{"year":2013,"stats":{"voters":1330,"pct":69.7},"result":[{"id":1,"votes":147,"pct":15.96,"reg":7,"name":"Česká strana sociálně demokratická"},{"id":2,"votes":27,"pct":2.93,"reg":714,"name":"Svobodní"},{"id":3,"votes":32,"pct":3.47,"reg":720,"name":"Česká pirátská strana"},{"id":4,"votes":189,"pct":20.52,"reg":721,"name":"TOP 09"},{"id":5,"votes":1,"pct":0.1,"reg":192,"name":"HLAVU VZHŮRU - volební blok"},{"id":6,"votes":73,"pct":7.92,"reg":53,"name":"Občanská demokratická strana"},{"id":9,"votes":13,"pct":1.41,"reg":771,"name":"politické hnutí Změna"},{"id":10,"votes":10,"pct":1.08,"reg":716,"name":"Strana soukromníků České republiky"},{"id":11,"votes":28,"pct":3.04,"reg":1,"name":"Křesťanská a demokratická unie - Československá strana lidová"},{"id":13,"votes":10,"pct":1.08,"reg":137,"name":"ROZUMNÍ"},{"id":15,"votes":5,"pct":0.54,"reg":724,"name":"Strana Práv Občanů ZEMANOVCI"},{"id":17,"votes":81,"pct":8.79,"reg":792,"name":"Úsvit - Národní Koalice"},{"id":18,"votes":6,"pct":0.65,"reg":156,"name":"Dělnická strana sociální spravedlnosti"},{"id":20,"votes":183,"pct":19.86,"reg":768,"name":"ANO 2011"},{"id":21,"votes":98,"pct":10.64,"reg":47,"name":"Komunistická strana Čech a Moravy"},{"id":23,"votes":18,"pct":1.95,"reg":5,"name":"Strana zelených"}]}],"senat":[{"date":20121012,"regular":true,"winner":{"id":8,"reg":38,"name":["PhDr.","Jaromír","Jermář",""],"age":56,"work":"senátor","from":"Klášter Hradiště nad Jizerou","fromID":536024,"member":7,"nomimee":7,"stats":{"round1":{"votes":13100,"pct":32.23},"round2":{"votes":17916,"pct":60.11}}}},{"date":20181005,"regular":true,"winner":{"id":2,"reg":38,"name":["MUDr.","Raduan","Nwelati",""],"age":52,"work":"primátor Mladé Boleslavi, lékař ortoped","from":"Mladá Boleslav","fromID":535419,"member":53,"nomimee":53,"stats":{"round1":{"votes":16317,"pct":33.86},"round2":{"votes":11504,"pct":61.96}}}}],"kraje":[{"year":2016,"stats":{"voters":1340,"pct":41.19},"result":[{"id":2,"votes":39,"pct":7.06,"reg":53,"name":"Občanská demokratická strana"},{"id":3,"votes":10,"pct":1.81,"reg":1149,"name":"Budoucnost pro Liberecký kraj"},{"id":10,"votes":1,"pct":0.18,"reg":1168,"name":"Koalice Republikánů Miroslava Sládka, Patriotů České republiky, HOZK a Nového směru"},{"id":12,"votes":37,"pct":6.7,"reg":7,"name":"Česká strana sociálně demokratická"},{"id":30,"votes":81,"pct":14.67,"reg":768,"name":"ANO 2011"},{"id":32,"votes":35,"pct":6.34,"reg":721,"name":"TOP 09"},{"id":37,"votes":37,"pct":6.7,"reg":47,"name":"Komunistická strana Čech a Moravy"},{"id":43,"votes":19,"pct":3.44,"reg":1102,"name":"Úsvit s Blokem proti islamizaci"},{"id":52,"votes":10,"pct":1.81,"reg":1141,"name":"Svobodní a Soukromníci"},{"id":66,"votes":14,"pct":2.53,"reg":584,"name":"ZMĚNA PRO LIBERECKÝ KRAJ"},{"id":67,"votes":2,"pct":0.36,"reg":1137,"name":"NE ILEGÁLNÍ IMIGRACI - PENÍZE RADĚJI PRO NAŠE LIDI"},{"id":78,"votes":17,"pct":3.07,"reg":1138,"name":"Koalice Svoboda a přímá demokracie - Tomio Okamura (SPD) a Strana Práv Občanů"},{"id":82,"votes":19,"pct":3.44,"reg":720,"name":"Česká pirátská strana"},{"id":83,"votes":230,"pct":41.66,"reg":703,"name":"Starostové pro Liberecký kraj"},{"id":84,"votes":1,"pct":0.18,"reg":764,"name":"Národní socialisté - LEV21"}]},{"year":2008,"stats":{"voters":1260,"pct":44.05},"result":[{"id":1,"votes":41,"pct":7.42,"reg":47,"name":"Komunistická strana Čech a Moravy"},{"id":15,"votes":84,"pct":15.21,"reg":703,"name":"Starostové pro Liberecký kraj"},{"id":18,"votes":25,"pct":4.52,"reg":5,"name":"Strana zelených"},{"id":22,"votes":3,"pct":0.54,"reg":626,"name":"NľRODNÖ SOCIALIST A ROZUMNÖ"},{"id":29,"votes":21,"pct":3.8,"reg":627,"name":"Koalice pro Libereckě kraj"},{"id":30,"votes":16,"pct":2.89,"reg":103,"name":"Strana pro otevřenou společnost"},{"id":33,"votes":1,"pct":0.18,"reg":11,"name":"Sdružení pro republiku-Republikánská strana Československa"},{"id":42,"votes":8,"pct":1.44,"reg":98,"name":"Volte Pravý Blok-stranu za ODVOLAT.polit.,NÍZKÉ daně,VYROVN.rozp.,MIN.byrokr.,SPRAV.just.,PŘÍMOU demokr. WWW.CIBULKA.NET"},{"id":47,"votes":193,"pct":34.96,"reg":53,"name":"Občanská demokratická strana"},{"id":48,"votes":128,"pct":23.18,"reg":7,"name":"Česká strana sociálně demokratická"},{"id":53,"votes":5,"pct":0.9,"reg":632,"name":"Koalice DS a DSSS"},{"id":57,"votes":27,"pct":4.89,"reg":119,"name":"Unie pro sport a zdraví"}]},{"year":2012,"stats":{"voters":1309,"pct":40.11},"result":[{"id":7,"votes":6,"pct":1.19,"reg":98,"name":"Volte Pravý Blok-stranu za ODVOLAT.polit.,NÍZKÉ daně,VYROVN.rozp.,MIN.byrokr.,SPRAV.just.,PŘÍMOU demokr. WWW.CIBULKA.NET"},{"id":8,"votes":12,"pct":2.39,"reg":724,"name":"Strana Práv Občanů ZEMANOVCI"},{"id":12,"votes":8,"pct":1.59,"reg":585,"name":"Koalice KDU-ČSL a Soukromníci"},{"id":14,"votes":7,"pct":1.39,"reg":103,"name":"Strana pro otevřenou společnost"},{"id":22,"votes":4,"pct":0.79,"reg":764,"name":"Národní socialisté"},{"id":23,"votes":121,"pct":24.15,"reg":703,"name":"Starostové pro Liberecký kraj"},{"id":43,"votes":62,"pct":12.37,"reg":47,"name":"Komunistická strana Čech a Moravy"},{"id":49,"votes":7,"pct":1.39,"reg":586,"name":"Koalice KONS a ČS"},{"id":53,"votes":3,"pct":0.59,"reg":600,"name":"Dělnická strana sociální spravedlnosti - Imigranty a islám v ČR nechceme!"},{"id":60,"votes":83,"pct":16.56,"reg":7,"name":"Česká strana sociálně demokratická"},{"id":62,"votes":44,"pct":8.78,"reg":659,"name":"Koalice STAN, TOP 09"},{"id":69,"votes":40,"pct":7.98,"reg":584,"name":"Koalice Zelení a Změna"},{"id":70,"votes":67,"pct":13.37,"reg":53,"name":"Občanská demokratická strana"},{"id":72,"votes":10,"pct":1.99,"reg":783,"name":"Česká strana selského rozumu"},{"id":77,"votes":6,"pct":1.19,"reg":714,"name":"Svobodní"},{"id":85,"votes":5,"pct":0.99,"reg":129,"name":"SNK Evropští demokraté"},{"id":90,"votes":4,"pct":0.79,"reg":780,"name":"Nová budoucnost pro Liberecký kraj"},{"id":93,"votes":12,"pct":2.39,"reg":720,"name":"Česká pirátská strana"}]}],"obce":[{"year":2018,"stats":{"voters":1349,"pct":45.07},"parts":[{"stats":{"voters":1349,"pct":45.07},"results":[{"id":1,"votes":6112,"pct":100,"reg":90,"name":"Sdružení nezávislých kandidátů obce Mírová pod Kozákovem","list":[{"id":1,"name":["","Jaroslav","Votrubec",""]},{"id":2,"name":["","Vlastimil","Kůtek",""]},{"id":3,"name":["","Eliška","Matoušová",""]},{"id":4,"name":["","Bohuslav","Kadlec",""]},{"id":5,"name":["","Jiří","Hejduk",""]},{"id":6,"name":["Ing.","Pavel","Doubek","Ph.D."]},{"id":7,"name":["","Miloslav","Mlejnek",""]},{"id":8,"name":["Ing.","Jaroslav","Vodháněl",""]},{"id":9,"name":["","Tomáš","Vodháněl",""]},{"id":10,"name":["","Vladimír","Karásek",""]},{"id":11,"name":["Ing.","František","Hejduk",""]},{"id":12,"name":["Ing.","Richard","Müller",""]},{"id":13,"name":["Ing.","Jiří","Červa",""]},{"id":14,"name":["","Eduard","Marek",""]},{"id":15,"name":["","Zuzana","Valešová",""]}]}]}]},{"year":2006,"parts":[{"stats":{"voters":1245,"pct":54.78},"results":[{"id":1,"votes":165,"pct":2.21,"reg":80,"name":"Tomáš Votrubec"},{"id":2,"votes":206,"pct":2.76,"reg":80,"name":"Ing. František HEJDUK"},{"id":3,"votes":7097,"pct":95.03,"reg":90,"name":"\"Sdružení nezávislých kandidátů obce Mírová pod Kozákovem\"","list":[{"id":1,"name":["","Jaroslav","Havlíček",""]},{"id":2,"name":["","Bohuslav","Kadlec",""]},{"id":3,"name":["","Vlastimil","Kůtek",""]},{"id":4,"name":["","Oldřich","Staněk",""]},{"id":5,"name":["","Bohumil","Zikmund",""]},{"id":6,"name":["Ing.","Jaroslav","Vodháněl",""]},{"id":7,"name":["","Vladimír","Pleštil",""]},{"id":8,"name":["","Jaroslav","Votrubec",""]},{"id":9,"name":["","Josef","Pícha",""]},{"id":10,"name":["","Stanislava","Svobodová",""]},{"id":11,"name":["Ing.","Pavel","Doubek","Ph. D"]},{"id":12,"name":["","Alena","Hejduková",""]},{"id":13,"name":["","Eliška","Matoušová",""]},{"id":14,"name":["","Miloslav","Mlejnek",""]},{"id":15,"name":["","Miroslav","Vosmík",""]}]}]}]},{"year":2010,"parts":[{"stats":{"voters":1280,"pct":41.09},"results":[{"id":1,"votes":5031,"pct":100,"reg":90,"name":"Sdružení nezávislých kandidátů Obce Mírová pod Kozákovem","list":[{"id":2,"name":["","Jaroslav","Havlíček",""]},{"id":1,"name":["","Jaroslav","Votrubec",""]},{"id":3,"name":["","Eliška","Matoušová",""]},{"id":4,"name":["","Bohuslav","Kadlec",""]},{"id":5,"name":["","Vlastimil","Kůtek",""]},{"id":6,"name":["Ing.","Pavel","Doubek","Ph.D."]},{"id":7,"name":["","Miloslav","Mlejnek",""]},{"id":8,"name":["Ing.","Jaroslav","Vodháněl",""]},{"id":9,"name":["","Jiří","Hejduk",""]},{"id":10,"name":["","Tomáš","Vodháněl",""]},{"id":11,"name":["","Aleš","Vele",""]},{"id":12,"name":["","Vladimír","Karásek",""]},{"id":13,"name":["Ing.","František","Hejduk",""]},{"id":14,"name":["Ing.","Richard","Müller",""]},{"id":15,"name":["RNDr.","Miroslav","Pivrnec",""]}]}]}]},{"year":2014,"parts":[{"stats":{"voters":1305,"pct":32.95},"results":[{"id":1,"votes":4342,"pct":100,"reg":90,"name":"Sdružení nezávislých kandidátů Obce Mírová pod Kozákovem","list":[{"id":1,"name":["","Jaroslav","Votrubec",""]},{"id":2,"name":["","Jaroslav","Havlíček",""]},{"id":3,"name":["","Eliška","Matoušová",""]},{"id":4,"name":["","Bohuslav","Kadlec",""]},{"id":5,"name":["","Vlastimil","Kůtek",""]},{"id":6,"name":["Ing.","Pavel","Doubek","Ph.D."]},{"id":7,"name":["Ing.","Richard","Müller",""]},{"id":8,"name":["Ing.","Jaroslav","Vodháněl",""]},{"id":9,"name":["","Jiří","Hejduk",""]},{"id":10,"name":["","Tomáš","Vodháněl",""]},{"id":11,"name":["","Aleš","Vele",""]},{"id":12,"name":["","Vladimír","Karásek",""]},{"id":13,"name":["Ing.","František","Hejduk",""]},{"id":14,"name":["","Miloslav","Mlejnek",""]},{"id":15,"name":["","Jiří","Červa",""]}]}]}]}],"eu":[{"year":2019,"stats":{"voters":1346,"pct":38.93},"result":[{"id":2,"votes":6,"pct":1.15,"reg":1178,"name":"Strana nezávislosti České republiky"},{"id":3,"votes":1,"pct":0.19,"reg":1177,"name":"CESTA ODPOVĚDNÉ SPOLEČNOSTI"},{"id":4,"votes":1,"pct":0.19,"reg":764,"name":"Národní socialisté"},{"id":5,"votes":86,"pct":16.44,"reg":53,"name":"Občanská demokratická strana"},{"id":6,"votes":8,"pct":1.53,"reg":1206,"name":"ANO, vytrollíme europarlament"},{"id":7,"votes":17,"pct":3.25,"reg":7,"name":"Česká strana sociálně demokratická"},{"id":9,"votes":19,"pct":3.63,"reg":47,"name":"Komunistická strana Čech a Moravy"},{"id":12,"votes":7,"pct":1.34,"reg":1438,"name":"Koalice ND a Rozumní"},{"id":13,"votes":3,"pct":0.57,"reg":98,"name":"Volte Pravý Blok-stranu za ODVOLAT.polit.,NÍZKÉ daně,VYROVN.rozp.,MIN.byrokr.,SPRAV.just.,PŘÍMOU demokr. WWW.CIBULKA.NET"},{"id":15,"votes":1,"pct":0.19,"reg":1222,"name":"Pro Česko"},{"id":16,"votes":2,"pct":0.38,"reg":1200,"name":"Vědci pro Českou republiku"},{"id":24,"votes":13,"pct":2.49,"reg":1220,"name":"HLAS"},{"id":25,"votes":4,"pct":0.76,"reg":1440,"name":"Koalice Svobodní a RČ"},{"id":26,"votes":102,"pct":19.5,"reg":659,"name":"Koalice STAN, TOP 09"},{"id":27,"votes":100,"pct":19.12,"reg":720,"name":"Česká pirátská strana"},{"id":28,"votes":47,"pct":8.99,"reg":1114,"name":"Svoboda a přímá demokracie - Tomio Okamura (SPD)"},{"id":29,"votes":1,"pct":0.19,"reg":762,"name":"ALIANCE NÁRODNÍCH SIL"},{"id":30,"votes":66,"pct":12.62,"reg":768,"name":"ANO 2011"},{"id":34,"votes":2,"pct":0.38,"reg":715,"name":"Demokratická strana zelených - ZA PRÁVA ZVÍŘAT"},{"id":35,"votes":1,"pct":0.19,"reg":1179,"name":"BEZPEČNOST, ODPOVĚDNOST, SOLIDARITA"},{"id":36,"votes":4,"pct":0.76,"reg":1390,"name":"Koalice NEZ a Soukromníci"},{"id":37,"votes":5,"pct":0.96,"reg":1219,"name":"Evropa společně"},{"id":39,"votes":25,"pct":4.78,"reg":1,"name":"Křesťanská a demokratická unie - Československá strana lidová"},{"id":40,"votes":2,"pct":0.38,"reg":1052,"name":"Alternativa pro Českou republiku 2017"}]},{"year":2014,"stats":{"voters":1315,"pct":20.3},"result":[{"id":1,"votes":1,"pct":0.38,"reg":129,"name":"SNK Evropští demokraté"},{"id":2,"votes":1,"pct":0.38,"reg":576,"name":"Koalice SSPD-SP a NO!"},{"id":4,"votes":2,"pct":0.76,"reg":79,"name":"Národní demokracie"},{"id":5,"votes":13,"pct":4.94,"reg":1,"name":"Křesťanská a demokratická unie - Československá strana lidová"},{"id":6,"votes":14,"pct":5.32,"reg":137,"name":"ROZUMNÍ"},{"id":7,"votes":67,"pct":25.48,"reg":659,"name":"Koalice STAN, TOP 09"},{"id":10,"votes":17,"pct":6.46,"reg":47,"name":"Komunistická strana Čech a Moravy"},{"id":14,"votes":27,"pct":10.27,"reg":7,"name":"Česká strana sociálně demokratická"},{"id":16,"votes":52,"pct":19.77,"reg":768,"name":"ANO 2011"},{"id":19,"votes":1,"pct":0.38,"reg":756,"name":"Česká strana regionů"},{"id":20,"votes":27,"pct":10.27,"reg":53,"name":"Občanská demokratická strana"},{"id":22,"votes":8,"pct":3.04,"reg":792,"name":"Úsvit - Národní Koalice"},{"id":23,"votes":3,"pct":1.14,"reg":5,"name":"Strana zelených"},{"id":24,"votes":11,"pct":4.18,"reg":714,"name":"Svobodní"},{"id":26,"votes":1,"pct":0.38,"reg":93,"name":"Komunistická strana Československa"},{"id":27,"votes":4,"pct":1.52,"reg":98,"name":"Volte Pravý Blok-stranu za ODVOLAT.polit.,NÍZKÉ daně,VYROVN.rozp.,MIN.byrokr.,SPRAV.just.,PŘÍMOU demokr. WWW.CIBULKA.NET"},{"id":28,"votes":1,"pct":0.38,"reg":1001,"name":"ANTIBURSÍK - STOP EKOTERORU !"},{"id":29,"votes":1,"pct":0.38,"reg":575,"name":"Dělnická strana sociální spravedlnosti - NE diktátu Bruselu"},{"id":32,"votes":9,"pct":3.42,"reg":720,"name":"Česká pirátská strana"},{"id":36,"votes":1,"pct":0.38,"reg":2,"name":"Česká strana národně sociální"},{"id":38,"votes":2,"pct":0.76,"reg":144,"name":"Věci veřejné"}]},{"year":2004,"stats":{"voters":1162,"pct":33.91},"result":[{"id":1,"votes":70,"pct":17.81,"reg":311,"name":"Koalice SNK ED a SD-SN"},{"id":2,"votes":1,"pct":0.25,"reg":55,"name":"Koruna Česká (monarchistická strana Čech, Moravy a Slezska)"},{"id":4,"votes":31,"pct":7.89,"reg":7,"name":"Česká strana sociálně demokratická"},{"id":5,"votes":1,"pct":0.25,"reg":310,"name":"Národní koalice"},{"id":6,"votes":159,"pct":40.46,"reg":53,"name":"Občanská demokratická strana"},{"id":7,"votes":3,"pct":0.76,"reg":103,"name":"Strana pro otevřenou společnost"},{"id":9,"votes":5,"pct":1.27,"reg":5,"name":"Strana zelených"},{"id":11,"votes":1,"pct":0.25,"reg":24,"name":"Konzervativní strana"},{"id":12,"votes":1,"pct":0.25,"reg":158,"name":"Starostové a osobnosti pro Moravu"},{"id":14,"votes":1,"pct":0.25,"reg":68,"name":"Masarykova demokratická strana"},{"id":17,"votes":1,"pct":0.25,"reg":159,"name":"Strana státu přímé demokracie - Strana práce"},{"id":18,"votes":1,"pct":0.25,"reg":140,"name":"Balbínova poetická strana"},{"id":20,"votes":20,"pct":5.09,"reg":1,"name":"Křesťanská a demokratická unie - Československá strana lidová"},{"id":21,"votes":5,"pct":1.27,"reg":98,"name":"Volte Pravý Blok-stranu za ODVOLAT.polit.,NÍZKÉ daně,VYROVN.rozp.,MIN.byrokr.,SPRAV.just.,PŘÍMOU demokr. WWW.CIBULKA.NET"},{"id":23,"votes":6,"pct":1.53,"reg":313,"name":"Unie liberálních demokratů"},{"id":24,"votes":47,"pct":11.96,"reg":47,"name":"Komunistická strana Čech a Moravy"},{"id":25,"votes":6,"pct":1.53,"reg":101,"name":"Strana venkova - spojené občanské síly"},{"id":26,"votes":2,"pct":0.51,"reg":20,"name":"Strana za životní jistoty"},{"id":28,"votes":1,"pct":0.25,"reg":9,"name":"Nezávislá iniciativa (NEI)"},{"id":30,"votes":1,"pct":0.25,"reg":160,"name":"\"Viktor Kožený - Občanská federální demokracie\""},{"id":31,"votes":4,"pct":1.02,"reg":127,"name":"Republikáni Miroslava Sládka"},{"id":32,"votes":26,"pct":6.62,"reg":88,"name":"NEZÁVISLÍ"}]},{"year":2009,"stats":{"voters":1267,"pct":34.81},"result":[{"id":1,"votes":3,"pct":0.68,"reg":713,"name":"Libertas.cz"},{"id":2,"votes":12,"pct":2.73,"reg":1,"name":"Křesťanská a demokratická unie - Československá strana lidová"},{"id":3,"votes":14,"pct":3.18,"reg":144,"name":"Věci veřejné"},{"id":4,"votes":185,"pct":42.05,"reg":53,"name":"Občanská demokratická strana"},{"id":5,"votes":16,"pct":3.64,"reg":654,"name":"Koalice Rozumní a HLAVU VZHŮRU"},{"id":6,"votes":3,"pct":0.68,"reg":98,"name":"Volte Pravý Blok-stranu za ODVOLAT.polit.,NÍZKÉ daně,VYROVN.rozp.,MIN.byrokr.,SPRAV.just.,PŘÍMOU demokr. WWW.CIBULKA.NET"},{"id":7,"votes":1,"pct":0.23,"reg":11,"name":"Sdružení pro republiku-Republikánská strana Československa"},{"id":8,"votes":2,"pct":0.45,"reg":175,"name":"Česká strana národně socialistická"},{"id":9,"votes":9,"pct":2.05,"reg":709,"name":"Evropská demokratická strana"},{"id":10,"votes":2,"pct":0.45,"reg":29,"name":"Strana svobodných demokratů"},{"id":11,"votes":1,"pct":0.23,"reg":715,"name":"Demokratická strana zelených - ZA PRÁVA ZVÍŘAT"},{"id":14,"votes":3,"pct":0.68,"reg":155,"name":"Blok proti islamizaci - Obrana domova"},{"id":16,"votes":2,"pct":0.45,"reg":83,"name":"Moravané"},{"id":18,"votes":1,"pct":0.23,"reg":138,"name":"Liberálové.CZ"},{"id":20,"votes":2,"pct":0.45,"reg":655,"name":"Nejen hasiči a živnostníci s učiteli do Evropy - www.hnpd.cz, www.sdzp.cz"},{"id":21,"votes":34,"pct":7.73,"reg":47,"name":"Komunistická strana Čech a Moravy"},{"id":22,"votes":14,"pct":3.18,"reg":656,"name":"Koalice STAN a ALTERNATIVA"},{"id":23,"votes":13,"pct":2.95,"reg":714,"name":"Svobodní"},{"id":24,"votes":11,"pct":2.5,"reg":129,"name":"SNK Evropští demokraté"},{"id":25,"votes":2,"pct":0.45,"reg":140,"name":"Balbínova poetická strana"},{"id":26,"votes":8,"pct":1.82,"reg":5,"name":"Strana zelených"},{"id":27,"votes":2,"pct":0.45,"reg":55,"name":"Koruna Česká (monarchistická strana Čech, Moravy a Slezska)"},{"id":29,"votes":1,"pct":0.23,"reg":716,"name":"Strana soukromníků České republiky"},{"id":31,"votes":4,"pct":0.91,"reg":153,"name":"Dělnická strana"},{"id":32,"votes":1,"pct":0.23,"reg":88,"name":"NEZÁVISLÍ"},{"id":33,"votes":94,"pct":21.36,"reg":7,"name":"Česká strana sociálně demokratická"}]}]},"obvod":{"id":38,"name":"Mladá Boleslav"},"hierarchy":{"kraj":{"nuts":"CZ051","name":"Liberecký kraj"},"okres":{"nuts":"CZ0514","name":"Semily"},"obvod":{"id":38,"name":"Mladá Boleslav"},"psc":51101,"gps":{"lnt":50.591643,"lng":15.19435}}}