{"id":589497,"name":"Dzbel","nuts":"CZ0713","okres":7103,"kraj":7100,"volby":{"prezident":[{"year":2018,"round1":{"votes":135,"voters":212,"attended":139,"candidates":[{"id":2,"name":["Mgr.","Michal","Horáček","Ph.D."],"votes":4,"pct":2.96},{"id":3,"name":["Mgr.","Pavel","Fischer",""],"votes":16,"pct":11.85},{"id":5,"name":["Mgr.","Petr","Hannig",""],"votes":1,"pct":0.74},{"id":6,"name":["Ing.","Vratislav","Kulhánek","Dr. h. c."],"votes":1,"pct":0.74},{"id":7,"name":["Ing.","Miloš","Zeman",""],"votes":76,"pct":56.3},{"id":8,"name":["MUDr. Bc.","Marek","Hilšer","Ph.D."],"votes":9,"pct":6.67},{"id":9,"name":["prof. Ing.","Jiří","Drahoš","DrSc., dr. h. c."],"votes":28,"pct":20.74}]},"round2":{"votes":155,"voters":210,"attended":155,"candidates":[{"id":7,"name":["Ing.","Miloš","Zeman",""],"votes":109,"pct":70.32},{"id":9,"name":["prof. Ing.","Jiří","Drahoš","DrSc., dr. h. c."],"votes":46,"pct":29.68}]},"winner":[]},{"year":2013,"round1":{"votes":146,"voters":214,"attended":146,"candidates":[{"id":1,"name":["MUDr.","Zuzana","Roithová","MBA"],"votes":18,"pct":12.33},{"id":2,"name":["Ing.","Jan","Fischer","CSc."],"votes":23,"pct":15.75},{"id":3,"name":["Ing.","Jana","Bobošíková",""],"votes":6,"pct":4.11},{"id":4,"name":["","Taťana","Fischerová",""],"votes":1,"pct":0.68},{"id":5,"name":["MUDr.","Přemysl","Sobotka",""],"votes":3,"pct":2.05},{"id":6,"name":["Ing.","Miloš","Zeman",""],"votes":36,"pct":24.66},{"id":7,"name":["Prof. JUDr.","Vladimír","Franz",""],"votes":9,"pct":6.16},{"id":8,"name":["","Jiří","Dienstbier",""],"votes":33,"pct":22.6},{"id":9,"name":["","Karel","Schwarzenberg",""],"votes":17,"pct":11.64}]},"round2":{"votes":134,"voters":213,"attended":135,"candidates":[{"id":6,"name":["Ing.","Miloš","Zeman",""],"votes":92,"pct":68.66},{"id":9,"name":["","Karel","Schwarzenberg",""],"votes":42,"pct":31.34}]}}],"snemovna":[{"year":2017,"stats":{"voters":209,"pct":63.64},"result":[{"id":1,"votes":2,"pct":1.5,"reg":53,"name":"Občanská demokratická strana"},{"id":2,"votes":1,"pct":0.75,"reg":769,"name":"Řád národa - Vlastenecká unie"},{"id":4,"votes":11,"pct":8.27,"reg":7,"name":"Česká strana sociálně demokratická"},{"id":7,"votes":5,"pct":3.75,"reg":166,"name":"STAROSTOVÉ A NEZÁVISLÍ"},{"id":8,"votes":22,"pct":16.54,"reg":47,"name":"Komunistická strana Čech a Moravy"},{"id":10,"votes":1,"pct":0.75,"reg":137,"name":"ROZUMNÍ - stop migraci a diktátu EU - peníze naim občanům, důchodcům, dětem, zdravotně postieným..."},{"id":12,"votes":1,"pct":0.75,"reg":714,"name":"Strana svobodných občanů"},{"id":15,"votes":6,"pct":4.51,"reg":720,"name":"Česká pirátská strana"},{"id":21,"votes":50,"pct":37.59,"reg":768,"name":"ANO 2011"},{"id":24,"votes":24,"pct":18.04,"reg":1,"name":"Křesanská a demokratická unie - Československá strana lidová"},{"id":27,"votes":2,"pct":1.5,"reg":1182,"name":"SPORTOVCI"},{"id":29,"votes":8,"pct":6.01,"reg":1114,"name":"Svoboda a přímá demokracie - Tomio Okamura (SPD)"}]},{"year":2006,"stats":{"voters":232,"pct":67.67},"result":[{"id":1,"votes":1,"pct":0.63,"reg":137,"name":"ROZUMNÍ"},{"id":3,"votes":1,"pct":0.63,"reg":140,"name":"Balbínova poetická strana"},{"id":6,"votes":1,"pct":0.63,"reg":88,"name":"NEZÁVISLÍ"},{"id":9,"votes":17,"pct":10.82,"reg":53,"name":"Občanská demokratická strana"},{"id":10,"votes":83,"pct":52.86,"reg":7,"name":"Česká strana sociálně demokratická"},{"id":14,"votes":1,"pct":0.63,"reg":98,"name":"Volte Pravý Blok-stranu za ODVOLAT.polit.,NÍZKÉ daně,VYROVN.rozp.,MIN.byrokr.,SPRAV.just.,PŘÍMOU demokr. WWW.CIBULKA.NET"},{"id":18,"votes":8,"pct":5.09,"reg":5,"name":"Strana zelených"},{"id":20,"votes":25,"pct":15.92,"reg":47,"name":"Komunistická strana Čech a Moravy"},{"id":24,"votes":20,"pct":12.73,"reg":1,"name":"Křesťanská a demokratická unie - Československá strana lidová"}]},{"year":2010,"stats":{"voters":215,"pct":67.44},"result":[{"id":4,"votes":11,"pct":7.58,"reg":144,"name":"Věci veřejné"},{"id":6,"votes":24,"pct":16.55,"reg":47,"name":"Komunistická strana Čech a Moravy"},{"id":9,"votes":56,"pct":38.62,"reg":7,"name":"Česká strana sociálně demokratická"},{"id":12,"votes":5,"pct":3.44,"reg":83,"name":"Moravané"},{"id":13,"votes":4,"pct":2.75,"reg":724,"name":"Strana Práv Občanů ZEMANOVCI"},{"id":15,"votes":11,"pct":7.58,"reg":721,"name":"TOP 09"},{"id":17,"votes":22,"pct":15.17,"reg":1,"name":"Křesťanská a demokratická unie - Československá strana lidová"},{"id":20,"votes":1,"pct":0.68,"reg":5,"name":"Strana zelených"},{"id":21,"votes":1,"pct":0.68,"reg":137,"name":"ROZUMNÍ"},{"id":23,"votes":1,"pct":0.68,"reg":720,"name":"Česká pirátská strana"},{"id":26,"votes":9,"pct":6.2,"reg":53,"name":"Občanská demokratická strana"}]},{"year":2013,"stats":{"voters":215,"pct":64.65},"result":[{"id":1,"votes":35,"pct":25.17,"reg":7,"name":"Česká strana sociálně demokratická"},{"id":3,"votes":4,"pct":2.87,"reg":720,"name":"Česká pirátská strana"},{"id":4,"votes":6,"pct":4.31,"reg":721,"name":"TOP 09"},{"id":6,"votes":3,"pct":2.15,"reg":53,"name":"Občanská demokratická strana"},{"id":11,"votes":25,"pct":17.98,"reg":1,"name":"Křesťanská a demokratická unie - Československá strana lidová"},{"id":15,"votes":4,"pct":2.87,"reg":724,"name":"Strana Práv Občanů ZEMANOVCI"},{"id":17,"votes":10,"pct":7.19,"reg":792,"name":"Úsvit - Národní Koalice"},{"id":20,"votes":22,"pct":15.82,"reg":768,"name":"ANO 2011"},{"id":21,"votes":28,"pct":20.14,"reg":47,"name":"Komunistická strana Čech a Moravy"},{"id":23,"votes":2,"pct":1.43,"reg":5,"name":"Strana zelených"}]}],"senat":[{"date":20121012,"regular":true,"winner":{"id":1,"reg":62,"name":["","Božena","Sekaninová",""],"age":55,"work":"senátorka","from":"Prostějov","fromID":589250,"member":7,"nomimee":7,"stats":{"round1":{"votes":14184,"pct":42.65},"round2":{"votes":12313,"pct":73.3}}}},{"date":20181005,"regular":true,"winner":{"id":2,"reg":62,"name":["MUDr.","Jitka","Chalánková",""],"age":61,"work":"dětská lékařka","from":"Prostějov","fromID":589250,"member":99,"nomimee":80,"stats":{"round1":{"votes":5370,"pct":12.68},"round2":{"votes":8472,"pct":59.85}}}}],"kraje":[{"year":2016,"stats":{"voters":208,"pct":33.65},"result":[{"id":6,"votes":1,"pct":1.44,"reg":1060,"name":"Piráti + Změna + ProRegion -> Kraj nové generace"},{"id":12,"votes":15,"pct":21.73,"reg":7,"name":"Česká strana sociálně demokratická"},{"id":26,"votes":3,"pct":4.34,"reg":55,"name":"Koruna Česká (monarchistická strana Čech, Moravy a Slezska)"},{"id":30,"votes":13,"pct":18.84,"reg":768,"name":"ANO 2011"},{"id":37,"votes":13,"pct":18.84,"reg":47,"name":"Komunistická strana Čech a Moravy"},{"id":42,"votes":6,"pct":8.69,"reg":1146,"name":"Starostové ProOlomoucký kraj"},{"id":74,"votes":15,"pct":21.73,"reg":303,"name":"Koalice pro Olomoucký kraj společně se starosty"},{"id":75,"votes":1,"pct":1.44,"reg":600,"name":"Dělnická strana sociální spravedlnosti - Imigranty a islám v ČR nechceme!"},{"id":78,"votes":2,"pct":2.89,"reg":1138,"name":"Koalice Svoboda a přímá demokracie - Tomio Okamura (SPD) a Strana Práv Občanů"}]},{"year":2008,"stats":{"voters":219,"pct":42.47},"result":[{"id":1,"votes":14,"pct":15.21,"reg":47,"name":"Komunistická strana Čech a Moravy"},{"id":2,"votes":3,"pct":3.26,"reg":639,"name":"Šance pro náš kraj"},{"id":12,"votes":11,"pct":11.95,"reg":1,"name":"Křesťanská a demokratická unie - Československá strana lidová"},{"id":18,"votes":1,"pct":1.08,"reg":5,"name":"Strana zelených"},{"id":19,"votes":3,"pct":3.26,"reg":83,"name":"Moravané"},{"id":32,"votes":1,"pct":1.08,"reg":137,"name":"ROZUMNÍ"},{"id":47,"votes":5,"pct":5.43,"reg":53,"name":"Občanská demokratická strana"},{"id":48,"votes":53,"pct":57.6,"reg":7,"name":"Česká strana sociálně demokratická"},{"id":53,"votes":1,"pct":1.08,"reg":632,"name":"Koalice DS a DSSS"}]},{"year":2012,"stats":{"voters":215,"pct":43.72},"result":[{"id":5,"votes":2,"pct":2.4,"reg":55,"name":"Koruna Česká (monarchistická strana Čech, Moravy a Slezska)"},{"id":8,"votes":1,"pct":1.2,"reg":724,"name":"Strana Práv Občanů ZEMANOVCI"},{"id":16,"votes":1,"pct":1.2,"reg":716,"name":"Strana soukromníků České republiky"},{"id":20,"votes":3,"pct":3.61,"reg":83,"name":"Moravané"},{"id":26,"votes":2,"pct":2.4,"reg":88,"name":"NEZÁVISLÍ"},{"id":42,"votes":5,"pct":6.02,"reg":659,"name":"Koalice STAN, TOP 09"},{"id":43,"votes":26,"pct":31.32,"reg":47,"name":"Komunistická strana Čech a Moravy"},{"id":60,"votes":24,"pct":28.91,"reg":7,"name":"Česká strana sociálně demokratická"},{"id":70,"votes":1,"pct":1.2,"reg":53,"name":"Občanská demokratická strana"},{"id":77,"votes":2,"pct":2.4,"reg":714,"name":"Svobodní"},{"id":87,"votes":15,"pct":18.07,"reg":303,"name":"Koalice KDU-ČSL a Zelení"},{"id":93,"votes":1,"pct":1.2,"reg":720,"name":"Česká pirátská strana"}]}],"obce":[{"year":2018,"stats":{"voters":206,"pct":48.54},"parts":[{"stats":{"voters":206,"pct":48.54},"results":[{"id":1,"votes":391,"pct":100,"reg":90,"name":"Náš venkov","list":[{"id":1,"name":["","Jana","Konečná",""]},{"id":2,"name":["","Jaromír","Zajíček",""]},{"id":3,"name":["","Jiří","Mrnka",""]},{"id":4,"name":["","Pavel","Slezáček",""]},{"id":5,"name":["","Lubomír","Jurníček",""]},{"id":6,"name":["","Petr","Konečný",""]},{"id":7,"name":["","Radek","Navrátil",""]}]}]}]},{"year":2006,"parts":[{"stats":{"voters":232,"pct":68.53},"results":[{"id":1,"votes":373,"pct":35.02,"reg":90,"name":"Sdružení nezávislých kandidátů - Náš venkov","list":[{"id":3,"name":["","Pavel","Slezáček",""]},{"id":1,"name":["","František","Hájek",""]}]},{"id":2,"votes":314,"pct":29.48,"reg":90,"name":"Sdružení nezávislých kandidátů  Pohodový Dzbel","list":[{"id":7,"name":["","Světlana","Navrátilová",""]},{"id":1,"name":["","Jaromír","Zajíček",""]}]},{"id":3,"votes":378,"pct":35.49,"reg":90,"name":"Sdružení nezávislých kandidátů  Za obec krásnější","list":[{"id":1,"name":["","Waldemar","Zatloukal",""]},{"id":5,"name":["","Bohumil","Novák",""]},{"id":2,"name":["","Ladislav","Tichý",""]}]}]}]},{"year":2010,"parts":[{"stats":{"voters":210,"pct":62.86},"results":[{"id":1,"votes":209,"pct":28.47,"reg":90,"name":"Sdružení nezávislých kandidátů - Naše obec Dzbel","list":[{"id":3,"name":["","Lubomír","Jurníček",""]},{"id":1,"name":["","Zdeněk","Konečný",""]}]},{"id":2,"votes":525,"pct":71.53,"reg":90,"name":"Sdružení nezávislých kandidátů  Náš venkov","list":[{"id":7,"name":["","Jana","Konečná",""]},{"id":3,"name":["","František","Hájek",""]},{"id":5,"name":["","Martin","Laštůvka",""]},{"id":1,"name":["","Jiří","Mrnka",""]},{"id":2,"name":["","Pavel","Slezáček",""]}]}]}]},{"year":2014,"parts":[{"stats":{"voters":214,"pct":65.89},"results":[{"id":1,"votes":170,"pct":20.33,"reg":792,"name":"Úsvit přímé demokracie","list":[{"id":1,"name":["","Pavel","Slezáček",""]}]},{"id":2,"votes":666,"pct":79.67,"reg":90,"name":"Náš venkov","list":[{"id":1,"name":["","Jana","Konečná",""]},{"id":5,"name":["Bc.","Martin","Laštůvka",""]},{"id":2,"name":["","Jaromír","Zajíček",""]},{"id":3,"name":["","František","Hájek",""]},{"id":4,"name":["","Zdeněk","Konečný",""]},{"id":6,"name":["","Lubomír","Jurníček",""]}]}]}]}],"eu":[{"year":2019,"stats":{"voters":206,"pct":24.27},"result":[{"id":6,"votes":3,"pct":6,"reg":1206,"name":"ANO, vytrollíme europarlament"},{"id":7,"votes":5,"pct":10,"reg":7,"name":"Česká strana sociálně demokratická"},{"id":9,"votes":4,"pct":8,"reg":47,"name":"Komunistická strana Čech a Moravy"},{"id":26,"votes":4,"pct":8,"reg":659,"name":"Koalice STAN, TOP 09"},{"id":27,"votes":2,"pct":4,"reg":720,"name":"Česká pirátská strana"},{"id":28,"votes":3,"pct":6,"reg":1114,"name":"Svoboda a přímá demokracie - Tomio Okamura (SPD)"},{"id":30,"votes":13,"pct":26,"reg":768,"name":"ANO 2011"},{"id":32,"votes":1,"pct":2,"reg":83,"name":"Moravané"},{"id":39,"votes":14,"pct":28,"reg":1,"name":"Křesťanská a demokratická unie - Československá strana lidová"},{"id":40,"votes":1,"pct":2,"reg":1052,"name":"Alternativa pro Českou republiku 2017"}]},{"year":2014,"stats":{"voters":213,"pct":17.37},"result":[{"id":5,"votes":8,"pct":21.62,"reg":1,"name":"Křesťanská a demokratická unie - Československá strana lidová"},{"id":6,"votes":1,"pct":2.7,"reg":137,"name":"ROZUMNÍ"},{"id":7,"votes":1,"pct":2.7,"reg":659,"name":"Koalice STAN, TOP 09"},{"id":9,"votes":1,"pct":2.7,"reg":764,"name":"Národní socialisté"},{"id":10,"votes":2,"pct":5.41,"reg":47,"name":"Komunistická strana Čech a Moravy"},{"id":14,"votes":7,"pct":18.92,"reg":7,"name":"Česká strana sociálně demokratická"},{"id":16,"votes":9,"pct":24.32,"reg":768,"name":"ANO 2011"},{"id":20,"votes":3,"pct":8.11,"reg":53,"name":"Občanská demokratická strana"},{"id":22,"votes":3,"pct":8.11,"reg":792,"name":"Úsvit - Národní Koalice"},{"id":32,"votes":2,"pct":5.41,"reg":720,"name":"Česká pirátská strana"}]},{"year":2004,"stats":{"voters":243,"pct":20.99},"result":[{"id":1,"votes":4,"pct":8,"reg":311,"name":"Koalice SNK ED a SD-SN"},{"id":4,"votes":3,"pct":6,"reg":7,"name":"Česká strana sociálně demokratická"},{"id":6,"votes":5,"pct":10,"reg":53,"name":"Občanská demokratická strana"},{"id":9,"votes":1,"pct":2,"reg":5,"name":"Strana zelených"},{"id":20,"votes":15,"pct":30,"reg":1,"name":"Křesťanská a demokratická unie - Československá strana lidová"},{"id":23,"votes":2,"pct":4,"reg":313,"name":"Unie liberálních demokratů"},{"id":24,"votes":17,"pct":34,"reg":47,"name":"Komunistická strana Čech a Moravy"},{"id":32,"votes":3,"pct":6,"reg":88,"name":"NEZÁVISLÍ"}]},{"year":2009,"stats":{"voters":221,"pct":27.15},"result":[{"id":2,"votes":9,"pct":15,"reg":1,"name":"Křesťanská a demokratická unie - Československá strana lidová"},{"id":4,"votes":6,"pct":10,"reg":53,"name":"Občanská demokratická strana"},{"id":5,"votes":2,"pct":3.33,"reg":654,"name":"Koalice Rozumní a HLAVU VZHŮRU"},{"id":6,"votes":1,"pct":1.67,"reg":98,"name":"Volte Pravý Blok-stranu za ODVOLAT.polit.,NÍZKÉ daně,VYROVN.rozp.,MIN.byrokr.,SPRAV.just.,PŘÍMOU demokr. WWW.CIBULKA.NET"},{"id":14,"votes":1,"pct":1.67,"reg":155,"name":"Blok proti islamizaci - Obrana domova"},{"id":16,"votes":3,"pct":5,"reg":83,"name":"Moravané"},{"id":20,"votes":1,"pct":1.67,"reg":655,"name":"Nejen hasiči a živnostníci s učiteli do Evropy - www.hnpd.cz, www.sdzp.cz"},{"id":21,"votes":12,"pct":20,"reg":47,"name":"Komunistická strana Čech a Moravy"},{"id":22,"votes":1,"pct":1.67,"reg":656,"name":"Koalice STAN a ALTERNATIVA"},{"id":26,"votes":3,"pct":5,"reg":5,"name":"Strana zelených"},{"id":31,"votes":2,"pct":3.33,"reg":153,"name":"Dělnická strana"},{"id":32,"votes":1,"pct":1.67,"reg":88,"name":"NEZÁVISLÍ"},{"id":33,"votes":18,"pct":30,"reg":7,"name":"Česká strana sociálně demokratická"}]}]},"obvod":{"id":62,"name":"Prostějov"}}