<?xml version="1.0" encoding="iso-8859-2"?>
<VYSLEDKY_OKRES xmlns="http://www.w3.org/namespace/" xmlns:xsi="http://www.w3.org/2001/XMLSchema-instance"
                xsi:schemaLocation="http://www.w3.org/namespace/ kz_vysledky_okres.xsd"
                DATUM_CAS_GENEROVANI="2019-11-29T10:49:23">
<OKRES NUTS_OKRES="CZ0802" NAZ_OKRES="Frýdek-Místek">
<UCAST OKRSKY_CELKEM="212" OKRSKY_ZPRAC="212" OKRSKY_ZPRAC_PROC="100.00" ZAPSANI_VOLICI="173941" VYDANE_OBALKY="57396" UCAST_PROC="33.00" ODEVZDANE_OBALKY="57248" PLATNE_HLASY="56146" PLATNE_HLASY_PROC="98.08" />
<HLASY_STRANA KSTRANA="1" HLASY="135" PROC_HLASU="0.24" />
<HLASY_STRANA KSTRANA="2" HLASY="3779" PROC_HLASU="6.73" />
<HLASY_STRANA KSTRANA="9" HLASY="542" PROC_HLASU="0.97" />
<HLASY_STRANA KSTRANA="12" HLASY="9885" PROC_HLASU="17.61" />
<HLASY_STRANA KSTRANA="24" HLASY="8266" PROC_HLASU="14.72" />
<HLASY_STRANA KSTRANA="26" HLASY="92" PROC_HLASU="0.16" />
<HLASY_STRANA KSTRANA="28" HLASY="16" PROC_HLASU="0.03" />
<HLASY_STRANA KSTRANA="30" HLASY="13675" PROC_HLASU="24.36" />
<HLASY_STRANA KSTRANA="31" HLASY="156" PROC_HLASU="0.28" />
<HLASY_STRANA KSTRANA="32" HLASY="1730" PROC_HLASU="3.08" />
<HLASY_STRANA KSTRANA="37" HLASY="5348" PROC_HLASU="9.53" />
<HLASY_STRANA KSTRANA="41" HLASY="62" PROC_HLASU="0.11" />
<HLASY_STRANA KSTRANA="43" HLASY="895" PROC_HLASU="1.59" />
<HLASY_STRANA KSTRANA="45" HLASY="120" PROC_HLASU="0.21" />
<HLASY_STRANA KSTRANA="46" HLASY="897" PROC_HLASU="1.60" />
<HLASY_STRANA KSTRANA="47" HLASY="2981" PROC_HLASU="5.31" />
<HLASY_STRANA KSTRANA="52" HLASY="688" PROC_HLASU="1.23" />
<HLASY_STRANA KSTRANA="65" HLASY="489" PROC_HLASU="0.87" />
<HLASY_STRANA KSTRANA="67" HLASY="136" PROC_HLASU="0.24" />
<HLASY_STRANA KSTRANA="68" HLASY="895" PROC_HLASU="1.59" />
<HLASY_STRANA KSTRANA="70" HLASY="78" PROC_HLASU="0.14" />
<HLASY_STRANA KSTRANA="75" HLASY="314" PROC_HLASU="0.56" />
<HLASY_STRANA KSTRANA="78" HLASY="3452" PROC_HLASU="6.15" />
<HLASY_STRANA KSTRANA="81" HLASY="30" PROC_HLASU="0.05" />
<HLASY_STRANA KSTRANA="82" HLASY="1485" PROC_HLASU="2.64" />
</OKRES>
<OBEC CIS_OBEC="507091" NAZ_OBEC="Nýdek">
<UCAST OKRSKY_CELKEM="2" OKRSKY_ZPRAC="2" OKRSKY_ZPRAC_PROC="100.00" ZAPSANI_VOLICI="1671" VYDANE_OBALKY="557" UCAST_PROC="33.33" ODEVZDANE_OBALKY="556" PLATNE_HLASY="537" PLATNE_HLASY_PROC="96.58" />
<HLASY_STRANA KSTRANA="2" HLASY="35" PROC_HLASU="6.51" />
<HLASY_STRANA KSTRANA="9" HLASY="2" PROC_HLASU="0.37" />
<HLASY_STRANA KSTRANA="12" HLASY="174" PROC_HLASU="32.40" />
<HLASY_STRANA KSTRANA="24" HLASY="71" PROC_HLASU="13.22" />
<HLASY_STRANA KSTRANA="30" HLASY="109" PROC_HLASU="20.29" />
<HLASY_STRANA KSTRANA="32" HLASY="9" PROC_HLASU="1.67" />
<HLASY_STRANA KSTRANA="37" HLASY="31" PROC_HLASU="5.77" />
<HLASY_STRANA KSTRANA="43" HLASY="10" PROC_HLASU="1.86" />
<HLASY_STRANA KSTRANA="45" HLASY="1" PROC_HLASU="0.18" />
<HLASY_STRANA KSTRANA="46" HLASY="5" PROC_HLASU="0.93" />
<HLASY_STRANA KSTRANA="47" HLASY="46" PROC_HLASU="8.56" />
<HLASY_STRANA KSTRANA="65" HLASY="2" PROC_HLASU="0.37" />
<HLASY_STRANA KSTRANA="67" HLASY="1" PROC_HLASU="0.18" />
<HLASY_STRANA KSTRANA="68" HLASY="5" PROC_HLASU="0.93" />
<HLASY_STRANA KSTRANA="70" HLASY="1" PROC_HLASU="0.18" />
<HLASY_STRANA KSTRANA="75" HLASY="5" PROC_HLASU="0.93" />
<HLASY_STRANA KSTRANA="78" HLASY="20" PROC_HLASU="3.72" />
<HLASY_STRANA KSTRANA="82" HLASY="10" PROC_HLASU="1.86" />
</OBEC>
<OBEC CIS_OBEC="507181" NAZ_OBEC="Pržno">
<UCAST OKRSKY_CELKEM="1" OKRSKY_ZPRAC="1" OKRSKY_ZPRAC_PROC="100.00" ZAPSANI_VOLICI="798" VYDANE_OBALKY="274" UCAST_PROC="34.34" ODEVZDANE_OBALKY="274" PLATNE_HLASY="271" PLATNE_HLASY_PROC="98.91" />
<HLASY_STRANA KSTRANA="2" HLASY="17" PROC_HLASU="6.27" />
<HLASY_STRANA KSTRANA="9" HLASY="2" PROC_HLASU="0.73" />
<HLASY_STRANA KSTRANA="12" HLASY="37" PROC_HLASU="13.65" />
<HLASY_STRANA KSTRANA="24" HLASY="37" PROC_HLASU="13.65" />
<HLASY_STRANA KSTRANA="26" HLASY="1" PROC_HLASU="0.36" />
<HLASY_STRANA KSTRANA="30" HLASY="65" PROC_HLASU="23.98" />
<HLASY_STRANA KSTRANA="32" HLASY="13" PROC_HLASU="4.79" />
<HLASY_STRANA KSTRANA="37" HLASY="15" PROC_HLASU="5.53" />
<HLASY_STRANA KSTRANA="46" HLASY="4" PROC_HLASU="1.47" />
<HLASY_STRANA KSTRANA="47" HLASY="37" PROC_HLASU="13.65" />
<HLASY_STRANA KSTRANA="52" HLASY="7" PROC_HLASU="2.58" />
<HLASY_STRANA KSTRANA="65" HLASY="1" PROC_HLASU="0.36" />
<HLASY_STRANA KSTRANA="68" HLASY="3" PROC_HLASU="1.10" />
<HLASY_STRANA KSTRANA="75" HLASY="1" PROC_HLASU="0.36" />
<HLASY_STRANA KSTRANA="78" HLASY="20" PROC_HLASU="7.38" />
<HLASY_STRANA KSTRANA="82" HLASY="11" PROC_HLASU="4.05" />
</OBEC>
<OBEC CIS_OBEC="507237" NAZ_OBEC="Komorní Lhotka">
<UCAST OKRSKY_CELKEM="1" OKRSKY_ZPRAC="1" OKRSKY_ZPRAC_PROC="100.00" ZAPSANI_VOLICI="1046" VYDANE_OBALKY="345" UCAST_PROC="32.98" ODEVZDANE_OBALKY="336" PLATNE_HLASY="336" PLATNE_HLASY_PROC="100.00" />
<HLASY_STRANA KSTRANA="2" HLASY="23" PROC_HLASU="6.84" />
<HLASY_STRANA KSTRANA="9" HLASY="6" PROC_HLASU="1.78" />
<HLASY_STRANA KSTRANA="12" HLASY="81" PROC_HLASU="24.10" />
<HLASY_STRANA KSTRANA="24" HLASY="69" PROC_HLASU="20.53" />
<HLASY_STRANA KSTRANA="26" HLASY="1" PROC_HLASU="0.29" />
<HLASY_STRANA KSTRANA="30" HLASY="70" PROC_HLASU="20.83" />
<HLASY_STRANA KSTRANA="32" HLASY="7" PROC_HLASU="2.08" />
<HLASY_STRANA KSTRANA="37" HLASY="27" PROC_HLASU="8.03" />
<HLASY_STRANA KSTRANA="43" HLASY="3" PROC_HLASU="0.89" />
<HLASY_STRANA KSTRANA="45" HLASY="2" PROC_HLASU="0.59" />
<HLASY_STRANA KSTRANA="47" HLASY="15" PROC_HLASU="4.46" />
<HLASY_STRANA KSTRANA="52" HLASY="9" PROC_HLASU="2.67" />
<HLASY_STRANA KSTRANA="65" HLASY="4" PROC_HLASU="1.19" />
<HLASY_STRANA KSTRANA="68" HLASY="3" PROC_HLASU="0.89" />
<HLASY_STRANA KSTRANA="78" HLASY="11" PROC_HLASU="3.27" />
<HLASY_STRANA KSTRANA="82" HLASY="5" PROC_HLASU="1.48" />
</OBEC>
<OBEC CIS_OBEC="507423" NAZ_OBEC="Janovice">
<UCAST OKRSKY_CELKEM="2" OKRSKY_ZPRAC="2" OKRSKY_ZPRAC_PROC="100.00" ZAPSANI_VOLICI="1529" VYDANE_OBALKY="537" UCAST_PROC="35.12" ODEVZDANE_OBALKY="537" PLATNE_HLASY="533" PLATNE_HLASY_PROC="99.26" />
<HLASY_STRANA KSTRANA="2" HLASY="27" PROC_HLASU="5.06" />
<HLASY_STRANA KSTRANA="9" HLASY="3" PROC_HLASU="0.56" />
<HLASY_STRANA KSTRANA="12" HLASY="59" PROC_HLASU="11.06" />
<HLASY_STRANA KSTRANA="24" HLASY="40" PROC_HLASU="7.50" />
<HLASY_STRANA KSTRANA="30" HLASY="73" PROC_HLASU="13.69" />
<HLASY_STRANA KSTRANA="32" HLASY="12" PROC_HLASU="2.25" />
<HLASY_STRANA KSTRANA="37" HLASY="69" PROC_HLASU="12.94" />
<HLASY_STRANA KSTRANA="41" HLASY="1" PROC_HLASU="0.18" />
<HLASY_STRANA KSTRANA="43" HLASY="4" PROC_HLASU="0.75" />
<HLASY_STRANA KSTRANA="45" HLASY="1" PROC_HLASU="0.18" />
<HLASY_STRANA KSTRANA="46" HLASY="3" PROC_HLASU="0.56" />
<HLASY_STRANA KSTRANA="47" HLASY="169" PROC_HLASU="31.70" />
<HLASY_STRANA KSTRANA="52" HLASY="5" PROC_HLASU="0.93" />
<HLASY_STRANA KSTRANA="65" HLASY="4" PROC_HLASU="0.75" />
<HLASY_STRANA KSTRANA="67" HLASY="5" PROC_HLASU="0.93" />
<HLASY_STRANA KSTRANA="68" HLASY="4" PROC_HLASU="0.75" />
<HLASY_STRANA KSTRANA="75" HLASY="1" PROC_HLASU="0.18" />
<HLASY_STRANA KSTRANA="78" HLASY="37" PROC_HLASU="6.94" />
<HLASY_STRANA KSTRANA="82" HLASY="16" PROC_HLASU="3.00" />
</OBEC>
<OBEC CIS_OBEC="507458" NAZ_OBEC="Košařiska">
<UCAST OKRSKY_CELKEM="1" OKRSKY_ZPRAC="1" OKRSKY_ZPRAC_PROC="100.00" ZAPSANI_VOLICI="296" VYDANE_OBALKY="116" UCAST_PROC="39.19" ODEVZDANE_OBALKY="116" PLATNE_HLASY="112" PLATNE_HLASY_PROC="96.55" />
<HLASY_STRANA KSTRANA="2" HLASY="10" PROC_HLASU="8.92" />
<HLASY_STRANA KSTRANA="9" HLASY="1" PROC_HLASU="0.89" />
<HLASY_STRANA KSTRANA="12" HLASY="18" PROC_HLASU="16.07" />
<HLASY_STRANA KSTRANA="24" HLASY="15" PROC_HLASU="13.39" />
<HLASY_STRANA KSTRANA="30" HLASY="18" PROC_HLASU="16.07" />
<HLASY_STRANA KSTRANA="32" HLASY="1" PROC_HLASU="0.89" />
<HLASY_STRANA KSTRANA="37" HLASY="7" PROC_HLASU="6.25" />
<HLASY_STRANA KSTRANA="43" HLASY="3" PROC_HLASU="2.67" />
<HLASY_STRANA KSTRANA="46" HLASY="1" PROC_HLASU="0.89" />
<HLASY_STRANA KSTRANA="47" HLASY="13" PROC_HLASU="11.60" />
<HLASY_STRANA KSTRANA="52" HLASY="2" PROC_HLASU="1.78" />
<HLASY_STRANA KSTRANA="68" HLASY="20" PROC_HLASU="17.85" />
<HLASY_STRANA KSTRANA="78" HLASY="2" PROC_HLASU="1.78" />
<HLASY_STRANA KSTRANA="82" HLASY="1" PROC_HLASU="0.89" />
</OBEC>
<OBEC CIS_OBEC="507547" NAZ_OBEC="Milíkov">
<UCAST OKRSKY_CELKEM="1" OKRSKY_ZPRAC="1" OKRSKY_ZPRAC_PROC="100.00" ZAPSANI_VOLICI="1072" VYDANE_OBALKY="392" UCAST_PROC="36.57" ODEVZDANE_OBALKY="391" PLATNE_HLASY="379" PLATNE_HLASY_PROC="96.93" />
<HLASY_STRANA KSTRANA="1" HLASY="1" PROC_HLASU="0.26" />
<HLASY_STRANA KSTRANA="2" HLASY="28" PROC_HLASU="7.38" />
<HLASY_STRANA KSTRANA="9" HLASY="3" PROC_HLASU="0.79" />
<HLASY_STRANA KSTRANA="12" HLASY="117" PROC_HLASU="30.87" />
<HLASY_STRANA KSTRANA="24" HLASY="64" PROC_HLASU="16.88" />
<HLASY_STRANA KSTRANA="30" HLASY="61" PROC_HLASU="16.09" />
<HLASY_STRANA KSTRANA="32" HLASY="5" PROC_HLASU="1.31" />
<HLASY_STRANA KSTRANA="37" HLASY="16" PROC_HLASU="4.22" />
<HLASY_STRANA KSTRANA="41" HLASY="1" PROC_HLASU="0.26" />
<HLASY_STRANA KSTRANA="43" HLASY="3" PROC_HLASU="0.79" />
<HLASY_STRANA KSTRANA="45" HLASY="1" PROC_HLASU="0.26" />
<HLASY_STRANA KSTRANA="46" HLASY="5" PROC_HLASU="1.31" />
<HLASY_STRANA KSTRANA="47" HLASY="41" PROC_HLASU="10.81" />
<HLASY_STRANA KSTRANA="52" HLASY="2" PROC_HLASU="0.52" />
<HLASY_STRANA KSTRANA="65" HLASY="1" PROC_HLASU="0.26" />
<HLASY_STRANA KSTRANA="67" HLASY="1" PROC_HLASU="0.26" />
<HLASY_STRANA KSTRANA="68" HLASY="6" PROC_HLASU="1.58" />
<HLASY_STRANA KSTRANA="75" HLASY="2" PROC_HLASU="0.52" />
<HLASY_STRANA KSTRANA="78" HLASY="12" PROC_HLASU="3.16" />
<HLASY_STRANA KSTRANA="82" HLASY="9" PROC_HLASU="2.37" />
</OBEC>
<OBEC CIS_OBEC="511633" NAZ_OBEC="Bocanovice">
<UCAST OKRSKY_CELKEM="1" OKRSKY_ZPRAC="1" OKRSKY_ZPRAC_PROC="100.00" ZAPSANI_VOLICI="347" VYDANE_OBALKY="123" UCAST_PROC="35.45" ODEVZDANE_OBALKY="120" PLATNE_HLASY="118" PLATNE_HLASY_PROC="98.33" />
<HLASY_STRANA KSTRANA="2" HLASY="10" PROC_HLASU="8.47" />
<HLASY_STRANA KSTRANA="9" HLASY="2" PROC_HLASU="1.69" />
<HLASY_STRANA KSTRANA="12" HLASY="33" PROC_HLASU="27.96" />
<HLASY_STRANA KSTRANA="24" HLASY="40" PROC_HLASU="33.89" />
<HLASY_STRANA KSTRANA="30" HLASY="12" PROC_HLASU="10.16" />
<HLASY_STRANA KSTRANA="32" HLASY="1" PROC_HLASU="0.84" />
<HLASY_STRANA KSTRANA="37" HLASY="6" PROC_HLASU="5.08" />
<HLASY_STRANA KSTRANA="43" HLASY="4" PROC_HLASU="3.38" />
<HLASY_STRANA KSTRANA="47" HLASY="6" PROC_HLASU="5.08" />
<HLASY_STRANA KSTRANA="52" HLASY="1" PROC_HLASU="0.84" />
<HLASY_STRANA KSTRANA="68" HLASY="1" PROC_HLASU="0.84" />
<HLASY_STRANA KSTRANA="75" HLASY="2" PROC_HLASU="1.69" />
</OBEC>
<OBEC CIS_OBEC="511935" NAZ_OBEC="Bukovec">
<UCAST OKRSKY_CELKEM="1" OKRSKY_ZPRAC="1" OKRSKY_ZPRAC_PROC="100.00" ZAPSANI_VOLICI="1055" VYDANE_OBALKY="400" UCAST_PROC="37.91" ODEVZDANE_OBALKY="398" PLATNE_HLASY="389" PLATNE_HLASY_PROC="97.74" />
<HLASY_STRANA KSTRANA="1" HLASY="1" PROC_HLASU="0.25" />
<HLASY_STRANA KSTRANA="2" HLASY="15" PROC_HLASU="3.85" />
<HLASY_STRANA KSTRANA="9" HLASY="1" PROC_HLASU="0.25" />
<HLASY_STRANA KSTRANA="12" HLASY="53" PROC_HLASU="13.62" />
<HLASY_STRANA KSTRANA="24" HLASY="159" PROC_HLASU="40.87" />
<HLASY_STRANA KSTRANA="30" HLASY="32" PROC_HLASU="8.22" />
<HLASY_STRANA KSTRANA="32" HLASY="6" PROC_HLASU="1.54" />
<HLASY_STRANA KSTRANA="37" HLASY="9" PROC_HLASU="2.31" />
<HLASY_STRANA KSTRANA="43" HLASY="5" PROC_HLASU="1.28" />
<HLASY_STRANA KSTRANA="45" HLASY="2" PROC_HLASU="0.51" />
<HLASY_STRANA KSTRANA="46" HLASY="6" PROC_HLASU="1.54" />
<HLASY_STRANA KSTRANA="47" HLASY="76" PROC_HLASU="19.53" />
<HLASY_STRANA KSTRANA="67" HLASY="1" PROC_HLASU="0.25" />
<HLASY_STRANA KSTRANA="78" HLASY="16" PROC_HLASU="4.11" />
<HLASY_STRANA KSTRANA="82" HLASY="7" PROC_HLASU="1.79" />
</OBEC>
<OBEC CIS_OBEC="511951" NAZ_OBEC="Dolní Lomná">
<UCAST OKRSKY_CELKEM="1" OKRSKY_ZPRAC="1" OKRSKY_ZPRAC_PROC="100.00" ZAPSANI_VOLICI="706" VYDANE_OBALKY="246" UCAST_PROC="34.84" ODEVZDANE_OBALKY="244" PLATNE_HLASY="240" PLATNE_HLASY_PROC="98.36" />
<HLASY_STRANA KSTRANA="2" HLASY="12" PROC_HLASU="5.00" />
<HLASY_STRANA KSTRANA="9" HLASY="1" PROC_HLASU="0.41" />
<HLASY_STRANA KSTRANA="12" HLASY="22" PROC_HLASU="9.16" />
<HLASY_STRANA KSTRANA="24" HLASY="43" PROC_HLASU="17.91" />
<HLASY_STRANA KSTRANA="30" HLASY="20" PROC_HLASU="8.33" />
<HLASY_STRANA KSTRANA="31" HLASY="3" PROC_HLASU="1.25" />
<HLASY_STRANA KSTRANA="37" HLASY="9" PROC_HLASU="3.75" />
<HLASY_STRANA KSTRANA="43" HLASY="2" PROC_HLASU="0.83" />
<HLASY_STRANA KSTRANA="46" HLASY="3" PROC_HLASU="1.25" />
<HLASY_STRANA KSTRANA="47" HLASY="112" PROC_HLASU="46.66" />
<HLASY_STRANA KSTRANA="52" HLASY="2" PROC_HLASU="0.83" />
<HLASY_STRANA KSTRANA="68" HLASY="3" PROC_HLASU="1.25" />
<HLASY_STRANA KSTRANA="75" HLASY="1" PROC_HLASU="0.41" />
<HLASY_STRANA KSTRANA="78" HLASY="6" PROC_HLASU="2.50" />
<HLASY_STRANA KSTRANA="82" HLASY="1" PROC_HLASU="0.41" />
</OBEC>
<OBEC CIS_OBEC="511986" NAZ_OBEC="Horní Lomná">
<UCAST OKRSKY_CELKEM="1" OKRSKY_ZPRAC="1" OKRSKY_ZPRAC_PROC="100.00" ZAPSANI_VOLICI="314" VYDANE_OBALKY="96" UCAST_PROC="30.57" ODEVZDANE_OBALKY="95" PLATNE_HLASY="93" PLATNE_HLASY_PROC="97.89" />
<HLASY_STRANA KSTRANA="2" HLASY="4" PROC_HLASU="4.30" />
<HLASY_STRANA KSTRANA="9" HLASY="1" PROC_HLASU="1.07" />
<HLASY_STRANA KSTRANA="12" HLASY="17" PROC_HLASU="18.27" />
<HLASY_STRANA KSTRANA="24" HLASY="29" PROC_HLASU="31.18" />
<HLASY_STRANA KSTRANA="30" HLASY="14" PROC_HLASU="15.05" />
<HLASY_STRANA KSTRANA="32" HLASY="2" PROC_HLASU="2.15" />
<HLASY_STRANA KSTRANA="37" HLASY="3" PROC_HLASU="3.22" />
<HLASY_STRANA KSTRANA="47" HLASY="19" PROC_HLASU="20.43" />
<HLASY_STRANA KSTRANA="65" HLASY="1" PROC_HLASU="1.07" />
<HLASY_STRANA KSTRANA="67" HLASY="1" PROC_HLASU="1.07" />
<HLASY_STRANA KSTRANA="68" HLASY="1" PROC_HLASU="1.07" />
<HLASY_STRANA KSTRANA="78" HLASY="1" PROC_HLASU="1.07" />
</OBEC>
<OBEC CIS_OBEC="512028" NAZ_OBEC="Písek">
<UCAST OKRSKY_CELKEM="1" OKRSKY_ZPRAC="1" OKRSKY_ZPRAC_PROC="100.00" ZAPSANI_VOLICI="1465" VYDANE_OBALKY="439" UCAST_PROC="29.97" ODEVZDANE_OBALKY="439" PLATNE_HLASY="427" PLATNE_HLASY_PROC="97.27" />
<HLASY_STRANA KSTRANA="2" HLASY="19" PROC_HLASU="4.44" />
<HLASY_STRANA KSTRANA="12" HLASY="115" PROC_HLASU="26.93" />
<HLASY_STRANA KSTRANA="24" HLASY="81" PROC_HLASU="18.96" />
<HLASY_STRANA KSTRANA="30" HLASY="83" PROC_HLASU="19.43" />
<HLASY_STRANA KSTRANA="31" HLASY="1" PROC_HLASU="0.23" />
<HLASY_STRANA KSTRANA="32" HLASY="6" PROC_HLASU="1.40" />
<HLASY_STRANA KSTRANA="37" HLASY="22" PROC_HLASU="5.15" />
<HLASY_STRANA KSTRANA="41" HLASY="2" PROC_HLASU="0.46" />
<HLASY_STRANA KSTRANA="43" HLASY="3" PROC_HLASU="0.70" />
<HLASY_STRANA KSTRANA="46" HLASY="5" PROC_HLASU="1.17" />
<HLASY_STRANA KSTRANA="47" HLASY="52" PROC_HLASU="12.17" />
<HLASY_STRANA KSTRANA="52" HLASY="2" PROC_HLASU="0.46" />
<HLASY_STRANA KSTRANA="65" HLASY="3" PROC_HLASU="0.70" />
<HLASY_STRANA KSTRANA="67" HLASY="2" PROC_HLASU="0.46" />
<HLASY_STRANA KSTRANA="68" HLASY="6" PROC_HLASU="1.40" />
<HLASY_STRANA KSTRANA="75" HLASY="2" PROC_HLASU="0.46" />
<HLASY_STRANA KSTRANA="78" HLASY="19" PROC_HLASU="4.44" />
<HLASY_STRANA KSTRANA="82" HLASY="4" PROC_HLASU="0.93" />
</OBEC>
<OBEC CIS_OBEC="512176" NAZ_OBEC="Hrádek">
<UCAST OKRSKY_CELKEM="1" OKRSKY_ZPRAC="1" OKRSKY_ZPRAC_PROC="100.00" ZAPSANI_VOLICI="1488" VYDANE_OBALKY="577" UCAST_PROC="38.78" ODEVZDANE_OBALKY="575" PLATNE_HLASY="542" PLATNE_HLASY_PROC="94.26" />
<HLASY_STRANA KSTRANA="1" HLASY="1" PROC_HLASU="0.18" />
<HLASY_STRANA KSTRANA="2" HLASY="30" PROC_HLASU="5.53" />
<HLASY_STRANA KSTRANA="9" HLASY="6" PROC_HLASU="1.10" />
<HLASY_STRANA KSTRANA="12" HLASY="145" PROC_HLASU="26.75" />
<HLASY_STRANA KSTRANA="24" HLASY="60" PROC_HLASU="11.07" />
<HLASY_STRANA KSTRANA="26" HLASY="1" PROC_HLASU="0.18" />
<HLASY_STRANA KSTRANA="30" HLASY="97" PROC_HLASU="17.89" />
<HLASY_STRANA KSTRANA="32" HLASY="6" PROC_HLASU="1.10" />
<HLASY_STRANA KSTRANA="37" HLASY="25" PROC_HLASU="4.61" />
<HLASY_STRANA KSTRANA="41" HLASY="1" PROC_HLASU="0.18" />
<HLASY_STRANA KSTRANA="43" HLASY="17" PROC_HLASU="3.13" />
<HLASY_STRANA KSTRANA="45" HLASY="1" PROC_HLASU="0.18" />
<HLASY_STRANA KSTRANA="46" HLASY="20" PROC_HLASU="3.69" />
<HLASY_STRANA KSTRANA="47" HLASY="104" PROC_HLASU="19.18" />
<HLASY_STRANA KSTRANA="67" HLASY="1" PROC_HLASU="0.18" />
<HLASY_STRANA KSTRANA="68" HLASY="2" PROC_HLASU="0.36" />
<HLASY_STRANA KSTRANA="75" HLASY="4" PROC_HLASU="0.73" />
<HLASY_STRANA KSTRANA="78" HLASY="16" PROC_HLASU="2.95" />
<HLASY_STRANA KSTRANA="82" HLASY="5" PROC_HLASU="0.92" />
</OBEC>
<OBEC CIS_OBEC="512184" NAZ_OBEC="Metylovice">
<UCAST OKRSKY_CELKEM="1" OKRSKY_ZPRAC="1" OKRSKY_ZPRAC_PROC="100.00" ZAPSANI_VOLICI="1406" VYDANE_OBALKY="538" UCAST_PROC="38.26" ODEVZDANE_OBALKY="538" PLATNE_HLASY="530" PLATNE_HLASY_PROC="98.51" />
<HLASY_STRANA KSTRANA="2" HLASY="29" PROC_HLASU="5.47" />
<HLASY_STRANA KSTRANA="9" HLASY="5" PROC_HLASU="0.94" />
<HLASY_STRANA KSTRANA="12" HLASY="61" PROC_HLASU="11.50" />
<HLASY_STRANA KSTRANA="24" HLASY="101" PROC_HLASU="19.05" />
<HLASY_STRANA KSTRANA="26" HLASY="2" PROC_HLASU="0.37" />
<HLASY_STRANA KSTRANA="30" HLASY="122" PROC_HLASU="23.01" />
<HLASY_STRANA KSTRANA="31" HLASY="1" PROC_HLASU="0.18" />
<HLASY_STRANA KSTRANA="32" HLASY="23" PROC_HLASU="4.33" />
<HLASY_STRANA KSTRANA="37" HLASY="60" PROC_HLASU="11.32" />
<HLASY_STRANA KSTRANA="41" HLASY="1" PROC_HLASU="0.18" />
<HLASY_STRANA KSTRANA="43" HLASY="4" PROC_HLASU="0.75" />
<HLASY_STRANA KSTRANA="46" HLASY="6" PROC_HLASU="1.13" />
<HLASY_STRANA KSTRANA="47" HLASY="41" PROC_HLASU="7.73" />
<HLASY_STRANA KSTRANA="52" HLASY="9" PROC_HLASU="1.69" />
<HLASY_STRANA KSTRANA="65" HLASY="7" PROC_HLASU="1.32" />
<HLASY_STRANA KSTRANA="68" HLASY="3" PROC_HLASU="0.56" />
<HLASY_STRANA KSTRANA="75" HLASY="1" PROC_HLASU="0.18" />
<HLASY_STRANA KSTRANA="78" HLASY="32" PROC_HLASU="6.03" />
<HLASY_STRANA KSTRANA="82" HLASY="22" PROC_HLASU="4.15" />
</OBEC>
<OBEC CIS_OBEC="512192" NAZ_OBEC="Horní Domaslavice">
<UCAST OKRSKY_CELKEM="1" OKRSKY_ZPRAC="1" OKRSKY_ZPRAC_PROC="100.00" ZAPSANI_VOLICI="629" VYDANE_OBALKY="229" UCAST_PROC="36.41" ODEVZDANE_OBALKY="229" PLATNE_HLASY="229" PLATNE_HLASY_PROC="100.00" />
<HLASY_STRANA KSTRANA="2" HLASY="17" PROC_HLASU="7.42" />
<HLASY_STRANA KSTRANA="12" HLASY="30" PROC_HLASU="13.10" />
<HLASY_STRANA KSTRANA="24" HLASY="56" PROC_HLASU="24.45" />
<HLASY_STRANA KSTRANA="30" HLASY="48" PROC_HLASU="20.96" />
<HLASY_STRANA KSTRANA="31" HLASY="1" PROC_HLASU="0.43" />
<HLASY_STRANA KSTRANA="32" HLASY="2" PROC_HLASU="0.87" />
<HLASY_STRANA KSTRANA="37" HLASY="25" PROC_HLASU="10.91" />
<HLASY_STRANA KSTRANA="43" HLASY="5" PROC_HLASU="2.18" />
<HLASY_STRANA KSTRANA="46" HLASY="1" PROC_HLASU="0.43" />
<HLASY_STRANA KSTRANA="47" HLASY="3" PROC_HLASU="1.31" />
<HLASY_STRANA KSTRANA="65" HLASY="3" PROC_HLASU="1.31" />
<HLASY_STRANA KSTRANA="68" HLASY="3" PROC_HLASU="1.31" />
<HLASY_STRANA KSTRANA="70" HLASY="1" PROC_HLASU="0.43" />
<HLASY_STRANA KSTRANA="75" HLASY="2" PROC_HLASU="0.87" />
<HLASY_STRANA KSTRANA="78" HLASY="23" PROC_HLASU="10.04" />
<HLASY_STRANA KSTRANA="82" HLASY="9" PROC_HLASU="3.93" />
</OBEC>
<OBEC CIS_OBEC="549665" NAZ_OBEC="Raškovice">
<UCAST OKRSKY_CELKEM="2" OKRSKY_ZPRAC="2" OKRSKY_ZPRAC_PROC="100.00" ZAPSANI_VOLICI="1507" VYDANE_OBALKY="521" UCAST_PROC="34.57" ODEVZDANE_OBALKY="521" PLATNE_HLASY="507" PLATNE_HLASY_PROC="97.31" />
<HLASY_STRANA KSTRANA="1" HLASY="2" PROC_HLASU="0.39" />
<HLASY_STRANA KSTRANA="2" HLASY="32" PROC_HLASU="6.31" />
<HLASY_STRANA KSTRANA="9" HLASY="4" PROC_HLASU="0.78" />
<HLASY_STRANA KSTRANA="12" HLASY="53" PROC_HLASU="10.45" />
<HLASY_STRANA KSTRANA="24" HLASY="30" PROC_HLASU="5.91" />
<HLASY_STRANA KSTRANA="30" HLASY="118" PROC_HLASU="23.27" />
<HLASY_STRANA KSTRANA="32" HLASY="30" PROC_HLASU="5.91" />
<HLASY_STRANA KSTRANA="37" HLASY="148" PROC_HLASU="29.19" />
<HLASY_STRANA KSTRANA="41" HLASY="2" PROC_HLASU="0.39" />
<HLASY_STRANA KSTRANA="43" HLASY="8" PROC_HLASU="1.57" />
<HLASY_STRANA KSTRANA="46" HLASY="4" PROC_HLASU="0.78" />
<HLASY_STRANA KSTRANA="47" HLASY="9" PROC_HLASU="1.77" />
<HLASY_STRANA KSTRANA="52" HLASY="8" PROC_HLASU="1.57" />
<HLASY_STRANA KSTRANA="65" HLASY="3" PROC_HLASU="0.59" />
<HLASY_STRANA KSTRANA="68" HLASY="5" PROC_HLASU="0.98" />
<HLASY_STRANA KSTRANA="78" HLASY="38" PROC_HLASU="7.49" />
<HLASY_STRANA KSTRANA="82" HLASY="13" PROC_HLASU="2.56" />
</OBEC>
<OBEC CIS_OBEC="549673" NAZ_OBEC="Krásná">
<UCAST OKRSKY_CELKEM="1" OKRSKY_ZPRAC="1" OKRSKY_ZPRAC_PROC="100.00" ZAPSANI_VOLICI="567" VYDANE_OBALKY="181" UCAST_PROC="31.92" ODEVZDANE_OBALKY="181" PLATNE_HLASY="181" PLATNE_HLASY_PROC="100.00" />
<HLASY_STRANA KSTRANA="2" HLASY="7" PROC_HLASU="3.86" />
<HLASY_STRANA KSTRANA="12" HLASY="25" PROC_HLASU="13.81" />
<HLASY_STRANA KSTRANA="24" HLASY="27" PROC_HLASU="14.91" />
<HLASY_STRANA KSTRANA="26" HLASY="2" PROC_HLASU="1.10" />
<HLASY_STRANA KSTRANA="30" HLASY="48" PROC_HLASU="26.51" />
<HLASY_STRANA KSTRANA="31" HLASY="1" PROC_HLASU="0.55" />
<HLASY_STRANA KSTRANA="32" HLASY="4" PROC_HLASU="2.20" />
<HLASY_STRANA KSTRANA="37" HLASY="32" PROC_HLASU="17.67" />
<HLASY_STRANA KSTRANA="45" HLASY="1" PROC_HLASU="0.55" />
<HLASY_STRANA KSTRANA="46" HLASY="3" PROC_HLASU="1.65" />
<HLASY_STRANA KSTRANA="47" HLASY="11" PROC_HLASU="6.07" />
<HLASY_STRANA KSTRANA="65" HLASY="4" PROC_HLASU="2.20" />
<HLASY_STRANA KSTRANA="68" HLASY="3" PROC_HLASU="1.65" />
<HLASY_STRANA KSTRANA="78" HLASY="12" PROC_HLASU="6.62" />
<HLASY_STRANA KSTRANA="82" HLASY="1" PROC_HLASU="0.55" />
</OBEC>
<OBEC CIS_OBEC="552488" NAZ_OBEC="Vojkovice">
<UCAST OKRSKY_CELKEM="1" OKRSKY_ZPRAC="1" OKRSKY_ZPRAC_PROC="100.00" ZAPSANI_VOLICI="509" VYDANE_OBALKY="146" UCAST_PROC="28.68" ODEVZDANE_OBALKY="146" PLATNE_HLASY="144" PLATNE_HLASY_PROC="98.63" />
<HLASY_STRANA KSTRANA="2" HLASY="2" PROC_HLASU="1.38" />
<HLASY_STRANA KSTRANA="9" HLASY="1" PROC_HLASU="0.69" />
<HLASY_STRANA KSTRANA="12" HLASY="21" PROC_HLASU="14.58" />
<HLASY_STRANA KSTRANA="24" HLASY="29" PROC_HLASU="20.13" />
<HLASY_STRANA KSTRANA="30" HLASY="42" PROC_HLASU="29.16" />
<HLASY_STRANA KSTRANA="31" HLASY="1" PROC_HLASU="0.69" />
<HLASY_STRANA KSTRANA="32" HLASY="5" PROC_HLASU="3.47" />
<HLASY_STRANA KSTRANA="37" HLASY="16" PROC_HLASU="11.11" />
<HLASY_STRANA KSTRANA="43" HLASY="2" PROC_HLASU="1.38" />
<HLASY_STRANA KSTRANA="45" HLASY="3" PROC_HLASU="2.08" />
<HLASY_STRANA KSTRANA="46" HLASY="1" PROC_HLASU="0.69" />
<HLASY_STRANA KSTRANA="47" HLASY="2" PROC_HLASU="1.38" />
<HLASY_STRANA KSTRANA="52" HLASY="1" PROC_HLASU="0.69" />
<HLASY_STRANA KSTRANA="68" HLASY="3" PROC_HLASU="2.08" />
<HLASY_STRANA KSTRANA="75" HLASY="2" PROC_HLASU="1.38" />
<HLASY_STRANA KSTRANA="78" HLASY="11" PROC_HLASU="7.63" />
<HLASY_STRANA KSTRANA="82" HLASY="2" PROC_HLASU="1.38" />
</OBEC>
<OBEC CIS_OBEC="552500" NAZ_OBEC="Pazderna">
<UCAST OKRSKY_CELKEM="1" OKRSKY_ZPRAC="1" OKRSKY_ZPRAC_PROC="100.00" ZAPSANI_VOLICI="228" VYDANE_OBALKY="65" UCAST_PROC="28.51" ODEVZDANE_OBALKY="65" PLATNE_HLASY="64" PLATNE_HLASY_PROC="98.46" />
<HLASY_STRANA KSTRANA="2" HLASY="2" PROC_HLASU="3.12" />
<HLASY_STRANA KSTRANA="12" HLASY="7" PROC_HLASU="10.93" />
<HLASY_STRANA KSTRANA="24" HLASY="21" PROC_HLASU="32.81" />
<HLASY_STRANA KSTRANA="30" HLASY="11" PROC_HLASU="17.18" />
<HLASY_STRANA KSTRANA="32" HLASY="1" PROC_HLASU="1.56" />
<HLASY_STRANA KSTRANA="37" HLASY="3" PROC_HLASU="4.68" />
<HLASY_STRANA KSTRANA="47" HLASY="3" PROC_HLASU="4.68" />
<HLASY_STRANA KSTRANA="68" HLASY="6" PROC_HLASU="9.37" />
<HLASY_STRANA KSTRANA="78" HLASY="5" PROC_HLASU="7.81" />
<HLASY_STRANA KSTRANA="82" HLASY="5" PROC_HLASU="7.81" />
</OBEC>
<OBEC CIS_OBEC="552518" NAZ_OBEC="Nošovice">
<UCAST OKRSKY_CELKEM="1" OKRSKY_ZPRAC="1" OKRSKY_ZPRAC_PROC="100.00" ZAPSANI_VOLICI="821" VYDANE_OBALKY="282" UCAST_PROC="34.35" ODEVZDANE_OBALKY="282" PLATNE_HLASY="280" PLATNE_HLASY_PROC="99.29" />
<HLASY_STRANA KSTRANA="2" HLASY="12" PROC_HLASU="4.28" />
<HLASY_STRANA KSTRANA="9" HLASY="3" PROC_HLASU="1.07" />
<HLASY_STRANA KSTRANA="12" HLASY="29" PROC_HLASU="10.35" />
<HLASY_STRANA KSTRANA="24" HLASY="42" PROC_HLASU="15.00" />
<HLASY_STRANA KSTRANA="30" HLASY="119" PROC_HLASU="42.50" />
<HLASY_STRANA KSTRANA="31" HLASY="1" PROC_HLASU="0.35" />
<HLASY_STRANA KSTRANA="32" HLASY="15" PROC_HLASU="5.35" />
<HLASY_STRANA KSTRANA="37" HLASY="21" PROC_HLASU="7.50" />
<HLASY_STRANA KSTRANA="41" HLASY="1" PROC_HLASU="0.35" />
<HLASY_STRANA KSTRANA="43" HLASY="3" PROC_HLASU="1.07" />
<HLASY_STRANA KSTRANA="47" HLASY="4" PROC_HLASU="1.42" />
<HLASY_STRANA KSTRANA="52" HLASY="1" PROC_HLASU="0.35" />
<HLASY_STRANA KSTRANA="68" HLASY="4" PROC_HLASU="1.42" />
<HLASY_STRANA KSTRANA="75" HLASY="4" PROC_HLASU="1.42" />
<HLASY_STRANA KSTRANA="78" HLASY="16" PROC_HLASU="5.71" />
<HLASY_STRANA KSTRANA="82" HLASY="5" PROC_HLASU="1.78" />
</OBEC>
<OBEC CIS_OBEC="552526" NAZ_OBEC="Nižní Lhoty">
<UCAST OKRSKY_CELKEM="1" OKRSKY_ZPRAC="1" OKRSKY_ZPRAC_PROC="100.00" ZAPSANI_VOLICI="214" VYDANE_OBALKY="75" UCAST_PROC="35.05" ODEVZDANE_OBALKY="75" PLATNE_HLASY="75" PLATNE_HLASY_PROC="100.00" />
<HLASY_STRANA KSTRANA="2" HLASY="7" PROC_HLASU="9.33" />
<HLASY_STRANA KSTRANA="12" HLASY="10" PROC_HLASU="13.33" />
<HLASY_STRANA KSTRANA="24" HLASY="23" PROC_HLASU="30.66" />
<HLASY_STRANA KSTRANA="30" HLASY="11" PROC_HLASU="14.66" />
<HLASY_STRANA KSTRANA="31" HLASY="1" PROC_HLASU="1.33" />
<HLASY_STRANA KSTRANA="32" HLASY="5" PROC_HLASU="6.66" />
<HLASY_STRANA KSTRANA="37" HLASY="4" PROC_HLASU="5.33" />
<HLASY_STRANA KSTRANA="47" HLASY="3" PROC_HLASU="4.00" />
<HLASY_STRANA KSTRANA="65" HLASY="1" PROC_HLASU="1.33" />
<HLASY_STRANA KSTRANA="68" HLASY="3" PROC_HLASU="4.00" />
<HLASY_STRANA KSTRANA="78" HLASY="5" PROC_HLASU="6.66" />
<HLASY_STRANA KSTRANA="82" HLASY="2" PROC_HLASU="2.66" />
</OBEC>
<OBEC CIS_OBEC="552542" NAZ_OBEC="Dobratice">
<UCAST OKRSKY_CELKEM="1" OKRSKY_ZPRAC="1" OKRSKY_ZPRAC_PROC="100.00" ZAPSANI_VOLICI="979" VYDANE_OBALKY="312" UCAST_PROC="31.87" ODEVZDANE_OBALKY="312" PLATNE_HLASY="309" PLATNE_HLASY_PROC="99.04" />
<HLASY_STRANA KSTRANA="2" HLASY="8" PROC_HLASU="2.58" />
<HLASY_STRANA KSTRANA="9" HLASY="3" PROC_HLASU="0.97" />
<HLASY_STRANA KSTRANA="12" HLASY="33" PROC_HLASU="10.67" />
<HLASY_STRANA KSTRANA="24" HLASY="72" PROC_HLASU="23.30" />
<HLASY_STRANA KSTRANA="28" HLASY="1" PROC_HLASU="0.32" />
<HLASY_STRANA KSTRANA="30" HLASY="81" PROC_HLASU="26.21" />
<HLASY_STRANA KSTRANA="31" HLASY="1" PROC_HLASU="0.32" />
<HLASY_STRANA KSTRANA="32" HLASY="5" PROC_HLASU="1.61" />
<HLASY_STRANA KSTRANA="37" HLASY="37" PROC_HLASU="11.97" />
<HLASY_STRANA KSTRANA="41" HLASY="1" PROC_HLASU="0.32" />
<HLASY_STRANA KSTRANA="43" HLASY="5" PROC_HLASU="1.61" />
<HLASY_STRANA KSTRANA="47" HLASY="28" PROC_HLASU="9.06" />
<HLASY_STRANA KSTRANA="52" HLASY="3" PROC_HLASU="0.97" />
<HLASY_STRANA KSTRANA="65" HLASY="4" PROC_HLASU="1.29" />
<HLASY_STRANA KSTRANA="68" HLASY="5" PROC_HLASU="1.61" />
<HLASY_STRANA KSTRANA="70" HLASY="1" PROC_HLASU="0.32" />
<HLASY_STRANA KSTRANA="75" HLASY="1" PROC_HLASU="0.32" />
<HLASY_STRANA KSTRANA="78" HLASY="9" PROC_HLASU="2.91" />
<HLASY_STRANA KSTRANA="82" HLASY="11" PROC_HLASU="3.55" />
</OBEC>
<OBEC CIS_OBEC="552551" NAZ_OBEC="Staré Město">
<UCAST OKRSKY_CELKEM="1" OKRSKY_ZPRAC="1" OKRSKY_ZPRAC_PROC="100.00" ZAPSANI_VOLICI="1195" VYDANE_OBALKY="473" UCAST_PROC="39.58" ODEVZDANE_OBALKY="473" PLATNE_HLASY="464" PLATNE_HLASY_PROC="98.10" />
<HLASY_STRANA KSTRANA="2" HLASY="29" PROC_HLASU="6.25" />
<HLASY_STRANA KSTRANA="9" HLASY="6" PROC_HLASU="1.29" />
<HLASY_STRANA KSTRANA="12" HLASY="39" PROC_HLASU="8.40" />
<HLASY_STRANA KSTRANA="24" HLASY="65" PROC_HLASU="14.00" />
<HLASY_STRANA KSTRANA="30" HLASY="146" PROC_HLASU="31.46" />
<HLASY_STRANA KSTRANA="31" HLASY="2" PROC_HLASU="0.43" />
<HLASY_STRANA KSTRANA="32" HLASY="20" PROC_HLASU="4.31" />
<HLASY_STRANA KSTRANA="37" HLASY="38" PROC_HLASU="8.18" />
<HLASY_STRANA KSTRANA="43" HLASY="2" PROC_HLASU="0.43" />
<HLASY_STRANA KSTRANA="46" HLASY="4" PROC_HLASU="0.86" />
<HLASY_STRANA KSTRANA="47" HLASY="16" PROC_HLASU="3.44" />
<HLASY_STRANA KSTRANA="52" HLASY="9" PROC_HLASU="1.93" />
<HLASY_STRANA KSTRANA="65" HLASY="3" PROC_HLASU="0.64" />
<HLASY_STRANA KSTRANA="67" HLASY="5" PROC_HLASU="1.07" />
<HLASY_STRANA KSTRANA="68" HLASY="9" PROC_HLASU="1.93" />
<HLASY_STRANA KSTRANA="70" HLASY="1" PROC_HLASU="0.21" />
<HLASY_STRANA KSTRANA="75" HLASY="4" PROC_HLASU="0.86" />
<HLASY_STRANA KSTRANA="78" HLASY="54" PROC_HLASU="11.63" />
<HLASY_STRANA KSTRANA="82" HLASY="12" PROC_HLASU="2.58" />
</OBEC>
<OBEC CIS_OBEC="552569" NAZ_OBEC="Staříč">
<UCAST OKRSKY_CELKEM="1" OKRSKY_ZPRAC="1" OKRSKY_ZPRAC_PROC="100.00" ZAPSANI_VOLICI="1744" VYDANE_OBALKY="589" UCAST_PROC="33.77" ODEVZDANE_OBALKY="589" PLATNE_HLASY="576" PLATNE_HLASY_PROC="97.79" />
<HLASY_STRANA KSTRANA="2" HLASY="45" PROC_HLASU="7.81" />
<HLASY_STRANA KSTRANA="9" HLASY="4" PROC_HLASU="0.69" />
<HLASY_STRANA KSTRANA="12" HLASY="94" PROC_HLASU="16.31" />
<HLASY_STRANA KSTRANA="24" HLASY="70" PROC_HLASU="12.15" />
<HLASY_STRANA KSTRANA="26" HLASY="1" PROC_HLASU="0.17" />
<HLASY_STRANA KSTRANA="30" HLASY="169" PROC_HLASU="29.34" />
<HLASY_STRANA KSTRANA="31" HLASY="1" PROC_HLASU="0.17" />
<HLASY_STRANA KSTRANA="32" HLASY="9" PROC_HLASU="1.56" />
<HLASY_STRANA KSTRANA="37" HLASY="73" PROC_HLASU="12.67" />
<HLASY_STRANA KSTRANA="43" HLASY="9" PROC_HLASU="1.56" />
<HLASY_STRANA KSTRANA="46" HLASY="1" PROC_HLASU="0.17" />
<HLASY_STRANA KSTRANA="47" HLASY="9" PROC_HLASU="1.56" />
<HLASY_STRANA KSTRANA="52" HLASY="9" PROC_HLASU="1.56" />
<HLASY_STRANA KSTRANA="65" HLASY="5" PROC_HLASU="0.86" />
<HLASY_STRANA KSTRANA="67" HLASY="1" PROC_HLASU="0.17" />
<HLASY_STRANA KSTRANA="68" HLASY="10" PROC_HLASU="1.73" />
<HLASY_STRANA KSTRANA="70" HLASY="4" PROC_HLASU="0.69" />
<HLASY_STRANA KSTRANA="75" HLASY="2" PROC_HLASU="0.34" />
<HLASY_STRANA KSTRANA="78" HLASY="48" PROC_HLASU="8.33" />
<HLASY_STRANA KSTRANA="82" HLASY="12" PROC_HLASU="2.08" />
</OBEC>
<OBEC CIS_OBEC="552577" NAZ_OBEC="Pstruží">
<UCAST OKRSKY_CELKEM="1" OKRSKY_ZPRAC="1" OKRSKY_ZPRAC_PROC="100.00" ZAPSANI_VOLICI="781" VYDANE_OBALKY="303" UCAST_PROC="38.80" ODEVZDANE_OBALKY="303" PLATNE_HLASY="301" PLATNE_HLASY_PROC="99.34" />
<HLASY_STRANA KSTRANA="2" HLASY="31" PROC_HLASU="10.29" />
<HLASY_STRANA KSTRANA="9" HLASY="2" PROC_HLASU="0.66" />
<HLASY_STRANA KSTRANA="12" HLASY="19" PROC_HLASU="6.31" />
<HLASY_STRANA KSTRANA="24" HLASY="31" PROC_HLASU="10.29" />
<HLASY_STRANA KSTRANA="26" HLASY="1" PROC_HLASU="0.33" />
<HLASY_STRANA KSTRANA="30" HLASY="74" PROC_HLASU="24.58" />
<HLASY_STRANA KSTRANA="32" HLASY="8" PROC_HLASU="2.65" />
<HLASY_STRANA KSTRANA="37" HLASY="39" PROC_HLASU="12.95" />
<HLASY_STRANA KSTRANA="43" HLASY="3" PROC_HLASU="0.99" />
<HLASY_STRANA KSTRANA="46" HLASY="11" PROC_HLASU="3.65" />
<HLASY_STRANA KSTRANA="47" HLASY="32" PROC_HLASU="10.63" />
<HLASY_STRANA KSTRANA="52" HLASY="11" PROC_HLASU="3.65" />
<HLASY_STRANA KSTRANA="65" HLASY="5" PROC_HLASU="1.66" />
<HLASY_STRANA KSTRANA="67" HLASY="1" PROC_HLASU="0.33" />
<HLASY_STRANA KSTRANA="68" HLASY="5" PROC_HLASU="1.66" />
<HLASY_STRANA KSTRANA="70" HLASY="1" PROC_HLASU="0.33" />
<HLASY_STRANA KSTRANA="75" HLASY="5" PROC_HLASU="1.66" />
<HLASY_STRANA KSTRANA="78" HLASY="16" PROC_HLASU="5.31" />
<HLASY_STRANA KSTRANA="82" HLASY="6" PROC_HLASU="1.99" />
</OBEC>
<OBEC CIS_OBEC="552593" NAZ_OBEC="Malenovice">
<UCAST OKRSKY_CELKEM="1" OKRSKY_ZPRAC="1" OKRSKY_ZPRAC_PROC="100.00" ZAPSANI_VOLICI="555" VYDANE_OBALKY="218" UCAST_PROC="39.28" ODEVZDANE_OBALKY="218" PLATNE_HLASY="215" PLATNE_HLASY_PROC="98.62" />
<HLASY_STRANA KSTRANA="2" HLASY="22" PROC_HLASU="10.23" />
<HLASY_STRANA KSTRANA="9" HLASY="3" PROC_HLASU="1.39" />
<HLASY_STRANA KSTRANA="12" HLASY="23" PROC_HLASU="10.69" />
<HLASY_STRANA KSTRANA="24" HLASY="44" PROC_HLASU="20.46" />
<HLASY_STRANA KSTRANA="26" HLASY="2" PROC_HLASU="0.93" />
<HLASY_STRANA KSTRANA="30" HLASY="42" PROC_HLASU="19.53" />
<HLASY_STRANA KSTRANA="32" HLASY="22" PROC_HLASU="10.23" />
<HLASY_STRANA KSTRANA="37" HLASY="10" PROC_HLASU="4.65" />
<HLASY_STRANA KSTRANA="43" HLASY="3" PROC_HLASU="1.39" />
<HLASY_STRANA KSTRANA="47" HLASY="17" PROC_HLASU="7.90" />
<HLASY_STRANA KSTRANA="52" HLASY="10" PROC_HLASU="4.65" />
<HLASY_STRANA KSTRANA="65" HLASY="1" PROC_HLASU="0.46" />
<HLASY_STRANA KSTRANA="68" HLASY="2" PROC_HLASU="0.93" />
<HLASY_STRANA KSTRANA="78" HLASY="6" PROC_HLASU="2.79" />
<HLASY_STRANA KSTRANA="82" HLASY="8" PROC_HLASU="3.72" />
</OBEC>
<OBEC CIS_OBEC="552607" NAZ_OBEC="Dolní Tošanovice">
<UCAST OKRSKY_CELKEM="1" OKRSKY_ZPRAC="1" OKRSKY_ZPRAC_PROC="100.00" ZAPSANI_VOLICI="270" VYDANE_OBALKY="96" UCAST_PROC="35.56" ODEVZDANE_OBALKY="95" PLATNE_HLASY="92" PLATNE_HLASY_PROC="96.84" />
<HLASY_STRANA KSTRANA="2" HLASY="2" PROC_HLASU="2.17" />
<HLASY_STRANA KSTRANA="9" HLASY="1" PROC_HLASU="1.08" />
<HLASY_STRANA KSTRANA="12" HLASY="24" PROC_HLASU="26.08" />
<HLASY_STRANA KSTRANA="24" HLASY="22" PROC_HLASU="23.91" />
<HLASY_STRANA KSTRANA="30" HLASY="14" PROC_HLASU="15.21" />
<HLASY_STRANA KSTRANA="31" HLASY="2" PROC_HLASU="2.17" />
<HLASY_STRANA KSTRANA="32" HLASY="2" PROC_HLASU="2.17" />
<HLASY_STRANA KSTRANA="37" HLASY="2" PROC_HLASU="2.17" />
<HLASY_STRANA KSTRANA="47" HLASY="6" PROC_HLASU="6.52" />
<HLASY_STRANA KSTRANA="68" HLASY="1" PROC_HLASU="1.08" />
<HLASY_STRANA KSTRANA="70" HLASY="1" PROC_HLASU="1.08" />
<HLASY_STRANA KSTRANA="78" HLASY="14" PROC_HLASU="15.21" />
<HLASY_STRANA KSTRANA="82" HLASY="1" PROC_HLASU="1.08" />
</OBEC>
<OBEC CIS_OBEC="552615" NAZ_OBEC="Vělopolí">
<UCAST OKRSKY_CELKEM="1" OKRSKY_ZPRAC="1" OKRSKY_ZPRAC_PROC="100.00" ZAPSANI_VOLICI="215" VYDANE_OBALKY="101" UCAST_PROC="46.98" ODEVZDANE_OBALKY="101" PLATNE_HLASY="98" PLATNE_HLASY_PROC="97.03" />
<HLASY_STRANA KSTRANA="1" HLASY="1" PROC_HLASU="1.02" />
<HLASY_STRANA KSTRANA="2" HLASY="16" PROC_HLASU="16.32" />
<HLASY_STRANA KSTRANA="12" HLASY="15" PROC_HLASU="15.30" />
<HLASY_STRANA KSTRANA="24" HLASY="28" PROC_HLASU="28.57" />
<HLASY_STRANA KSTRANA="30" HLASY="13" PROC_HLASU="13.26" />
<HLASY_STRANA KSTRANA="31" HLASY="1" PROC_HLASU="1.02" />
<HLASY_STRANA KSTRANA="32" HLASY="1" PROC_HLASU="1.02" />
<HLASY_STRANA KSTRANA="37" HLASY="6" PROC_HLASU="6.12" />
<HLASY_STRANA KSTRANA="43" HLASY="1" PROC_HLASU="1.02" />
<HLASY_STRANA KSTRANA="47" HLASY="5" PROC_HLASU="5.10" />
<HLASY_STRANA KSTRANA="65" HLASY="1" PROC_HLASU="1.02" />
<HLASY_STRANA KSTRANA="68" HLASY="2" PROC_HLASU="2.04" />
<HLASY_STRANA KSTRANA="75" HLASY="2" PROC_HLASU="2.04" />
<HLASY_STRANA KSTRANA="78" HLASY="2" PROC_HLASU="2.04" />
<HLASY_STRANA KSTRANA="81" HLASY="1" PROC_HLASU="1.02" />
<HLASY_STRANA KSTRANA="82" HLASY="3" PROC_HLASU="3.06" />
</OBEC>
<OBEC CIS_OBEC="552623" NAZ_OBEC="Třanovice">
<UCAST OKRSKY_CELKEM="1" OKRSKY_ZPRAC="1" OKRSKY_ZPRAC_PROC="100.00" ZAPSANI_VOLICI="839" VYDANE_OBALKY="356" UCAST_PROC="42.43" ODEVZDANE_OBALKY="355" PLATNE_HLASY="345" PLATNE_HLASY_PROC="97.18" />
<HLASY_STRANA KSTRANA="2" HLASY="35" PROC_HLASU="10.14" />
<HLASY_STRANA KSTRANA="12" HLASY="51" PROC_HLASU="14.78" />
<HLASY_STRANA KSTRANA="24" HLASY="95" PROC_HLASU="27.53" />
<HLASY_STRANA KSTRANA="30" HLASY="57" PROC_HLASU="16.52" />
<HLASY_STRANA KSTRANA="32" HLASY="9" PROC_HLASU="2.60" />
<HLASY_STRANA KSTRANA="37" HLASY="15" PROC_HLASU="4.34" />
<HLASY_STRANA KSTRANA="43" HLASY="8" PROC_HLASU="2.31" />
<HLASY_STRANA KSTRANA="46" HLASY="1" PROC_HLASU="0.28" />
<HLASY_STRANA KSTRANA="47" HLASY="28" PROC_HLASU="8.11" />
<HLASY_STRANA KSTRANA="52" HLASY="5" PROC_HLASU="1.44" />
<HLASY_STRANA KSTRANA="65" HLASY="2" PROC_HLASU="0.57" />
<HLASY_STRANA KSTRANA="67" HLASY="3" PROC_HLASU="0.86" />
<HLASY_STRANA KSTRANA="68" HLASY="9" PROC_HLASU="2.60" />
<HLASY_STRANA KSTRANA="78" HLASY="20" PROC_HLASU="5.79" />
<HLASY_STRANA KSTRANA="82" HLASY="7" PROC_HLASU="2.02" />
</OBEC>
<OBEC CIS_OBEC="552631" NAZ_OBEC="Horní Tošanovice">
<UCAST OKRSKY_CELKEM="1" OKRSKY_ZPRAC="1" OKRSKY_ZPRAC_PROC="100.00" ZAPSANI_VOLICI="451" VYDANE_OBALKY="121" UCAST_PROC="26.83" ODEVZDANE_OBALKY="121" PLATNE_HLASY="118" PLATNE_HLASY_PROC="97.52" />
<HLASY_STRANA KSTRANA="2" HLASY="13" PROC_HLASU="11.01" />
<HLASY_STRANA KSTRANA="9" HLASY="1" PROC_HLASU="0.84" />
<HLASY_STRANA KSTRANA="12" HLASY="15" PROC_HLASU="12.71" />
<HLASY_STRANA KSTRANA="24" HLASY="13" PROC_HLASU="11.01" />
<HLASY_STRANA KSTRANA="30" HLASY="15" PROC_HLASU="12.71" />
<HLASY_STRANA KSTRANA="31" HLASY="2" PROC_HLASU="1.69" />
<HLASY_STRANA KSTRANA="37" HLASY="12" PROC_HLASU="10.16" />
<HLASY_STRANA KSTRANA="45" HLASY="2" PROC_HLASU="1.69" />
<HLASY_STRANA KSTRANA="46" HLASY="1" PROC_HLASU="0.84" />
<HLASY_STRANA KSTRANA="47" HLASY="26" PROC_HLASU="22.03" />
<HLASY_STRANA KSTRANA="68" HLASY="1" PROC_HLASU="0.84" />
<HLASY_STRANA KSTRANA="75" HLASY="2" PROC_HLASU="1.69" />
<HLASY_STRANA KSTRANA="78" HLASY="11" PROC_HLASU="9.32" />
<HLASY_STRANA KSTRANA="82" HLASY="4" PROC_HLASU="3.38" />
</OBEC>
<OBEC CIS_OBEC="552640" NAZ_OBEC="Řeka">
<UCAST OKRSKY_CELKEM="1" OKRSKY_ZPRAC="1" OKRSKY_ZPRAC_PROC="100.00" ZAPSANI_VOLICI="441" VYDANE_OBALKY="164" UCAST_PROC="37.19" ODEVZDANE_OBALKY="164" PLATNE_HLASY="155" PLATNE_HLASY_PROC="94.51" />
<HLASY_STRANA KSTRANA="2" HLASY="7" PROC_HLASU="4.51" />
<HLASY_STRANA KSTRANA="9" HLASY="1" PROC_HLASU="0.64" />
<HLASY_STRANA KSTRANA="12" HLASY="41" PROC_HLASU="26.45" />
<HLASY_STRANA KSTRANA="24" HLASY="18" PROC_HLASU="11.61" />
<HLASY_STRANA KSTRANA="30" HLASY="28" PROC_HLASU="18.06" />
<HLASY_STRANA KSTRANA="32" HLASY="4" PROC_HLASU="2.58" />
<HLASY_STRANA KSTRANA="37" HLASY="17" PROC_HLASU="10.96" />
<HLASY_STRANA KSTRANA="43" HLASY="3" PROC_HLASU="1.93" />
<HLASY_STRANA KSTRANA="46" HLASY="1" PROC_HLASU="0.64" />
<HLASY_STRANA KSTRANA="47" HLASY="2" PROC_HLASU="1.29" />
<HLASY_STRANA KSTRANA="52" HLASY="5" PROC_HLASU="3.22" />
<HLASY_STRANA KSTRANA="68" HLASY="5" PROC_HLASU="3.22" />
<HLASY_STRANA KSTRANA="78" HLASY="17" PROC_HLASU="10.96" />
<HLASY_STRANA KSTRANA="82" HLASY="6" PROC_HLASU="3.87" />
</OBEC>
<OBEC CIS_OBEC="552658" NAZ_OBEC="Smilovice">
<UCAST OKRSKY_CELKEM="1" OKRSKY_ZPRAC="1" OKRSKY_ZPRAC_PROC="100.00" ZAPSANI_VOLICI="610" VYDANE_OBALKY="256" UCAST_PROC="41.97" ODEVZDANE_OBALKY="255" PLATNE_HLASY="252" PLATNE_HLASY_PROC="98.82" />
<HLASY_STRANA KSTRANA="1" HLASY="2" PROC_HLASU="0.79" />
<HLASY_STRANA KSTRANA="2" HLASY="11" PROC_HLASU="4.36" />
<HLASY_STRANA KSTRANA="9" HLASY="3" PROC_HLASU="1.19" />
<HLASY_STRANA KSTRANA="12" HLASY="38" PROC_HLASU="15.07" />
<HLASY_STRANA KSTRANA="24" HLASY="45" PROC_HLASU="17.85" />
<HLASY_STRANA KSTRANA="30" HLASY="87" PROC_HLASU="34.52" />
<HLASY_STRANA KSTRANA="32" HLASY="9" PROC_HLASU="3.57" />
<HLASY_STRANA KSTRANA="37" HLASY="7" PROC_HLASU="2.77" />
<HLASY_STRANA KSTRANA="43" HLASY="1" PROC_HLASU="0.39" />
<HLASY_STRANA KSTRANA="46" HLASY="5" PROC_HLASU="1.98" />
<HLASY_STRANA KSTRANA="47" HLASY="5" PROC_HLASU="1.98" />
<HLASY_STRANA KSTRANA="52" HLASY="4" PROC_HLASU="1.58" />
<HLASY_STRANA KSTRANA="65" HLASY="1" PROC_HLASU="0.39" />
<HLASY_STRANA KSTRANA="67" HLASY="1" PROC_HLASU="0.39" />
<HLASY_STRANA KSTRANA="68" HLASY="2" PROC_HLASU="0.79" />
<HLASY_STRANA KSTRANA="75" HLASY="1" PROC_HLASU="0.39" />
<HLASY_STRANA KSTRANA="78" HLASY="22" PROC_HLASU="8.73" />
<HLASY_STRANA KSTRANA="81" HLASY="1" PROC_HLASU="0.39" />
<HLASY_STRANA KSTRANA="82" HLASY="7" PROC_HLASU="2.77" />
</OBEC>
<OBEC CIS_OBEC="552674" NAZ_OBEC="Střítež">
<UCAST OKRSKY_CELKEM="1" OKRSKY_ZPRAC="1" OKRSKY_ZPRAC_PROC="100.00" ZAPSANI_VOLICI="810" VYDANE_OBALKY="273" UCAST_PROC="33.70" ODEVZDANE_OBALKY="270" PLATNE_HLASY="259" PLATNE_HLASY_PROC="95.93" />
<HLASY_STRANA KSTRANA="1" HLASY="3" PROC_HLASU="1.15" />
<HLASY_STRANA KSTRANA="2" HLASY="15" PROC_HLASU="5.79" />
<HLASY_STRANA KSTRANA="9" HLASY="1" PROC_HLASU="0.38" />
<HLASY_STRANA KSTRANA="12" HLASY="44" PROC_HLASU="16.98" />
<HLASY_STRANA KSTRANA="24" HLASY="63" PROC_HLASU="24.32" />
<HLASY_STRANA KSTRANA="30" HLASY="61" PROC_HLASU="23.55" />
<HLASY_STRANA KSTRANA="31" HLASY="2" PROC_HLASU="0.77" />
<HLASY_STRANA KSTRANA="32" HLASY="3" PROC_HLASU="1.15" />
<HLASY_STRANA KSTRANA="37" HLASY="21" PROC_HLASU="8.10" />
<HLASY_STRANA KSTRANA="43" HLASY="3" PROC_HLASU="1.15" />
<HLASY_STRANA KSTRANA="46" HLASY="2" PROC_HLASU="0.77" />
<HLASY_STRANA KSTRANA="47" HLASY="9" PROC_HLASU="3.47" />
<HLASY_STRANA KSTRANA="52" HLASY="1" PROC_HLASU="0.38" />
<HLASY_STRANA KSTRANA="67" HLASY="2" PROC_HLASU="0.77" />
<HLASY_STRANA KSTRANA="68" HLASY="3" PROC_HLASU="1.15" />
<HLASY_STRANA KSTRANA="78" HLASY="14" PROC_HLASU="5.40" />
<HLASY_STRANA KSTRANA="81" HLASY="1" PROC_HLASU="0.38" />
<HLASY_STRANA KSTRANA="82" HLASY="11" PROC_HLASU="4.24" />
</OBEC>
<OBEC CIS_OBEC="552682" NAZ_OBEC="Vyšní Lhoty">
<UCAST OKRSKY_CELKEM="1" OKRSKY_ZPRAC="1" OKRSKY_ZPRAC_PROC="100.00" ZAPSANI_VOLICI="716" VYDANE_OBALKY="229" UCAST_PROC="31.98" ODEVZDANE_OBALKY="228" PLATNE_HLASY="224" PLATNE_HLASY_PROC="98.25" />
<HLASY_STRANA KSTRANA="2" HLASY="12" PROC_HLASU="5.35" />
<HLASY_STRANA KSTRANA="9" HLASY="6" PROC_HLASU="2.67" />
<HLASY_STRANA KSTRANA="12" HLASY="30" PROC_HLASU="13.39" />
<HLASY_STRANA KSTRANA="24" HLASY="27" PROC_HLASU="12.05" />
<HLASY_STRANA KSTRANA="30" HLASY="56" PROC_HLASU="25.00" />
<HLASY_STRANA KSTRANA="32" HLASY="9" PROC_HLASU="4.01" />
<HLASY_STRANA KSTRANA="37" HLASY="26" PROC_HLASU="11.60" />
<HLASY_STRANA KSTRANA="41" HLASY="1" PROC_HLASU="0.44" />
<HLASY_STRANA KSTRANA="43" HLASY="3" PROC_HLASU="1.33" />
<HLASY_STRANA KSTRANA="45" HLASY="1" PROC_HLASU="0.44" />
<HLASY_STRANA KSTRANA="47" HLASY="18" PROC_HLASU="8.03" />
<HLASY_STRANA KSTRANA="52" HLASY="1" PROC_HLASU="0.44" />
<HLASY_STRANA KSTRANA="65" HLASY="2" PROC_HLASU="0.89" />
<HLASY_STRANA KSTRANA="75" HLASY="4" PROC_HLASU="1.78" />
<HLASY_STRANA KSTRANA="78" HLASY="20" PROC_HLASU="8.92" />
<HLASY_STRANA KSTRANA="82" HLASY="8" PROC_HLASU="3.57" />
</OBEC>
<OBEC CIS_OBEC="552691" NAZ_OBEC="Žabeň">
<UCAST OKRSKY_CELKEM="1" OKRSKY_ZPRAC="1" OKRSKY_ZPRAC_PROC="100.00" ZAPSANI_VOLICI="647" VYDANE_OBALKY="271" UCAST_PROC="41.89" ODEVZDANE_OBALKY="271" PLATNE_HLASY="269" PLATNE_HLASY_PROC="99.26" />
<HLASY_STRANA KSTRANA="1" HLASY="1" PROC_HLASU="0.37" />
<HLASY_STRANA KSTRANA="2" HLASY="20" PROC_HLASU="7.43" />
<HLASY_STRANA KSTRANA="9" HLASY="4" PROC_HLASU="1.48" />
<HLASY_STRANA KSTRANA="12" HLASY="39" PROC_HLASU="14.49" />
<HLASY_STRANA KSTRANA="24" HLASY="28" PROC_HLASU="10.40" />
<HLASY_STRANA KSTRANA="30" HLASY="54" PROC_HLASU="20.07" />
<HLASY_STRANA KSTRANA="32" HLASY="9" PROC_HLASU="3.34" />
<HLASY_STRANA KSTRANA="37" HLASY="29" PROC_HLASU="10.78" />
<HLASY_STRANA KSTRANA="43" HLASY="1" PROC_HLASU="0.37" />
<HLASY_STRANA KSTRANA="46" HLASY="4" PROC_HLASU="1.48" />
<HLASY_STRANA KSTRANA="47" HLASY="21" PROC_HLASU="7.80" />
<HLASY_STRANA KSTRANA="52" HLASY="1" PROC_HLASU="0.37" />
<HLASY_STRANA KSTRANA="65" HLASY="5" PROC_HLASU="1.85" />
<HLASY_STRANA KSTRANA="67" HLASY="1" PROC_HLASU="0.37" />
<HLASY_STRANA KSTRANA="68" HLASY="12" PROC_HLASU="4.46" />
<HLASY_STRANA KSTRANA="70" HLASY="1" PROC_HLASU="0.37" />
<HLASY_STRANA KSTRANA="75" HLASY="5" PROC_HLASU="1.85" />
<HLASY_STRANA KSTRANA="78" HLASY="28" PROC_HLASU="10.40" />
<HLASY_STRANA KSTRANA="82" HLASY="6" PROC_HLASU="2.23" />
</OBEC>
<OBEC CIS_OBEC="554014" NAZ_OBEC="Návsí">
<UCAST OKRSKY_CELKEM="3" OKRSKY_ZPRAC="3" OKRSKY_ZPRAC_PROC="100.00" ZAPSANI_VOLICI="3115" VYDANE_OBALKY="975" UCAST_PROC="31.30" ODEVZDANE_OBALKY="975" PLATNE_HLASY="954" PLATNE_HLASY_PROC="97.85" />
<HLASY_STRANA KSTRANA="1" HLASY="12" PROC_HLASU="1.25" />
<HLASY_STRANA KSTRANA="2" HLASY="73" PROC_HLASU="7.65" />
<HLASY_STRANA KSTRANA="9" HLASY="10" PROC_HLASU="1.04" />
<HLASY_STRANA KSTRANA="12" HLASY="271" PROC_HLASU="28.40" />
<HLASY_STRANA KSTRANA="24" HLASY="145" PROC_HLASU="15.19" />
<HLASY_STRANA KSTRANA="26" HLASY="2" PROC_HLASU="0.20" />
<HLASY_STRANA KSTRANA="30" HLASY="161" PROC_HLASU="16.87" />
<HLASY_STRANA KSTRANA="31" HLASY="1" PROC_HLASU="0.10" />
<HLASY_STRANA KSTRANA="32" HLASY="8" PROC_HLASU="0.83" />
<HLASY_STRANA KSTRANA="37" HLASY="52" PROC_HLASU="5.45" />
<HLASY_STRANA KSTRANA="43" HLASY="11" PROC_HLASU="1.15" />
<HLASY_STRANA KSTRANA="45" HLASY="1" PROC_HLASU="0.10" />
<HLASY_STRANA KSTRANA="46" HLASY="19" PROC_HLASU="1.99" />
<HLASY_STRANA KSTRANA="47" HLASY="85" PROC_HLASU="8.90" />
<HLASY_STRANA KSTRANA="52" HLASY="5" PROC_HLASU="0.52" />
<HLASY_STRANA KSTRANA="65" HLASY="6" PROC_HLASU="0.62" />
<HLASY_STRANA KSTRANA="67" HLASY="2" PROC_HLASU="0.20" />
<HLASY_STRANA KSTRANA="68" HLASY="11" PROC_HLASU="1.15" />
<HLASY_STRANA KSTRANA="70" HLASY="1" PROC_HLASU="0.10" />
<HLASY_STRANA KSTRANA="75" HLASY="7" PROC_HLASU="0.73" />
<HLASY_STRANA KSTRANA="78" HLASY="55" PROC_HLASU="5.76" />
<HLASY_STRANA KSTRANA="81" HLASY="2" PROC_HLASU="0.20" />
<HLASY_STRANA KSTRANA="82" HLASY="14" PROC_HLASU="1.46" />
</OBEC>
<OBEC CIS_OBEC="554928" NAZ_OBEC="Vendryně">
<UCAST OKRSKY_CELKEM="4" OKRSKY_ZPRAC="4" OKRSKY_ZPRAC_PROC="100.00" ZAPSANI_VOLICI="3504" VYDANE_OBALKY="1486" UCAST_PROC="42.41" ODEVZDANE_OBALKY="1479" PLATNE_HLASY="1442" PLATNE_HLASY_PROC="97.50" />
<HLASY_STRANA KSTRANA="1" HLASY="4" PROC_HLASU="0.27" />
<HLASY_STRANA KSTRANA="2" HLASY="127" PROC_HLASU="8.80" />
<HLASY_STRANA KSTRANA="9" HLASY="6" PROC_HLASU="0.41" />
<HLASY_STRANA KSTRANA="12" HLASY="315" PROC_HLASU="21.84" />
<HLASY_STRANA KSTRANA="24" HLASY="291" PROC_HLASU="20.18" />
<HLASY_STRANA KSTRANA="28" HLASY="1" PROC_HLASU="0.06" />
<HLASY_STRANA KSTRANA="30" HLASY="305" PROC_HLASU="21.15" />
<HLASY_STRANA KSTRANA="31" HLASY="2" PROC_HLASU="0.13" />
<HLASY_STRANA KSTRANA="32" HLASY="21" PROC_HLASU="1.45" />
<HLASY_STRANA KSTRANA="37" HLASY="68" PROC_HLASU="4.71" />
<HLASY_STRANA KSTRANA="43" HLASY="20" PROC_HLASU="1.38" />
<HLASY_STRANA KSTRANA="45" HLASY="2" PROC_HLASU="0.13" />
<HLASY_STRANA KSTRANA="46" HLASY="25" PROC_HLASU="1.73" />
<HLASY_STRANA KSTRANA="47" HLASY="86" PROC_HLASU="5.96" />
<HLASY_STRANA KSTRANA="52" HLASY="7" PROC_HLASU="0.48" />
<HLASY_STRANA KSTRANA="65" HLASY="5" PROC_HLASU="0.34" />
<HLASY_STRANA KSTRANA="67" HLASY="3" PROC_HLASU="0.20" />
<HLASY_STRANA KSTRANA="68" HLASY="35" PROC_HLASU="2.42" />
<HLASY_STRANA KSTRANA="75" HLASY="10" PROC_HLASU="0.69" />
<HLASY_STRANA KSTRANA="78" HLASY="72" PROC_HLASU="4.99" />
<HLASY_STRANA KSTRANA="81" HLASY="1" PROC_HLASU="0.06" />
<HLASY_STRANA KSTRANA="82" HLASY="36" PROC_HLASU="2.49" />
</OBEC>
<OBEC CIS_OBEC="556971" NAZ_OBEC="Ropice">
<UCAST OKRSKY_CELKEM="1" OKRSKY_ZPRAC="1" OKRSKY_ZPRAC_PROC="100.00" ZAPSANI_VOLICI="1260" VYDANE_OBALKY="450" UCAST_PROC="35.71" ODEVZDANE_OBALKY="445" PLATNE_HLASY="439" PLATNE_HLASY_PROC="98.65" />
<HLASY_STRANA KSTRANA="1" HLASY="2" PROC_HLASU="0.45" />
<HLASY_STRANA KSTRANA="2" HLASY="25" PROC_HLASU="5.69" />
<HLASY_STRANA KSTRANA="9" HLASY="4" PROC_HLASU="0.91" />
<HLASY_STRANA KSTRANA="12" HLASY="80" PROC_HLASU="18.22" />
<HLASY_STRANA KSTRANA="24" HLASY="115" PROC_HLASU="26.19" />
<HLASY_STRANA KSTRANA="30" HLASY="95" PROC_HLASU="21.64" />
<HLASY_STRANA KSTRANA="31" HLASY="1" PROC_HLASU="0.22" />
<HLASY_STRANA KSTRANA="32" HLASY="6" PROC_HLASU="1.36" />
<HLASY_STRANA KSTRANA="37" HLASY="23" PROC_HLASU="5.23" />
<HLASY_STRANA KSTRANA="41" HLASY="2" PROC_HLASU="0.45" />
<HLASY_STRANA KSTRANA="43" HLASY="10" PROC_HLASU="2.27" />
<HLASY_STRANA KSTRANA="45" HLASY="1" PROC_HLASU="0.22" />
<HLASY_STRANA KSTRANA="46" HLASY="10" PROC_HLASU="2.27" />
<HLASY_STRANA KSTRANA="47" HLASY="8" PROC_HLASU="1.82" />
<HLASY_STRANA KSTRANA="52" HLASY="3" PROC_HLASU="0.68" />
<HLASY_STRANA KSTRANA="65" HLASY="7" PROC_HLASU="1.59" />
<HLASY_STRANA KSTRANA="67" HLASY="1" PROC_HLASU="0.22" />
<HLASY_STRANA KSTRANA="68" HLASY="7" PROC_HLASU="1.59" />
<HLASY_STRANA KSTRANA="70" HLASY="1" PROC_HLASU="0.22" />
<HLASY_STRANA KSTRANA="75" HLASY="1" PROC_HLASU="0.22" />
<HLASY_STRANA KSTRANA="78" HLASY="27" PROC_HLASU="6.15" />
<HLASY_STRANA KSTRANA="82" HLASY="10" PROC_HLASU="2.27" />
</OBEC>
<OBEC CIS_OBEC="557226" NAZ_OBEC="Písečná">
<UCAST OKRSKY_CELKEM="1" OKRSKY_ZPRAC="1" OKRSKY_ZPRAC_PROC="100.00" ZAPSANI_VOLICI="752" VYDANE_OBALKY="325" UCAST_PROC="43.22" ODEVZDANE_OBALKY="322" PLATNE_HLASY="314" PLATNE_HLASY_PROC="97.52" />
<HLASY_STRANA KSTRANA="1" HLASY="2" PROC_HLASU="0.63" />
<HLASY_STRANA KSTRANA="2" HLASY="18" PROC_HLASU="5.73" />
<HLASY_STRANA KSTRANA="9" HLASY="3" PROC_HLASU="0.95" />
<HLASY_STRANA KSTRANA="12" HLASY="71" PROC_HLASU="22.61" />
<HLASY_STRANA KSTRANA="24" HLASY="60" PROC_HLASU="19.10" />
<HLASY_STRANA KSTRANA="30" HLASY="56" PROC_HLASU="17.83" />
<HLASY_STRANA KSTRANA="31" HLASY="1" PROC_HLASU="0.31" />
<HLASY_STRANA KSTRANA="37" HLASY="10" PROC_HLASU="3.18" />
<HLASY_STRANA KSTRANA="43" HLASY="1" PROC_HLASU="0.31" />
<HLASY_STRANA KSTRANA="47" HLASY="62" PROC_HLASU="19.74" />
<HLASY_STRANA KSTRANA="52" HLASY="7" PROC_HLASU="2.22" />
<HLASY_STRANA KSTRANA="67" HLASY="2" PROC_HLASU="0.63" />
<HLASY_STRANA KSTRANA="68" HLASY="5" PROC_HLASU="1.59" />
<HLASY_STRANA KSTRANA="75" HLASY="1" PROC_HLASU="0.31" />
<HLASY_STRANA KSTRANA="78" HLASY="7" PROC_HLASU="2.22" />
<HLASY_STRANA KSTRANA="82" HLASY="8" PROC_HLASU="2.54" />
</OBEC>
<OBEC CIS_OBEC="568163" NAZ_OBEC="Žermanice">
<UCAST OKRSKY_CELKEM="1" OKRSKY_ZPRAC="1" OKRSKY_ZPRAC_PROC="100.00" ZAPSANI_VOLICI="263" VYDANE_OBALKY="76" UCAST_PROC="28.90" ODEVZDANE_OBALKY="76" PLATNE_HLASY="73" PLATNE_HLASY_PROC="96.05" />
<HLASY_STRANA KSTRANA="2" HLASY="3" PROC_HLASU="4.10" />
<HLASY_STRANA KSTRANA="9" HLASY="1" PROC_HLASU="1.36" />
<HLASY_STRANA KSTRANA="12" HLASY="10" PROC_HLASU="13.69" />
<HLASY_STRANA KSTRANA="30" HLASY="20" PROC_HLASU="27.39" />
<HLASY_STRANA KSTRANA="32" HLASY="1" PROC_HLASU="1.36" />
<HLASY_STRANA KSTRANA="37" HLASY="8" PROC_HLASU="10.95" />
<HLASY_STRANA KSTRANA="45" HLASY="2" PROC_HLASU="2.73" />
<HLASY_STRANA KSTRANA="46" HLASY="2" PROC_HLASU="2.73" />
<HLASY_STRANA KSTRANA="52" HLASY="5" PROC_HLASU="6.84" />
<HLASY_STRANA KSTRANA="68" HLASY="4" PROC_HLASU="5.47" />
<HLASY_STRANA KSTRANA="78" HLASY="11" PROC_HLASU="15.06" />
<HLASY_STRANA KSTRANA="82" HLASY="6" PROC_HLASU="8.21" />
</OBEC>
<OBEC CIS_OBEC="568791" NAZ_OBEC="Soběšovice">
<UCAST OKRSKY_CELKEM="1" OKRSKY_ZPRAC="1" OKRSKY_ZPRAC_PROC="100.00" ZAPSANI_VOLICI="748" VYDANE_OBALKY="247" UCAST_PROC="33.02" ODEVZDANE_OBALKY="247" PLATNE_HLASY="242" PLATNE_HLASY_PROC="97.98" />
<HLASY_STRANA KSTRANA="2" HLASY="9" PROC_HLASU="3.71" />
<HLASY_STRANA KSTRANA="9" HLASY="5" PROC_HLASU="2.06" />
<HLASY_STRANA KSTRANA="12" HLASY="33" PROC_HLASU="13.63" />
<HLASY_STRANA KSTRANA="24" HLASY="29" PROC_HLASU="11.98" />
<HLASY_STRANA KSTRANA="30" HLASY="78" PROC_HLASU="32.23" />
<HLASY_STRANA KSTRANA="31" HLASY="3" PROC_HLASU="1.23" />
<HLASY_STRANA KSTRANA="32" HLASY="6" PROC_HLASU="2.47" />
<HLASY_STRANA KSTRANA="37" HLASY="25" PROC_HLASU="10.33" />
<HLASY_STRANA KSTRANA="43" HLASY="2" PROC_HLASU="0.82" />
<HLASY_STRANA KSTRANA="46" HLASY="1" PROC_HLASU="0.41" />
<HLASY_STRANA KSTRANA="47" HLASY="4" PROC_HLASU="1.65" />
<HLASY_STRANA KSTRANA="52" HLASY="4" PROC_HLASU="1.65" />
<HLASY_STRANA KSTRANA="65" HLASY="1" PROC_HLASU="0.41" />
<HLASY_STRANA KSTRANA="68" HLASY="14" PROC_HLASU="5.78" />
<HLASY_STRANA KSTRANA="70" HLASY="1" PROC_HLASU="0.41" />
<HLASY_STRANA KSTRANA="75" HLASY="1" PROC_HLASU="0.41" />
<HLASY_STRANA KSTRANA="78" HLASY="16" PROC_HLASU="6.61" />
<HLASY_STRANA KSTRANA="82" HLASY="10" PROC_HLASU="4.13" />
</OBEC>
<OBEC CIS_OBEC="568813" NAZ_OBEC="Pražmo">
<UCAST OKRSKY_CELKEM="1" OKRSKY_ZPRAC="1" OKRSKY_ZPRAC_PROC="100.00" ZAPSANI_VOLICI="751" VYDANE_OBALKY="247" UCAST_PROC="32.89" ODEVZDANE_OBALKY="247" PLATNE_HLASY="244" PLATNE_HLASY_PROC="98.79" />
<HLASY_STRANA KSTRANA="2" HLASY="10" PROC_HLASU="4.09" />
<HLASY_STRANA KSTRANA="9" HLASY="4" PROC_HLASU="1.63" />
<HLASY_STRANA KSTRANA="12" HLASY="24" PROC_HLASU="9.83" />
<HLASY_STRANA KSTRANA="24" HLASY="42" PROC_HLASU="17.21" />
<HLASY_STRANA KSTRANA="30" HLASY="62" PROC_HLASU="25.40" />
<HLASY_STRANA KSTRANA="31" HLASY="1" PROC_HLASU="0.40" />
<HLASY_STRANA KSTRANA="32" HLASY="3" PROC_HLASU="1.22" />
<HLASY_STRANA KSTRANA="37" HLASY="40" PROC_HLASU="16.39" />
<HLASY_STRANA KSTRANA="43" HLASY="4" PROC_HLASU="1.63" />
<HLASY_STRANA KSTRANA="46" HLASY="2" PROC_HLASU="0.81" />
<HLASY_STRANA KSTRANA="47" HLASY="16" PROC_HLASU="6.55" />
<HLASY_STRANA KSTRANA="52" HLASY="2" PROC_HLASU="0.81" />
<HLASY_STRANA KSTRANA="65" HLASY="2" PROC_HLASU="0.81" />
<HLASY_STRANA KSTRANA="68" HLASY="5" PROC_HLASU="2.04" />
<HLASY_STRANA KSTRANA="78" HLASY="17" PROC_HLASU="6.96" />
<HLASY_STRANA KSTRANA="82" HLASY="10" PROC_HLASU="4.09" />
</OBEC>
<OBEC CIS_OBEC="568830" NAZ_OBEC="Řepiště">
<UCAST OKRSKY_CELKEM="1" OKRSKY_ZPRAC="1" OKRSKY_ZPRAC_PROC="100.00" ZAPSANI_VOLICI="1444" VYDANE_OBALKY="585" UCAST_PROC="40.51" ODEVZDANE_OBALKY="585" PLATNE_HLASY="578" PLATNE_HLASY_PROC="98.80" />
<HLASY_STRANA KSTRANA="1" HLASY="4" PROC_HLASU="0.69" />
<HLASY_STRANA KSTRANA="2" HLASY="46" PROC_HLASU="7.95" />
<HLASY_STRANA KSTRANA="9" HLASY="4" PROC_HLASU="0.69" />
<HLASY_STRANA KSTRANA="12" HLASY="87" PROC_HLASU="15.05" />
<HLASY_STRANA KSTRANA="24" HLASY="39" PROC_HLASU="6.74" />
<HLASY_STRANA KSTRANA="26" HLASY="1" PROC_HLASU="0.17" />
<HLASY_STRANA KSTRANA="30" HLASY="155" PROC_HLASU="26.81" />
<HLASY_STRANA KSTRANA="31" HLASY="1" PROC_HLASU="0.17" />
<HLASY_STRANA KSTRANA="32" HLASY="27" PROC_HLASU="4.67" />
<HLASY_STRANA KSTRANA="37" HLASY="77" PROC_HLASU="13.32" />
<HLASY_STRANA KSTRANA="43" HLASY="9" PROC_HLASU="1.55" />
<HLASY_STRANA KSTRANA="45" HLASY="4" PROC_HLASU="0.69" />
<HLASY_STRANA KSTRANA="46" HLASY="5" PROC_HLASU="0.86" />
<HLASY_STRANA KSTRANA="47" HLASY="28" PROC_HLASU="4.84" />
<HLASY_STRANA KSTRANA="52" HLASY="13" PROC_HLASU="2.24" />
<HLASY_STRANA KSTRANA="65" HLASY="5" PROC_HLASU="0.86" />
<HLASY_STRANA KSTRANA="68" HLASY="18" PROC_HLASU="3.11" />
<HLASY_STRANA KSTRANA="70" HLASY="1" PROC_HLASU="0.17" />
<HLASY_STRANA KSTRANA="75" HLASY="2" PROC_HLASU="0.34" />
<HLASY_STRANA KSTRANA="78" HLASY="41" PROC_HLASU="7.09" />
<HLASY_STRANA KSTRANA="82" HLASY="11" PROC_HLASU="1.90" />
</OBEC>
<OBEC CIS_OBEC="569631" NAZ_OBEC="Sviadnov">
<UCAST OKRSKY_CELKEM="1" OKRSKY_ZPRAC="1" OKRSKY_ZPRAC_PROC="100.00" ZAPSANI_VOLICI="1485" VYDANE_OBALKY="575" UCAST_PROC="38.72" ODEVZDANE_OBALKY="575" PLATNE_HLASY="561" PLATNE_HLASY_PROC="97.57" />
<HLASY_STRANA KSTRANA="2" HLASY="65" PROC_HLASU="11.58" />
<HLASY_STRANA KSTRANA="9" HLASY="12" PROC_HLASU="2.13" />
<HLASY_STRANA KSTRANA="12" HLASY="81" PROC_HLASU="14.43" />
<HLASY_STRANA KSTRANA="24" HLASY="49" PROC_HLASU="8.73" />
<HLASY_STRANA KSTRANA="26" HLASY="4" PROC_HLASU="0.71" />
<HLASY_STRANA KSTRANA="30" HLASY="142" PROC_HLASU="25.31" />
<HLASY_STRANA KSTRANA="31" HLASY="2" PROC_HLASU="0.35" />
<HLASY_STRANA KSTRANA="32" HLASY="13" PROC_HLASU="2.31" />
<HLASY_STRANA KSTRANA="37" HLASY="47" PROC_HLASU="8.37" />
<HLASY_STRANA KSTRANA="43" HLASY="6" PROC_HLASU="1.06" />
<HLASY_STRANA KSTRANA="45" HLASY="1" PROC_HLASU="0.17" />
<HLASY_STRANA KSTRANA="46" HLASY="3" PROC_HLASU="0.53" />
<HLASY_STRANA KSTRANA="47" HLASY="21" PROC_HLASU="3.74" />
<HLASY_STRANA KSTRANA="52" HLASY="9" PROC_HLASU="1.60" />
<HLASY_STRANA KSTRANA="65" HLASY="8" PROC_HLASU="1.42" />
<HLASY_STRANA KSTRANA="68" HLASY="49" PROC_HLASU="8.73" />
<HLASY_STRANA KSTRANA="70" HLASY="3" PROC_HLASU="0.53" />
<HLASY_STRANA KSTRANA="75" HLASY="4" PROC_HLASU="0.71" />
<HLASY_STRANA KSTRANA="78" HLASY="33" PROC_HLASU="5.88" />
<HLASY_STRANA KSTRANA="82" HLASY="9" PROC_HLASU="1.60" />
</OBEC>
<OBEC CIS_OBEC="598003" NAZ_OBEC="Frýdek-Místek">
<UCAST OKRSKY_CELKEM="57" OKRSKY_ZPRAC="57" OKRSKY_ZPRAC_PROC="100.00" ZAPSANI_VOLICI="46656" VYDANE_OBALKY="13391" UCAST_PROC="28.70" ODEVZDANE_OBALKY="13382" PLATNE_HLASY="13189" PLATNE_HLASY_PROC="98.56" />
<HLASY_STRANA KSTRANA="1" HLASY="21" PROC_HLASU="0.15" />
<HLASY_STRANA KSTRANA="2" HLASY="759" PROC_HLASU="5.75" />
<HLASY_STRANA KSTRANA="9" HLASY="145" PROC_HLASU="1.09" />
<HLASY_STRANA KSTRANA="12" HLASY="2197" PROC_HLASU="16.65" />
<HLASY_STRANA KSTRANA="24" HLASY="1528" PROC_HLASU="11.58" />
<HLASY_STRANA KSTRANA="26" HLASY="34" PROC_HLASU="0.25" />
<HLASY_STRANA KSTRANA="28" HLASY="3" PROC_HLASU="0.02" />
<HLASY_STRANA KSTRANA="30" HLASY="3705" PROC_HLASU="28.09" />
<HLASY_STRANA KSTRANA="31" HLASY="36" PROC_HLASU="0.27" />
<HLASY_STRANA KSTRANA="32" HLASY="447" PROC_HLASU="3.38" />
<HLASY_STRANA KSTRANA="37" HLASY="1556" PROC_HLASU="11.79" />
<HLASY_STRANA KSTRANA="41" HLASY="16" PROC_HLASU="0.12" />
<HLASY_STRANA KSTRANA="43" HLASY="199" PROC_HLASU="1.50" />
<HLASY_STRANA KSTRANA="45" HLASY="39" PROC_HLASU="0.29" />
<HLASY_STRANA KSTRANA="46" HLASY="147" PROC_HLASU="1.11" />
<HLASY_STRANA KSTRANA="47" HLASY="313" PROC_HLASU="2.37" />
<HLASY_STRANA KSTRANA="52" HLASY="140" PROC_HLASU="1.06" />
<HLASY_STRANA KSTRANA="65" HLASY="113" PROC_HLASU="0.85" />
<HLASY_STRANA KSTRANA="67" HLASY="37" PROC_HLASU="0.28" />
<HLASY_STRANA KSTRANA="68" HLASY="194" PROC_HLASU="1.47" />
<HLASY_STRANA KSTRANA="70" HLASY="21" PROC_HLASU="0.15" />
<HLASY_STRANA KSTRANA="75" HLASY="74" PROC_HLASU="0.56" />
<HLASY_STRANA KSTRANA="78" HLASY="1004" PROC_HLASU="7.61" />
<HLASY_STRANA KSTRANA="81" HLASY="7" PROC_HLASU="0.05" />
<HLASY_STRANA KSTRANA="82" HLASY="454" PROC_HLASU="3.44" />
</OBEC>
<OBEC CIS_OBEC="598011" NAZ_OBEC="Baška">
<UCAST OKRSKY_CELKEM="3" OKRSKY_ZPRAC="3" OKRSKY_ZPRAC_PROC="100.00" ZAPSANI_VOLICI="3096" VYDANE_OBALKY="1129" UCAST_PROC="36.47" ODEVZDANE_OBALKY="1116" PLATNE_HLASY="1100" PLATNE_HLASY_PROC="98.57" />
<HLASY_STRANA KSTRANA="1" HLASY="1" PROC_HLASU="0.09" />
<HLASY_STRANA KSTRANA="2" HLASY="75" PROC_HLASU="6.81" />
<HLASY_STRANA KSTRANA="9" HLASY="6" PROC_HLASU="0.54" />
<HLASY_STRANA KSTRANA="12" HLASY="121" PROC_HLASU="11.00" />
<HLASY_STRANA KSTRANA="24" HLASY="240" PROC_HLASU="21.81" />
<HLASY_STRANA KSTRANA="26" HLASY="4" PROC_HLASU="0.36" />
<HLASY_STRANA KSTRANA="30" HLASY="254" PROC_HLASU="23.09" />
<HLASY_STRANA KSTRANA="31" HLASY="2" PROC_HLASU="0.18" />
<HLASY_STRANA KSTRANA="32" HLASY="43" PROC_HLASU="3.90" />
<HLASY_STRANA KSTRANA="37" HLASY="159" PROC_HLASU="14.45" />
<HLASY_STRANA KSTRANA="43" HLASY="14" PROC_HLASU="1.27" />
<HLASY_STRANA KSTRANA="45" HLASY="5" PROC_HLASU="0.45" />
<HLASY_STRANA KSTRANA="46" HLASY="15" PROC_HLASU="1.36" />
<HLASY_STRANA KSTRANA="47" HLASY="26" PROC_HLASU="2.36" />
<HLASY_STRANA KSTRANA="52" HLASY="18" PROC_HLASU="1.63" />
<HLASY_STRANA KSTRANA="65" HLASY="6" PROC_HLASU="0.54" />
<HLASY_STRANA KSTRANA="67" HLASY="4" PROC_HLASU="0.36" />
<HLASY_STRANA KSTRANA="68" HLASY="10" PROC_HLASU="0.90" />
<HLASY_STRANA KSTRANA="70" HLASY="2" PROC_HLASU="0.18" />
<HLASY_STRANA KSTRANA="75" HLASY="3" PROC_HLASU="0.27" />
<HLASY_STRANA KSTRANA="78" HLASY="68" PROC_HLASU="6.18" />
<HLASY_STRANA KSTRANA="82" HLASY="24" PROC_HLASU="2.18" />
</OBEC>
<OBEC CIS_OBEC="598020" NAZ_OBEC="Bílá">
<UCAST OKRSKY_CELKEM="1" OKRSKY_ZPRAC="1" OKRSKY_ZPRAC_PROC="100.00" ZAPSANI_VOLICI="255" VYDANE_OBALKY="91" UCAST_PROC="35.69" ODEVZDANE_OBALKY="91" PLATNE_HLASY="89" PLATNE_HLASY_PROC="97.80" />
<HLASY_STRANA KSTRANA="2" HLASY="7" PROC_HLASU="7.86" />
<HLASY_STRANA KSTRANA="12" HLASY="14" PROC_HLASU="15.73" />
<HLASY_STRANA KSTRANA="24" HLASY="13" PROC_HLASU="14.60" />
<HLASY_STRANA KSTRANA="30" HLASY="21" PROC_HLASU="23.59" />
<HLASY_STRANA KSTRANA="32" HLASY="1" PROC_HLASU="1.12" />
<HLASY_STRANA KSTRANA="37" HLASY="12" PROC_HLASU="13.48" />
<HLASY_STRANA KSTRANA="43" HLASY="2" PROC_HLASU="2.24" />
<HLASY_STRANA KSTRANA="46" HLASY="2" PROC_HLASU="2.24" />
<HLASY_STRANA KSTRANA="47" HLASY="5" PROC_HLASU="5.61" />
<HLASY_STRANA KSTRANA="75" HLASY="2" PROC_HLASU="2.24" />
<HLASY_STRANA KSTRANA="78" HLASY="8" PROC_HLASU="8.98" />
<HLASY_STRANA KSTRANA="81" HLASY="1" PROC_HLASU="1.12" />
<HLASY_STRANA KSTRANA="82" HLASY="1" PROC_HLASU="1.12" />
</OBEC>
<OBEC CIS_OBEC="598038" NAZ_OBEC="Brušperk">
<UCAST OKRSKY_CELKEM="3" OKRSKY_ZPRAC="3" OKRSKY_ZPRAC_PROC="100.00" ZAPSANI_VOLICI="3268" VYDANE_OBALKY="1307" UCAST_PROC="39.99" ODEVZDANE_OBALKY="1306" PLATNE_HLASY="1294" PLATNE_HLASY_PROC="99.08" />
<HLASY_STRANA KSTRANA="2" HLASY="133" PROC_HLASU="10.27" />
<HLASY_STRANA KSTRANA="9" HLASY="14" PROC_HLASU="1.08" />
<HLASY_STRANA KSTRANA="12" HLASY="207" PROC_HLASU="15.99" />
<HLASY_STRANA KSTRANA="24" HLASY="135" PROC_HLASU="10.43" />
<HLASY_STRANA KSTRANA="26" HLASY="1" PROC_HLASU="0.07" />
<HLASY_STRANA KSTRANA="28" HLASY="4" PROC_HLASU="0.30" />
<HLASY_STRANA KSTRANA="30" HLASY="326" PROC_HLASU="25.19" />
<HLASY_STRANA KSTRANA="31" HLASY="7" PROC_HLASU="0.54" />
<HLASY_STRANA KSTRANA="32" HLASY="34" PROC_HLASU="2.62" />
<HLASY_STRANA KSTRANA="37" HLASY="178" PROC_HLASU="13.75" />
<HLASY_STRANA KSTRANA="43" HLASY="27" PROC_HLASU="2.08" />
<HLASY_STRANA KSTRANA="45" HLASY="6" PROC_HLASU="0.46" />
<HLASY_STRANA KSTRANA="46" HLASY="8" PROC_HLASU="0.61" />
<HLASY_STRANA KSTRANA="47" HLASY="26" PROC_HLASU="2.00" />
<HLASY_STRANA KSTRANA="52" HLASY="19" PROC_HLASU="1.46" />
<HLASY_STRANA KSTRANA="65" HLASY="20" PROC_HLASU="1.54" />
<HLASY_STRANA KSTRANA="68" HLASY="32" PROC_HLASU="2.47" />
<HLASY_STRANA KSTRANA="70" HLASY="1" PROC_HLASU="0.07" />
<HLASY_STRANA KSTRANA="75" HLASY="4" PROC_HLASU="0.30" />
<HLASY_STRANA KSTRANA="78" HLASY="79" PROC_HLASU="6.10" />
<HLASY_STRANA KSTRANA="81" HLASY="2" PROC_HLASU="0.15" />
<HLASY_STRANA KSTRANA="82" HLASY="31" PROC_HLASU="2.39" />
</OBEC>
<OBEC CIS_OBEC="598046" NAZ_OBEC="Bruzovice">
<UCAST OKRSKY_CELKEM="1" OKRSKY_ZPRAC="1" OKRSKY_ZPRAC_PROC="100.00" ZAPSANI_VOLICI="680" VYDANE_OBALKY="238" UCAST_PROC="35.00" ODEVZDANE_OBALKY="238" PLATNE_HLASY="235" PLATNE_HLASY_PROC="98.74" />
<HLASY_STRANA KSTRANA="2" HLASY="10" PROC_HLASU="4.25" />
<HLASY_STRANA KSTRANA="9" HLASY="5" PROC_HLASU="2.12" />
<HLASY_STRANA KSTRANA="12" HLASY="45" PROC_HLASU="19.14" />
<HLASY_STRANA KSTRANA="24" HLASY="37" PROC_HLASU="15.74" />
<HLASY_STRANA KSTRANA="26" HLASY="4" PROC_HLASU="1.70" />
<HLASY_STRANA KSTRANA="28" HLASY="3" PROC_HLASU="1.27" />
<HLASY_STRANA KSTRANA="30" HLASY="41" PROC_HLASU="17.44" />
<HLASY_STRANA KSTRANA="32" HLASY="7" PROC_HLASU="2.97" />
<HLASY_STRANA KSTRANA="37" HLASY="20" PROC_HLASU="8.51" />
<HLASY_STRANA KSTRANA="43" HLASY="2" PROC_HLASU="0.85" />
<HLASY_STRANA KSTRANA="46" HLASY="3" PROC_HLASU="1.27" />
<HLASY_STRANA KSTRANA="47" HLASY="12" PROC_HLASU="5.10" />
<HLASY_STRANA KSTRANA="52" HLASY="7" PROC_HLASU="2.97" />
<HLASY_STRANA KSTRANA="67" HLASY="1" PROC_HLASU="0.42" />
<HLASY_STRANA KSTRANA="68" HLASY="7" PROC_HLASU="2.97" />
<HLASY_STRANA KSTRANA="75" HLASY="4" PROC_HLASU="1.70" />
<HLASY_STRANA KSTRANA="78" HLASY="22" PROC_HLASU="9.36" />
<HLASY_STRANA KSTRANA="82" HLASY="5" PROC_HLASU="2.12" />
</OBEC>
<OBEC CIS_OBEC="598062" NAZ_OBEC="Bystřice">
<UCAST OKRSKY_CELKEM="5" OKRSKY_ZPRAC="5" OKRSKY_ZPRAC_PROC="100.00" ZAPSANI_VOLICI="4236" VYDANE_OBALKY="1400" UCAST_PROC="33.05" ODEVZDANE_OBALKY="1394" PLATNE_HLASY="1360" PLATNE_HLASY_PROC="97.56" />
<HLASY_STRANA KSTRANA="1" HLASY="2" PROC_HLASU="0.14" />
<HLASY_STRANA KSTRANA="2" HLASY="129" PROC_HLASU="9.48" />
<HLASY_STRANA KSTRANA="9" HLASY="7" PROC_HLASU="0.51" />
<HLASY_STRANA KSTRANA="12" HLASY="463" PROC_HLASU="34.04" />
<HLASY_STRANA KSTRANA="24" HLASY="195" PROC_HLASU="14.33" />
<HLASY_STRANA KSTRANA="30" HLASY="216" PROC_HLASU="15.88" />
<HLASY_STRANA KSTRANA="32" HLASY="34" PROC_HLASU="2.50" />
<HLASY_STRANA KSTRANA="37" HLASY="68" PROC_HLASU="5.00" />
<HLASY_STRANA KSTRANA="41" HLASY="2" PROC_HLASU="0.14" />
<HLASY_STRANA KSTRANA="43" HLASY="27" PROC_HLASU="1.98" />
<HLASY_STRANA KSTRANA="45" HLASY="1" PROC_HLASU="0.07" />
<HLASY_STRANA KSTRANA="46" HLASY="21" PROC_HLASU="1.54" />
<HLASY_STRANA KSTRANA="47" HLASY="59" PROC_HLASU="4.33" />
<HLASY_STRANA KSTRANA="52" HLASY="7" PROC_HLASU="0.51" />
<HLASY_STRANA KSTRANA="65" HLASY="9" PROC_HLASU="0.66" />
<HLASY_STRANA KSTRANA="68" HLASY="7" PROC_HLASU="0.51" />
<HLASY_STRANA KSTRANA="70" HLASY="1" PROC_HLASU="0.07" />
<HLASY_STRANA KSTRANA="75" HLASY="10" PROC_HLASU="0.73" />
<HLASY_STRANA KSTRANA="78" HLASY="68" PROC_HLASU="5.00" />
<HLASY_STRANA KSTRANA="81" HLASY="2" PROC_HLASU="0.14" />
<HLASY_STRANA KSTRANA="82" HLASY="32" PROC_HLASU="2.35" />
</OBEC>
<OBEC CIS_OBEC="598071" NAZ_OBEC="Čeladná">
<UCAST OKRSKY_CELKEM="4" OKRSKY_ZPRAC="4" OKRSKY_ZPRAC_PROC="100.00" ZAPSANI_VOLICI="2213" VYDANE_OBALKY="978" UCAST_PROC="44.19" ODEVZDANE_OBALKY="978" PLATNE_HLASY="970" PLATNE_HLASY_PROC="99.18" />
<HLASY_STRANA KSTRANA="1" HLASY="2" PROC_HLASU="0.20" />
<HLASY_STRANA KSTRANA="2" HLASY="63" PROC_HLASU="6.49" />
<HLASY_STRANA KSTRANA="9" HLASY="1" PROC_HLASU="0.10" />
<HLASY_STRANA KSTRANA="12" HLASY="90" PROC_HLASU="9.27" />
<HLASY_STRANA KSTRANA="24" HLASY="77" PROC_HLASU="7.93" />
<HLASY_STRANA KSTRANA="30" HLASY="171" PROC_HLASU="17.62" />
<HLASY_STRANA KSTRANA="31" HLASY="3" PROC_HLASU="0.30" />
<HLASY_STRANA KSTRANA="32" HLASY="32" PROC_HLASU="3.29" />
<HLASY_STRANA KSTRANA="37" HLASY="75" PROC_HLASU="7.73" />
<HLASY_STRANA KSTRANA="41" HLASY="4" PROC_HLASU="0.41" />
<HLASY_STRANA KSTRANA="43" HLASY="1" PROC_HLASU="0.10" />
<HLASY_STRANA KSTRANA="45" HLASY="1" PROC_HLASU="0.10" />
<HLASY_STRANA KSTRANA="46" HLASY="270" PROC_HLASU="27.83" />
<HLASY_STRANA KSTRANA="47" HLASY="26" PROC_HLASU="2.68" />
<HLASY_STRANA KSTRANA="52" HLASY="29" PROC_HLASU="2.98" />
<HLASY_STRANA KSTRANA="65" HLASY="12" PROC_HLASU="1.23" />
<HLASY_STRANA KSTRANA="67" HLASY="5" PROC_HLASU="0.51" />
<HLASY_STRANA KSTRANA="68" HLASY="12" PROC_HLASU="1.23" />
<HLASY_STRANA KSTRANA="75" HLASY="5" PROC_HLASU="0.51" />
<HLASY_STRANA KSTRANA="78" HLASY="60" PROC_HLASU="6.18" />
<HLASY_STRANA KSTRANA="82" HLASY="31" PROC_HLASU="3.19" />
</OBEC>
<OBEC CIS_OBEC="598089" NAZ_OBEC="Dobrá">
<UCAST OKRSKY_CELKEM="2" OKRSKY_ZPRAC="2" OKRSKY_ZPRAC_PROC="100.00" ZAPSANI_VOLICI="2551" VYDANE_OBALKY="1015" UCAST_PROC="39.79" ODEVZDANE_OBALKY="1014" PLATNE_HLASY="994" PLATNE_HLASY_PROC="98.03" />
<HLASY_STRANA KSTRANA="1" HLASY="1" PROC_HLASU="0.10" />
<HLASY_STRANA KSTRANA="2" HLASY="40" PROC_HLASU="4.02" />
<HLASY_STRANA KSTRANA="9" HLASY="9" PROC_HLASU="0.90" />
<HLASY_STRANA KSTRANA="12" HLASY="141" PROC_HLASU="14.18" />
<HLASY_STRANA KSTRANA="24" HLASY="271" PROC_HLASU="27.26" />
<HLASY_STRANA KSTRANA="26" HLASY="2" PROC_HLASU="0.20" />
<HLASY_STRANA KSTRANA="30" HLASY="247" PROC_HLASU="24.84" />
<HLASY_STRANA KSTRANA="31" HLASY="1" PROC_HLASU="0.10" />
<HLASY_STRANA KSTRANA="32" HLASY="23" PROC_HLASU="2.31" />
<HLASY_STRANA KSTRANA="37" HLASY="93" PROC_HLASU="9.35" />
<HLASY_STRANA KSTRANA="43" HLASY="14" PROC_HLASU="1.40" />
<HLASY_STRANA KSTRANA="45" HLASY="1" PROC_HLASU="0.10" />
<HLASY_STRANA KSTRANA="46" HLASY="3" PROC_HLASU="0.30" />
<HLASY_STRANA KSTRANA="47" HLASY="25" PROC_HLASU="2.51" />
<HLASY_STRANA KSTRANA="52" HLASY="16" PROC_HLASU="1.60" />
<HLASY_STRANA KSTRANA="65" HLASY="12" PROC_HLASU="1.20" />
<HLASY_STRANA KSTRANA="68" HLASY="13" PROC_HLASU="1.30" />
<HLASY_STRANA KSTRANA="70" HLASY="1" PROC_HLASU="0.10" />
<HLASY_STRANA KSTRANA="75" HLASY="2" PROC_HLASU="0.20" />
<HLASY_STRANA KSTRANA="78" HLASY="59" PROC_HLASU="5.93" />
<HLASY_STRANA KSTRANA="82" HLASY="20" PROC_HLASU="2.01" />
</OBEC>
<OBEC CIS_OBEC="598101" NAZ_OBEC="Dolní Domaslavice">
<UCAST OKRSKY_CELKEM="1" OKRSKY_ZPRAC="1" OKRSKY_ZPRAC_PROC="100.00" ZAPSANI_VOLICI="1075" VYDANE_OBALKY="330" UCAST_PROC="30.70" ODEVZDANE_OBALKY="328" PLATNE_HLASY="322" PLATNE_HLASY_PROC="98.17" />
<HLASY_STRANA KSTRANA="1" HLASY="2" PROC_HLASU="0.62" />
<HLASY_STRANA KSTRANA="2" HLASY="27" PROC_HLASU="8.38" />
<HLASY_STRANA KSTRANA="9" HLASY="11" PROC_HLASU="3.41" />
<HLASY_STRANA KSTRANA="12" HLASY="33" PROC_HLASU="10.24" />
<HLASY_STRANA KSTRANA="24" HLASY="52" PROC_HLASU="16.14" />
<HLASY_STRANA KSTRANA="30" HLASY="69" PROC_HLASU="21.42" />
<HLASY_STRANA KSTRANA="32" HLASY="11" PROC_HLASU="3.41" />
<HLASY_STRANA KSTRANA="37" HLASY="34" PROC_HLASU="10.55" />
<HLASY_STRANA KSTRANA="41" HLASY="2" PROC_HLASU="0.62" />
<HLASY_STRANA KSTRANA="43" HLASY="6" PROC_HLASU="1.86" />
<HLASY_STRANA KSTRANA="45" HLASY="1" PROC_HLASU="0.31" />
<HLASY_STRANA KSTRANA="46" HLASY="1" PROC_HLASU="0.31" />
<HLASY_STRANA KSTRANA="47" HLASY="8" PROC_HLASU="2.48" />
<HLASY_STRANA KSTRANA="52" HLASY="2" PROC_HLASU="0.62" />
<HLASY_STRANA KSTRANA="65" HLASY="2" PROC_HLASU="0.62" />
<HLASY_STRANA KSTRANA="68" HLASY="6" PROC_HLASU="1.86" />
<HLASY_STRANA KSTRANA="75" HLASY="1" PROC_HLASU="0.31" />
<HLASY_STRANA KSTRANA="78" HLASY="45" PROC_HLASU="13.97" />
<HLASY_STRANA KSTRANA="82" HLASY="9" PROC_HLASU="2.79" />
</OBEC>
<OBEC CIS_OBEC="598135" NAZ_OBEC="Fryčovice">
<UCAST OKRSKY_CELKEM="2" OKRSKY_ZPRAC="2" OKRSKY_ZPRAC_PROC="100.00" ZAPSANI_VOLICI="1945" VYDANE_OBALKY="679" UCAST_PROC="34.91" ODEVZDANE_OBALKY="679" PLATNE_HLASY="660" PLATNE_HLASY_PROC="97.20" />
<HLASY_STRANA KSTRANA="2" HLASY="40" PROC_HLASU="6.06" />
<HLASY_STRANA KSTRANA="9" HLASY="11" PROC_HLASU="1.66" />
<HLASY_STRANA KSTRANA="12" HLASY="119" PROC_HLASU="18.03" />
<HLASY_STRANA KSTRANA="24" HLASY="83" PROC_HLASU="12.57" />
<HLASY_STRANA KSTRANA="30" HLASY="160" PROC_HLASU="24.24" />
<HLASY_STRANA KSTRANA="31" HLASY="8" PROC_HLASU="1.21" />
<HLASY_STRANA KSTRANA="32" HLASY="13" PROC_HLASU="1.96" />
<HLASY_STRANA KSTRANA="37" HLASY="112" PROC_HLASU="16.96" />
<HLASY_STRANA KSTRANA="41" HLASY="2" PROC_HLASU="0.30" />
<HLASY_STRANA KSTRANA="43" HLASY="12" PROC_HLASU="1.81" />
<HLASY_STRANA KSTRANA="46" HLASY="1" PROC_HLASU="0.15" />
<HLASY_STRANA KSTRANA="47" HLASY="15" PROC_HLASU="2.27" />
<HLASY_STRANA KSTRANA="52" HLASY="8" PROC_HLASU="1.21" />
<HLASY_STRANA KSTRANA="65" HLASY="3" PROC_HLASU="0.45" />
<HLASY_STRANA KSTRANA="68" HLASY="16" PROC_HLASU="2.42" />
<HLASY_STRANA KSTRANA="70" HLASY="1" PROC_HLASU="0.15" />
<HLASY_STRANA KSTRANA="75" HLASY="2" PROC_HLASU="0.30" />
<HLASY_STRANA KSTRANA="78" HLASY="34" PROC_HLASU="5.15" />
<HLASY_STRANA KSTRANA="82" HLASY="20" PROC_HLASU="3.03" />
</OBEC>
<OBEC CIS_OBEC="598143" NAZ_OBEC="Frýdlant nad Ostravicí">
<UCAST OKRSKY_CELKEM="10" OKRSKY_ZPRAC="10" OKRSKY_ZPRAC_PROC="100.00" ZAPSANI_VOLICI="8116" VYDANE_OBALKY="3019" UCAST_PROC="37.20" ODEVZDANE_OBALKY="3019" PLATNE_HLASY="2964" PLATNE_HLASY_PROC="98.18" />
<HLASY_STRANA KSTRANA="1" HLASY="4" PROC_HLASU="0.13" />
<HLASY_STRANA KSTRANA="2" HLASY="127" PROC_HLASU="4.28" />
<HLASY_STRANA KSTRANA="9" HLASY="16" PROC_HLASU="0.53" />
<HLASY_STRANA KSTRANA="12" HLASY="364" PROC_HLASU="12.28" />
<HLASY_STRANA KSTRANA="24" HLASY="325" PROC_HLASU="10.96" />
<HLASY_STRANA KSTRANA="26" HLASY="3" PROC_HLASU="0.10" />
<HLASY_STRANA KSTRANA="28" HLASY="1" PROC_HLASU="0.03" />
<HLASY_STRANA KSTRANA="30" HLASY="679" PROC_HLASU="22.90" />
<HLASY_STRANA KSTRANA="31" HLASY="7" PROC_HLASU="0.23" />
<HLASY_STRANA KSTRANA="32" HLASY="102" PROC_HLASU="3.44" />
<HLASY_STRANA KSTRANA="37" HLASY="304" PROC_HLASU="10.25" />
<HLASY_STRANA KSTRANA="41" HLASY="6" PROC_HLASU="0.20" />
<HLASY_STRANA KSTRANA="43" HLASY="30" PROC_HLASU="1.01" />
<HLASY_STRANA KSTRANA="45" HLASY="6" PROC_HLASU="0.20" />
<HLASY_STRANA KSTRANA="46" HLASY="77" PROC_HLASU="2.59" />
<HLASY_STRANA KSTRANA="47" HLASY="502" PROC_HLASU="16.93" />
<HLASY_STRANA KSTRANA="52" HLASY="126" PROC_HLASU="4.25" />
<HLASY_STRANA KSTRANA="65" HLASY="20" PROC_HLASU="0.67" />
<HLASY_STRANA KSTRANA="67" HLASY="4" PROC_HLASU="0.13" />
<HLASY_STRANA KSTRANA="68" HLASY="26" PROC_HLASU="0.87" />
<HLASY_STRANA KSTRANA="70" HLASY="3" PROC_HLASU="0.10" />
<HLASY_STRANA KSTRANA="75" HLASY="20" PROC_HLASU="0.67" />
<HLASY_STRANA KSTRANA="78" HLASY="146" PROC_HLASU="4.92" />
<HLASY_STRANA KSTRANA="82" HLASY="66" PROC_HLASU="2.22" />
</OBEC>
<OBEC CIS_OBEC="598160" NAZ_OBEC="Hnojník">
<UCAST OKRSKY_CELKEM="1" OKRSKY_ZPRAC="1" OKRSKY_ZPRAC_PROC="100.00" ZAPSANI_VOLICI="1208" VYDANE_OBALKY="438" UCAST_PROC="36.26" ODEVZDANE_OBALKY="436" PLATNE_HLASY="418" PLATNE_HLASY_PROC="95.87" />
<HLASY_STRANA KSTRANA="2" HLASY="16" PROC_HLASU="3.82" />
<HLASY_STRANA KSTRANA="9" HLASY="10" PROC_HLASU="2.39" />
<HLASY_STRANA KSTRANA="12" HLASY="83" PROC_HLASU="19.85" />
<HLASY_STRANA KSTRANA="24" HLASY="95" PROC_HLASU="22.72" />
<HLASY_STRANA KSTRANA="30" HLASY="96" PROC_HLASU="22.96" />
<HLASY_STRANA KSTRANA="31" HLASY="2" PROC_HLASU="0.47" />
<HLASY_STRANA KSTRANA="32" HLASY="6" PROC_HLASU="1.43" />
<HLASY_STRANA KSTRANA="37" HLASY="36" PROC_HLASU="8.61" />
<HLASY_STRANA KSTRANA="41" HLASY="1" PROC_HLASU="0.23" />
<HLASY_STRANA KSTRANA="43" HLASY="13" PROC_HLASU="3.11" />
<HLASY_STRANA KSTRANA="46" HLASY="5" PROC_HLASU="1.19" />
<HLASY_STRANA KSTRANA="47" HLASY="13" PROC_HLASU="3.11" />
<HLASY_STRANA KSTRANA="52" HLASY="4" PROC_HLASU="0.95" />
<HLASY_STRANA KSTRANA="67" HLASY="1" PROC_HLASU="0.23" />
<HLASY_STRANA KSTRANA="68" HLASY="6" PROC_HLASU="1.43" />
<HLASY_STRANA KSTRANA="70" HLASY="1" PROC_HLASU="0.23" />
<HLASY_STRANA KSTRANA="78" HLASY="19" PROC_HLASU="4.54" />
<HLASY_STRANA KSTRANA="81" HLASY="1" PROC_HLASU="0.23" />
<HLASY_STRANA KSTRANA="82" HLASY="10" PROC_HLASU="2.39" />
</OBEC>
<OBEC CIS_OBEC="598232" NAZ_OBEC="Hrčava">
<UCAST OKRSKY_CELKEM="1" OKRSKY_ZPRAC="1" OKRSKY_ZPRAC_PROC="100.00" ZAPSANI_VOLICI="198" VYDANE_OBALKY="74" UCAST_PROC="37.37" ODEVZDANE_OBALKY="74" PLATNE_HLASY="72" PLATNE_HLASY_PROC="97.30" />
<HLASY_STRANA KSTRANA="2" HLASY="4" PROC_HLASU="5.55" />
<HLASY_STRANA KSTRANA="12" HLASY="21" PROC_HLASU="29.16" />
<HLASY_STRANA KSTRANA="24" HLASY="5" PROC_HLASU="6.94" />
<HLASY_STRANA KSTRANA="30" HLASY="9" PROC_HLASU="12.50" />
<HLASY_STRANA KSTRANA="32" HLASY="1" PROC_HLASU="1.38" />
<HLASY_STRANA KSTRANA="37" HLASY="16" PROC_HLASU="22.22" />
<HLASY_STRANA KSTRANA="47" HLASY="10" PROC_HLASU="13.88" />
<HLASY_STRANA KSTRANA="68" HLASY="1" PROC_HLASU="1.38" />
<HLASY_STRANA KSTRANA="78" HLASY="5" PROC_HLASU="6.94" />
</OBEC>
<OBEC CIS_OBEC="598259" NAZ_OBEC="Jablunkov">
<UCAST OKRSKY_CELKEM="5" OKRSKY_ZPRAC="5" OKRSKY_ZPRAC_PROC="100.00" ZAPSANI_VOLICI="4546" VYDANE_OBALKY="1651" UCAST_PROC="36.32" ODEVZDANE_OBALKY="1645" PLATNE_HLASY="1613" PLATNE_HLASY_PROC="98.05" />
<HLASY_STRANA KSTRANA="1" HLASY="1" PROC_HLASU="0.06" />
<HLASY_STRANA KSTRANA="2" HLASY="120" PROC_HLASU="7.43" />
<HLASY_STRANA KSTRANA="9" HLASY="19" PROC_HLASU="1.17" />
<HLASY_STRANA KSTRANA="12" HLASY="530" PROC_HLASU="32.85" />
<HLASY_STRANA KSTRANA="24" HLASY="428" PROC_HLASU="26.53" />
<HLASY_STRANA KSTRANA="26" HLASY="1" PROC_HLASU="0.06" />
<HLASY_STRANA KSTRANA="30" HLASY="204" PROC_HLASU="12.64" />
<HLASY_STRANA KSTRANA="31" HLASY="1" PROC_HLASU="0.06" />
<HLASY_STRANA KSTRANA="32" HLASY="25" PROC_HLASU="1.54" />
<HLASY_STRANA KSTRANA="37" HLASY="50" PROC_HLASU="3.09" />
<HLASY_STRANA KSTRANA="41" HLASY="2" PROC_HLASU="0.12" />
<HLASY_STRANA KSTRANA="43" HLASY="38" PROC_HLASU="2.35" />
<HLASY_STRANA KSTRANA="45" HLASY="4" PROC_HLASU="0.24" />
<HLASY_STRANA KSTRANA="46" HLASY="8" PROC_HLASU="0.49" />
<HLASY_STRANA KSTRANA="47" HLASY="91" PROC_HLASU="5.64" />
<HLASY_STRANA KSTRANA="52" HLASY="3" PROC_HLASU="0.18" />
<HLASY_STRANA KSTRANA="65" HLASY="3" PROC_HLASU="0.18" />
<HLASY_STRANA KSTRANA="67" HLASY="1" PROC_HLASU="0.06" />
<HLASY_STRANA KSTRANA="68" HLASY="5" PROC_HLASU="0.30" />
<HLASY_STRANA KSTRANA="75" HLASY="8" PROC_HLASU="0.49" />
<HLASY_STRANA KSTRANA="78" HLASY="37" PROC_HLASU="2.29" />
<HLASY_STRANA KSTRANA="82" HLASY="34" PROC_HLASU="2.10" />
</OBEC>
<OBEC CIS_OBEC="598275" NAZ_OBEC="Kaňovice">
<UCAST OKRSKY_CELKEM="1" OKRSKY_ZPRAC="1" OKRSKY_ZPRAC_PROC="100.00" ZAPSANI_VOLICI="246" VYDANE_OBALKY="125" UCAST_PROC="50.81" ODEVZDANE_OBALKY="125" PLATNE_HLASY="125" PLATNE_HLASY_PROC="100.00" />
<HLASY_STRANA KSTRANA="2" HLASY="11" PROC_HLASU="8.80" />
<HLASY_STRANA KSTRANA="9" HLASY="3" PROC_HLASU="2.40" />
<HLASY_STRANA KSTRANA="12" HLASY="15" PROC_HLASU="12.00" />
<HLASY_STRANA KSTRANA="24" HLASY="14" PROC_HLASU="11.20" />
<HLASY_STRANA KSTRANA="26" HLASY="1" PROC_HLASU="0.80" />
<HLASY_STRANA KSTRANA="30" HLASY="34" PROC_HLASU="27.20" />
<HLASY_STRANA KSTRANA="32" HLASY="8" PROC_HLASU="6.40" />
<HLASY_STRANA KSTRANA="37" HLASY="5" PROC_HLASU="4.00" />
<HLASY_STRANA KSTRANA="43" HLASY="2" PROC_HLASU="1.60" />
<HLASY_STRANA KSTRANA="45" HLASY="1" PROC_HLASU="0.80" />
<HLASY_STRANA KSTRANA="47" HLASY="10" PROC_HLASU="8.00" />
<HLASY_STRANA KSTRANA="52" HLASY="1" PROC_HLASU="0.80" />
<HLASY_STRANA KSTRANA="67" HLASY="1" PROC_HLASU="0.80" />
<HLASY_STRANA KSTRANA="68" HLASY="5" PROC_HLASU="4.00" />
<HLASY_STRANA KSTRANA="78" HLASY="12" PROC_HLASU="9.60" />
<HLASY_STRANA KSTRANA="82" HLASY="2" PROC_HLASU="1.60" />
</OBEC>
<OBEC CIS_OBEC="598321" NAZ_OBEC="Kozlovice">
<UCAST OKRSKY_CELKEM="3" OKRSKY_ZPRAC="3" OKRSKY_ZPRAC_PROC="100.00" ZAPSANI_VOLICI="2425" VYDANE_OBALKY="852" UCAST_PROC="35.13" ODEVZDANE_OBALKY="852" PLATNE_HLASY="842" PLATNE_HLASY_PROC="98.83" />
<HLASY_STRANA KSTRANA="2" HLASY="77" PROC_HLASU="9.14" />
<HLASY_STRANA KSTRANA="9" HLASY="12" PROC_HLASU="1.42" />
<HLASY_STRANA KSTRANA="12" HLASY="138" PROC_HLASU="16.38" />
<HLASY_STRANA KSTRANA="24" HLASY="199" PROC_HLASU="23.63" />
<HLASY_STRANA KSTRANA="26" HLASY="1" PROC_HLASU="0.11" />
<HLASY_STRANA KSTRANA="30" HLASY="196" PROC_HLASU="23.27" />
<HLASY_STRANA KSTRANA="31" HLASY="1" PROC_HLASU="0.11" />
<HLASY_STRANA KSTRANA="32" HLASY="30" PROC_HLASU="3.56" />
<HLASY_STRANA KSTRANA="37" HLASY="49" PROC_HLASU="5.81" />
<HLASY_STRANA KSTRANA="43" HLASY="2" PROC_HLASU="0.23" />
<HLASY_STRANA KSTRANA="45" HLASY="2" PROC_HLASU="0.23" />
<HLASY_STRANA KSTRANA="46" HLASY="4" PROC_HLASU="0.47" />
<HLASY_STRANA KSTRANA="47" HLASY="18" PROC_HLASU="2.13" />
<HLASY_STRANA KSTRANA="52" HLASY="11" PROC_HLASU="1.30" />
<HLASY_STRANA KSTRANA="65" HLASY="12" PROC_HLASU="1.42" />
<HLASY_STRANA KSTRANA="67" HLASY="2" PROC_HLASU="0.23" />
<HLASY_STRANA KSTRANA="68" HLASY="16" PROC_HLASU="1.90" />
<HLASY_STRANA KSTRANA="75" HLASY="6" PROC_HLASU="0.71" />
<HLASY_STRANA KSTRANA="78" HLASY="44" PROC_HLASU="5.22" />
<HLASY_STRANA KSTRANA="81" HLASY="1" PROC_HLASU="0.11" />
<HLASY_STRANA KSTRANA="82" HLASY="21" PROC_HLASU="2.49" />
</OBEC>
<OBEC CIS_OBEC="598348" NAZ_OBEC="Krmelín">
<UCAST OKRSKY_CELKEM="2" OKRSKY_ZPRAC="2" OKRSKY_ZPRAC_PROC="100.00" ZAPSANI_VOLICI="1863" VYDANE_OBALKY="923" UCAST_PROC="49.54" ODEVZDANE_OBALKY="922" PLATNE_HLASY="911" PLATNE_HLASY_PROC="98.81" />
<HLASY_STRANA KSTRANA="2" HLASY="105" PROC_HLASU="11.52" />
<HLASY_STRANA KSTRANA="9" HLASY="2" PROC_HLASU="0.21" />
<HLASY_STRANA KSTRANA="12" HLASY="116" PROC_HLASU="12.73" />
<HLASY_STRANA KSTRANA="24" HLASY="104" PROC_HLASU="11.41" />
<HLASY_STRANA KSTRANA="26" HLASY="1" PROC_HLASU="0.10" />
<HLASY_STRANA KSTRANA="30" HLASY="263" PROC_HLASU="28.86" />
<HLASY_STRANA KSTRANA="31" HLASY="7" PROC_HLASU="0.76" />
<HLASY_STRANA KSTRANA="32" HLASY="33" PROC_HLASU="3.62" />
<HLASY_STRANA KSTRANA="37" HLASY="77" PROC_HLASU="8.45" />
<HLASY_STRANA KSTRANA="43" HLASY="12" PROC_HLASU="1.31" />
<HLASY_STRANA KSTRANA="45" HLASY="1" PROC_HLASU="0.10" />
<HLASY_STRANA KSTRANA="46" HLASY="3" PROC_HLASU="0.32" />
<HLASY_STRANA KSTRANA="47" HLASY="46" PROC_HLASU="5.04" />
<HLASY_STRANA KSTRANA="52" HLASY="9" PROC_HLASU="0.98" />
<HLASY_STRANA KSTRANA="65" HLASY="9" PROC_HLASU="0.98" />
<HLASY_STRANA KSTRANA="67" HLASY="1" PROC_HLASU="0.10" />
<HLASY_STRANA KSTRANA="68" HLASY="28" PROC_HLASU="3.07" />
<HLASY_STRANA KSTRANA="70" HLASY="2" PROC_HLASU="0.21" />
<HLASY_STRANA KSTRANA="75" HLASY="6" PROC_HLASU="0.65" />
<HLASY_STRANA KSTRANA="78" HLASY="61" PROC_HLASU="6.69" />
<HLASY_STRANA KSTRANA="82" HLASY="25" PROC_HLASU="2.74" />
</OBEC>
<OBEC CIS_OBEC="598356" NAZ_OBEC="Kunčice pod Ondřejníkem">
<UCAST OKRSKY_CELKEM="2" OKRSKY_ZPRAC="2" OKRSKY_ZPRAC_PROC="100.00" ZAPSANI_VOLICI="1868" VYDANE_OBALKY="629" UCAST_PROC="33.67" ODEVZDANE_OBALKY="629" PLATNE_HLASY="620" PLATNE_HLASY_PROC="98.57" />
<HLASY_STRANA KSTRANA="1" HLASY="1" PROC_HLASU="0.16" />
<HLASY_STRANA KSTRANA="2" HLASY="57" PROC_HLASU="9.19" />
<HLASY_STRANA KSTRANA="9" HLASY="7" PROC_HLASU="1.12" />
<HLASY_STRANA KSTRANA="12" HLASY="73" PROC_HLASU="11.77" />
<HLASY_STRANA KSTRANA="24" HLASY="115" PROC_HLASU="18.54" />
<HLASY_STRANA KSTRANA="26" HLASY="1" PROC_HLASU="0.16" />
<HLASY_STRANA KSTRANA="30" HLASY="147" PROC_HLASU="23.70" />
<HLASY_STRANA KSTRANA="31" HLASY="8" PROC_HLASU="1.29" />
<HLASY_STRANA KSTRANA="32" HLASY="18" PROC_HLASU="2.90" />
<HLASY_STRANA KSTRANA="37" HLASY="52" PROC_HLASU="8.38" />
<HLASY_STRANA KSTRANA="43" HLASY="9" PROC_HLASU="1.45" />
<HLASY_STRANA KSTRANA="45" HLASY="2" PROC_HLASU="0.32" />
<HLASY_STRANA KSTRANA="46" HLASY="31" PROC_HLASU="5.00" />
<HLASY_STRANA KSTRANA="47" HLASY="14" PROC_HLASU="2.25" />
<HLASY_STRANA KSTRANA="52" HLASY="8" PROC_HLASU="1.29" />
<HLASY_STRANA KSTRANA="65" HLASY="7" PROC_HLASU="1.12" />
<HLASY_STRANA KSTRANA="67" HLASY="1" PROC_HLASU="0.16" />
<HLASY_STRANA KSTRANA="68" HLASY="11" PROC_HLASU="1.77" />
<HLASY_STRANA KSTRANA="75" HLASY="1" PROC_HLASU="0.16" />
<HLASY_STRANA KSTRANA="78" HLASY="42" PROC_HLASU="6.77" />
<HLASY_STRANA KSTRANA="82" HLASY="15" PROC_HLASU="2.41" />
</OBEC>
<OBEC CIS_OBEC="598364" NAZ_OBEC="Lhotka">
<UCAST OKRSKY_CELKEM="1" OKRSKY_ZPRAC="1" OKRSKY_ZPRAC_PROC="100.00" ZAPSANI_VOLICI="435" VYDANE_OBALKY="157" UCAST_PROC="36.09" ODEVZDANE_OBALKY="157" PLATNE_HLASY="155" PLATNE_HLASY_PROC="98.73" />
<HLASY_STRANA KSTRANA="2" HLASY="15" PROC_HLASU="9.67" />
<HLASY_STRANA KSTRANA="12" HLASY="26" PROC_HLASU="16.77" />
<HLASY_STRANA KSTRANA="24" HLASY="20" PROC_HLASU="12.90" />
<HLASY_STRANA KSTRANA="26" HLASY="1" PROC_HLASU="0.64" />
<HLASY_STRANA KSTRANA="30" HLASY="42" PROC_HLASU="27.09" />
<HLASY_STRANA KSTRANA="32" HLASY="7" PROC_HLASU="4.51" />
<HLASY_STRANA KSTRANA="37" HLASY="17" PROC_HLASU="10.96" />
<HLASY_STRANA KSTRANA="43" HLASY="1" PROC_HLASU="0.64" />
<HLASY_STRANA KSTRANA="47" HLASY="8" PROC_HLASU="5.16" />
<HLASY_STRANA KSTRANA="52" HLASY="4" PROC_HLASU="2.58" />
<HLASY_STRANA KSTRANA="65" HLASY="1" PROC_HLASU="0.64" />
<HLASY_STRANA KSTRANA="68" HLASY="6" PROC_HLASU="3.87" />
<HLASY_STRANA KSTRANA="78" HLASY="3" PROC_HLASU="1.93" />
<HLASY_STRANA KSTRANA="82" HLASY="4" PROC_HLASU="2.58" />
</OBEC>
<OBEC CIS_OBEC="598399" NAZ_OBEC="Lučina">
<UCAST OKRSKY_CELKEM="1" OKRSKY_ZPRAC="1" OKRSKY_ZPRAC_PROC="100.00" ZAPSANI_VOLICI="1121" VYDANE_OBALKY="408" UCAST_PROC="36.40" ODEVZDANE_OBALKY="408" PLATNE_HLASY="385" PLATNE_HLASY_PROC="94.36" />
<HLASY_STRANA KSTRANA="1" HLASY="2" PROC_HLASU="0.51" />
<HLASY_STRANA KSTRANA="2" HLASY="16" PROC_HLASU="4.15" />
<HLASY_STRANA KSTRANA="9" HLASY="2" PROC_HLASU="0.51" />
<HLASY_STRANA KSTRANA="12" HLASY="82" PROC_HLASU="21.29" />
<HLASY_STRANA KSTRANA="24" HLASY="29" PROC_HLASU="7.53" />
<HLASY_STRANA KSTRANA="30" HLASY="105" PROC_HLASU="27.27" />
<HLASY_STRANA KSTRANA="32" HLASY="11" PROC_HLASU="2.85" />
<HLASY_STRANA KSTRANA="37" HLASY="48" PROC_HLASU="12.46" />
<HLASY_STRANA KSTRANA="41" HLASY="1" PROC_HLASU="0.25" />
<HLASY_STRANA KSTRANA="43" HLASY="7" PROC_HLASU="1.81" />
<HLASY_STRANA KSTRANA="46" HLASY="6" PROC_HLASU="1.55" />
<HLASY_STRANA KSTRANA="47" HLASY="14" PROC_HLASU="3.63" />
<HLASY_STRANA KSTRANA="52" HLASY="2" PROC_HLASU="0.51" />
<HLASY_STRANA KSTRANA="65" HLASY="3" PROC_HLASU="0.77" />
<HLASY_STRANA KSTRANA="67" HLASY="3" PROC_HLASU="0.77" />
<HLASY_STRANA KSTRANA="68" HLASY="15" PROC_HLASU="3.89" />
<HLASY_STRANA KSTRANA="70" HLASY="1" PROC_HLASU="0.25" />
<HLASY_STRANA KSTRANA="75" HLASY="5" PROC_HLASU="1.29" />
<HLASY_STRANA KSTRANA="78" HLASY="22" PROC_HLASU="5.71" />
<HLASY_STRANA KSTRANA="81" HLASY="1" PROC_HLASU="0.25" />
<HLASY_STRANA KSTRANA="82" HLASY="10" PROC_HLASU="2.59" />
</OBEC>
<OBEC CIS_OBEC="598445" NAZ_OBEC="Morávka">
<UCAST OKRSKY_CELKEM="1" OKRSKY_ZPRAC="1" OKRSKY_ZPRAC_PROC="100.00" ZAPSANI_VOLICI="945" VYDANE_OBALKY="374" UCAST_PROC="39.58" ODEVZDANE_OBALKY="374" PLATNE_HLASY="366" PLATNE_HLASY_PROC="97.86" />
<HLASY_STRANA KSTRANA="1" HLASY="1" PROC_HLASU="0.27" />
<HLASY_STRANA KSTRANA="2" HLASY="20" PROC_HLASU="5.46" />
<HLASY_STRANA KSTRANA="9" HLASY="4" PROC_HLASU="1.09" />
<HLASY_STRANA KSTRANA="12" HLASY="61" PROC_HLASU="16.66" />
<HLASY_STRANA KSTRANA="24" HLASY="53" PROC_HLASU="14.48" />
<HLASY_STRANA KSTRANA="30" HLASY="104" PROC_HLASU="28.41" />
<HLASY_STRANA KSTRANA="32" HLASY="11" PROC_HLASU="3.00" />
<HLASY_STRANA KSTRANA="37" HLASY="47" PROC_HLASU="12.84" />
<HLASY_STRANA KSTRANA="41" HLASY="1" PROC_HLASU="0.27" />
<HLASY_STRANA KSTRANA="43" HLASY="3" PROC_HLASU="0.81" />
<HLASY_STRANA KSTRANA="45" HLASY="1" PROC_HLASU="0.27" />
<HLASY_STRANA KSTRANA="47" HLASY="19" PROC_HLASU="5.19" />
<HLASY_STRANA KSTRANA="52" HLASY="2" PROC_HLASU="0.54" />
<HLASY_STRANA KSTRANA="65" HLASY="12" PROC_HLASU="3.27" />
<HLASY_STRANA KSTRANA="68" HLASY="4" PROC_HLASU="1.09" />
<HLASY_STRANA KSTRANA="75" HLASY="2" PROC_HLASU="0.54" />
<HLASY_STRANA KSTRANA="78" HLASY="8" PROC_HLASU="2.18" />
<HLASY_STRANA KSTRANA="82" HLASY="13" PROC_HLASU="3.55" />
</OBEC>
<OBEC CIS_OBEC="598453" NAZ_OBEC="Mosty u Jablunkova">
<UCAST OKRSKY_CELKEM="3" OKRSKY_ZPRAC="3" OKRSKY_ZPRAC_PROC="100.00" ZAPSANI_VOLICI="3094" VYDANE_OBALKY="815" UCAST_PROC="26.34" ODEVZDANE_OBALKY="815" PLATNE_HLASY="793" PLATNE_HLASY_PROC="97.30" />
<HLASY_STRANA KSTRANA="1" HLASY="3" PROC_HLASU="0.37" />
<HLASY_STRANA KSTRANA="2" HLASY="65" PROC_HLASU="8.19" />
<HLASY_STRANA KSTRANA="9" HLASY="13" PROC_HLASU="1.63" />
<HLASY_STRANA KSTRANA="12" HLASY="179" PROC_HLASU="22.57" />
<HLASY_STRANA KSTRANA="24" HLASY="186" PROC_HLASU="23.45" />
<HLASY_STRANA KSTRANA="26" HLASY="2" PROC_HLASU="0.25" />
<HLASY_STRANA KSTRANA="30" HLASY="155" PROC_HLASU="19.54" />
<HLASY_STRANA KSTRANA="31" HLASY="1" PROC_HLASU="0.12" />
<HLASY_STRANA KSTRANA="32" HLASY="13" PROC_HLASU="1.63" />
<HLASY_STRANA KSTRANA="37" HLASY="39" PROC_HLASU="4.91" />
<HLASY_STRANA KSTRANA="41" HLASY="1" PROC_HLASU="0.12" />
<HLASY_STRANA KSTRANA="43" HLASY="19" PROC_HLASU="2.39" />
<HLASY_STRANA KSTRANA="46" HLASY="14" PROC_HLASU="1.76" />
<HLASY_STRANA KSTRANA="47" HLASY="43" PROC_HLASU="5.42" />
<HLASY_STRANA KSTRANA="52" HLASY="1" PROC_HLASU="0.12" />
<HLASY_STRANA KSTRANA="65" HLASY="7" PROC_HLASU="0.88" />
<HLASY_STRANA KSTRANA="67" HLASY="2" PROC_HLASU="0.25" />
<HLASY_STRANA KSTRANA="68" HLASY="8" PROC_HLASU="1.00" />
<HLASY_STRANA KSTRANA="75" HLASY="6" PROC_HLASU="0.75" />
<HLASY_STRANA KSTRANA="78" HLASY="21" PROC_HLASU="2.64" />
<HLASY_STRANA KSTRANA="82" HLASY="15" PROC_HLASU="1.89" />
</OBEC>
<OBEC CIS_OBEC="598542" NAZ_OBEC="Ostravice">
<UCAST OKRSKY_CELKEM="2" OKRSKY_ZPRAC="2" OKRSKY_ZPRAC_PROC="100.00" ZAPSANI_VOLICI="2007" VYDANE_OBALKY="713" UCAST_PROC="35.53" ODEVZDANE_OBALKY="712" PLATNE_HLASY="694" PLATNE_HLASY_PROC="97.47" />
<HLASY_STRANA KSTRANA="1" HLASY="3" PROC_HLASU="0.43" />
<HLASY_STRANA KSTRANA="2" HLASY="32" PROC_HLASU="4.61" />
<HLASY_STRANA KSTRANA="9" HLASY="8" PROC_HLASU="1.15" />
<HLASY_STRANA KSTRANA="12" HLASY="96" PROC_HLASU="13.83" />
<HLASY_STRANA KSTRANA="24" HLASY="50" PROC_HLASU="7.20" />
<HLASY_STRANA KSTRANA="30" HLASY="153" PROC_HLASU="22.04" />
<HLASY_STRANA KSTRANA="31" HLASY="5" PROC_HLASU="0.72" />
<HLASY_STRANA KSTRANA="32" HLASY="126" PROC_HLASU="18.15" />
<HLASY_STRANA KSTRANA="37" HLASY="66" PROC_HLASU="9.51" />
<HLASY_STRANA KSTRANA="43" HLASY="8" PROC_HLASU="1.15" />
<HLASY_STRANA KSTRANA="45" HLASY="1" PROC_HLASU="0.14" />
<HLASY_STRANA KSTRANA="46" HLASY="15" PROC_HLASU="2.16" />
<HLASY_STRANA KSTRANA="47" HLASY="25" PROC_HLASU="3.60" />
<HLASY_STRANA KSTRANA="52" HLASY="18" PROC_HLASU="2.59" />
<HLASY_STRANA KSTRANA="65" HLASY="9" PROC_HLASU="1.29" />
<HLASY_STRANA KSTRANA="67" HLASY="3" PROC_HLASU="0.43" />
<HLASY_STRANA KSTRANA="68" HLASY="6" PROC_HLASU="0.86" />
<HLASY_STRANA KSTRANA="70" HLASY="1" PROC_HLASU="0.14" />
<HLASY_STRANA KSTRANA="75" HLASY="4" PROC_HLASU="0.57" />
<HLASY_STRANA KSTRANA="78" HLASY="53" PROC_HLASU="7.63" />
<HLASY_STRANA KSTRANA="82" HLASY="12" PROC_HLASU="1.72" />
</OBEC>
<OBEC CIS_OBEC="598551" NAZ_OBEC="Palkovice">
<UCAST OKRSKY_CELKEM="3" OKRSKY_ZPRAC="3" OKRSKY_ZPRAC_PROC="100.00" ZAPSANI_VOLICI="2640" VYDANE_OBALKY="1057" UCAST_PROC="40.04" ODEVZDANE_OBALKY="1056" PLATNE_HLASY="1032" PLATNE_HLASY_PROC="97.73" />
<HLASY_STRANA KSTRANA="2" HLASY="57" PROC_HLASU="5.52" />
<HLASY_STRANA KSTRANA="9" HLASY="8" PROC_HLASU="0.77" />
<HLASY_STRANA KSTRANA="12" HLASY="141" PROC_HLASU="13.66" />
<HLASY_STRANA KSTRANA="24" HLASY="144" PROC_HLASU="13.95" />
<HLASY_STRANA KSTRANA="26" HLASY="3" PROC_HLASU="0.29" />
<HLASY_STRANA KSTRANA="30" HLASY="223" PROC_HLASU="21.60" />
<HLASY_STRANA KSTRANA="31" HLASY="2" PROC_HLASU="0.19" />
<HLASY_STRANA KSTRANA="32" HLASY="122" PROC_HLASU="11.82" />
<HLASY_STRANA KSTRANA="37" HLASY="118" PROC_HLASU="11.43" />
<HLASY_STRANA KSTRANA="41" HLASY="2" PROC_HLASU="0.19" />
<HLASY_STRANA KSTRANA="43" HLASY="13" PROC_HLASU="1.25" />
<HLASY_STRANA KSTRANA="45" HLASY="2" PROC_HLASU="0.19" />
<HLASY_STRANA KSTRANA="46" HLASY="14" PROC_HLASU="1.35" />
<HLASY_STRANA KSTRANA="47" HLASY="40" PROC_HLASU="3.87" />
<HLASY_STRANA KSTRANA="52" HLASY="15" PROC_HLASU="1.45" />
<HLASY_STRANA KSTRANA="65" HLASY="5" PROC_HLASU="0.48" />
<HLASY_STRANA KSTRANA="67" HLASY="2" PROC_HLASU="0.19" />
<HLASY_STRANA KSTRANA="68" HLASY="14" PROC_HLASU="1.35" />
<HLASY_STRANA KSTRANA="75" HLASY="2" PROC_HLASU="0.19" />
<HLASY_STRANA KSTRANA="78" HLASY="76" PROC_HLASU="7.36" />
<HLASY_STRANA KSTRANA="82" HLASY="29" PROC_HLASU="2.81" />
</OBEC>
<OBEC CIS_OBEC="598569" NAZ_OBEC="Paskov">
<UCAST OKRSKY_CELKEM="4" OKRSKY_ZPRAC="4" OKRSKY_ZPRAC_PROC="100.00" ZAPSANI_VOLICI="3234" VYDANE_OBALKY="1015" UCAST_PROC="31.39" ODEVZDANE_OBALKY="1015" PLATNE_HLASY="1002" PLATNE_HLASY_PROC="98.72" />
<HLASY_STRANA KSTRANA="1" HLASY="2" PROC_HLASU="0.19" />
<HLASY_STRANA KSTRANA="2" HLASY="94" PROC_HLASU="9.38" />
<HLASY_STRANA KSTRANA="9" HLASY="10" PROC_HLASU="0.99" />
<HLASY_STRANA KSTRANA="12" HLASY="146" PROC_HLASU="14.57" />
<HLASY_STRANA KSTRANA="24" HLASY="59" PROC_HLASU="5.88" />
<HLASY_STRANA KSTRANA="26" HLASY="3" PROC_HLASU="0.29" />
<HLASY_STRANA KSTRANA="30" HLASY="291" PROC_HLASU="29.04" />
<HLASY_STRANA KSTRANA="31" HLASY="5" PROC_HLASU="0.49" />
<HLASY_STRANA KSTRANA="32" HLASY="43" PROC_HLASU="4.29" />
<HLASY_STRANA KSTRANA="37" HLASY="141" PROC_HLASU="14.07" />
<HLASY_STRANA KSTRANA="41" HLASY="2" PROC_HLASU="0.19" />
<HLASY_STRANA KSTRANA="43" HLASY="5" PROC_HLASU="0.49" />
<HLASY_STRANA KSTRANA="45" HLASY="1" PROC_HLASU="0.09" />
<HLASY_STRANA KSTRANA="46" HLASY="2" PROC_HLASU="0.19" />
<HLASY_STRANA KSTRANA="47" HLASY="31" PROC_HLASU="3.09" />
<HLASY_STRANA KSTRANA="52" HLASY="14" PROC_HLASU="1.39" />
<HLASY_STRANA KSTRANA="65" HLASY="8" PROC_HLASU="0.79" />
<HLASY_STRANA KSTRANA="67" HLASY="5" PROC_HLASU="0.49" />
<HLASY_STRANA KSTRANA="68" HLASY="20" PROC_HLASU="1.99" />
<HLASY_STRANA KSTRANA="70" HLASY="2" PROC_HLASU="0.19" />
<HLASY_STRANA KSTRANA="75" HLASY="10" PROC_HLASU="0.99" />
<HLASY_STRANA KSTRANA="78" HLASY="74" PROC_HLASU="7.38" />
<HLASY_STRANA KSTRANA="82" HLASY="34" PROC_HLASU="3.39" />
</OBEC>
<OBEC CIS_OBEC="598674" NAZ_OBEC="Sedliště">
<UCAST OKRSKY_CELKEM="1" OKRSKY_ZPRAC="1" OKRSKY_ZPRAC_PROC="100.00" ZAPSANI_VOLICI="1240" VYDANE_OBALKY="516" UCAST_PROC="41.61" ODEVZDANE_OBALKY="516" PLATNE_HLASY="510" PLATNE_HLASY_PROC="98.84" />
<HLASY_STRANA KSTRANA="1" HLASY="3" PROC_HLASU="0.58" />
<HLASY_STRANA KSTRANA="2" HLASY="33" PROC_HLASU="6.47" />
<HLASY_STRANA KSTRANA="9" HLASY="6" PROC_HLASU="1.17" />
<HLASY_STRANA KSTRANA="12" HLASY="49" PROC_HLASU="9.60" />
<HLASY_STRANA KSTRANA="24" HLASY="120" PROC_HLASU="23.52" />
<HLASY_STRANA KSTRANA="26" HLASY="4" PROC_HLASU="0.78" />
<HLASY_STRANA KSTRANA="30" HLASY="134" PROC_HLASU="26.27" />
<HLASY_STRANA KSTRANA="31" HLASY="3" PROC_HLASU="0.58" />
<HLASY_STRANA KSTRANA="32" HLASY="10" PROC_HLASU="1.96" />
<HLASY_STRANA KSTRANA="37" HLASY="61" PROC_HLASU="11.96" />
<HLASY_STRANA KSTRANA="43" HLASY="4" PROC_HLASU="0.78" />
<HLASY_STRANA KSTRANA="45" HLASY="1" PROC_HLASU="0.19" />
<HLASY_STRANA KSTRANA="46" HLASY="5" PROC_HLASU="0.98" />
<HLASY_STRANA KSTRANA="47" HLASY="8" PROC_HLASU="1.56" />
<HLASY_STRANA KSTRANA="52" HLASY="6" PROC_HLASU="1.17" />
<HLASY_STRANA KSTRANA="65" HLASY="4" PROC_HLASU="0.78" />
<HLASY_STRANA KSTRANA="67" HLASY="1" PROC_HLASU="0.19" />
<HLASY_STRANA KSTRANA="68" HLASY="11" PROC_HLASU="2.15" />
<HLASY_STRANA KSTRANA="70" HLASY="6" PROC_HLASU="1.17" />
<HLASY_STRANA KSTRANA="75" HLASY="2" PROC_HLASU="0.39" />
<HLASY_STRANA KSTRANA="78" HLASY="30" PROC_HLASU="5.88" />
<HLASY_STRANA KSTRANA="82" HLASY="9" PROC_HLASU="1.76" />
</OBEC>
<OBEC CIS_OBEC="598691" NAZ_OBEC="Hukvaldy">
<UCAST OKRSKY_CELKEM="2" OKRSKY_ZPRAC="2" OKRSKY_ZPRAC_PROC="100.00" ZAPSANI_VOLICI="1691" VYDANE_OBALKY="697" UCAST_PROC="41.22" ODEVZDANE_OBALKY="697" PLATNE_HLASY="692" PLATNE_HLASY_PROC="99.28" />
<HLASY_STRANA KSTRANA="2" HLASY="59" PROC_HLASU="8.52" />
<HLASY_STRANA KSTRANA="9" HLASY="7" PROC_HLASU="1.01" />
<HLASY_STRANA KSTRANA="12" HLASY="105" PROC_HLASU="15.17" />
<HLASY_STRANA KSTRANA="24" HLASY="99" PROC_HLASU="14.30" />
<HLASY_STRANA KSTRANA="26" HLASY="4" PROC_HLASU="0.57" />
<HLASY_STRANA KSTRANA="30" HLASY="179" PROC_HLASU="25.86" />
<HLASY_STRANA KSTRANA="31" HLASY="4" PROC_HLASU="0.57" />
<HLASY_STRANA KSTRANA="32" HLASY="32" PROC_HLASU="4.62" />
<HLASY_STRANA KSTRANA="37" HLASY="87" PROC_HLASU="12.57" />
<HLASY_STRANA KSTRANA="41" HLASY="1" PROC_HLASU="0.14" />
<HLASY_STRANA KSTRANA="43" HLASY="3" PROC_HLASU="0.43" />
<HLASY_STRANA KSTRANA="45" HLASY="2" PROC_HLASU="0.28" />
<HLASY_STRANA KSTRANA="46" HLASY="1" PROC_HLASU="0.14" />
<HLASY_STRANA KSTRANA="47" HLASY="28" PROC_HLASU="4.04" />
<HLASY_STRANA KSTRANA="52" HLASY="8" PROC_HLASU="1.15" />
<HLASY_STRANA KSTRANA="65" HLASY="6" PROC_HLASU="0.86" />
<HLASY_STRANA KSTRANA="67" HLASY="2" PROC_HLASU="0.28" />
<HLASY_STRANA KSTRANA="68" HLASY="14" PROC_HLASU="2.02" />
<HLASY_STRANA KSTRANA="70" HLASY="1" PROC_HLASU="0.14" />
<HLASY_STRANA KSTRANA="75" HLASY="2" PROC_HLASU="0.28" />
<HLASY_STRANA KSTRANA="78" HLASY="30" PROC_HLASU="4.33" />
<HLASY_STRANA KSTRANA="82" HLASY="18" PROC_HLASU="2.60" />
</OBEC>
<OBEC CIS_OBEC="598747" NAZ_OBEC="Staré Hamry">
<UCAST OKRSKY_CELKEM="1" OKRSKY_ZPRAC="1" OKRSKY_ZPRAC_PROC="100.00" ZAPSANI_VOLICI="464" VYDANE_OBALKY="168" UCAST_PROC="36.21" ODEVZDANE_OBALKY="167" PLATNE_HLASY="163" PLATNE_HLASY_PROC="97.60" />
<HLASY_STRANA KSTRANA="2" HLASY="4" PROC_HLASU="2.45" />
<HLASY_STRANA KSTRANA="9" HLASY="1" PROC_HLASU="0.61" />
<HLASY_STRANA KSTRANA="12" HLASY="56" PROC_HLASU="34.35" />
<HLASY_STRANA KSTRANA="24" HLASY="19" PROC_HLASU="11.65" />
<HLASY_STRANA KSTRANA="28" HLASY="1" PROC_HLASU="0.61" />
<HLASY_STRANA KSTRANA="30" HLASY="23" PROC_HLASU="14.11" />
<HLASY_STRANA KSTRANA="31" HLASY="1" PROC_HLASU="0.61" />
<HLASY_STRANA KSTRANA="32" HLASY="3" PROC_HLASU="1.84" />
<HLASY_STRANA KSTRANA="37" HLASY="15" PROC_HLASU="9.20" />
<HLASY_STRANA KSTRANA="41" HLASY="1" PROC_HLASU="0.61" />
<HLASY_STRANA KSTRANA="43" HLASY="3" PROC_HLASU="1.84" />
<HLASY_STRANA KSTRANA="46" HLASY="1" PROC_HLASU="0.61" />
<HLASY_STRANA KSTRANA="47" HLASY="11" PROC_HLASU="6.74" />
<HLASY_STRANA KSTRANA="52" HLASY="1" PROC_HLASU="0.61" />
<HLASY_STRANA KSTRANA="65" HLASY="1" PROC_HLASU="0.61" />
<HLASY_STRANA KSTRANA="67" HLASY="1" PROC_HLASU="0.61" />
<HLASY_STRANA KSTRANA="68" HLASY="2" PROC_HLASU="1.22" />
<HLASY_STRANA KSTRANA="70" HLASY="1" PROC_HLASU="0.61" />
<HLASY_STRANA KSTRANA="75" HLASY="1" PROC_HLASU="0.61" />
<HLASY_STRANA KSTRANA="78" HLASY="11" PROC_HLASU="6.74" />
<HLASY_STRANA KSTRANA="82" HLASY="6" PROC_HLASU="3.68" />
</OBEC>
<OBEC CIS_OBEC="598810" NAZ_OBEC="Třinec">
<UCAST OKRSKY_CELKEM="38" OKRSKY_ZPRAC="38" OKRSKY_ZPRAC_PROC="100.00" ZAPSANI_VOLICI="29382" VYDANE_OBALKY="8340" UCAST_PROC="28.38" ODEVZDANE_OBALKY="8279" PLATNE_HLASY="8065" PLATNE_HLASY_PROC="97.42" />
<HLASY_STRANA KSTRANA="1" HLASY="50" PROC_HLASU="0.61" />
<HLASY_STRANA KSTRANA="2" HLASY="604" PROC_HLASU="7.48" />
<HLASY_STRANA KSTRANA="9" HLASY="80" PROC_HLASU="0.99" />
<HLASY_STRANA KSTRANA="12" HLASY="1590" PROC_HLASU="19.71" />
<HLASY_STRANA KSTRANA="24" HLASY="1143" PROC_HLASU="14.17" />
<HLASY_STRANA KSTRANA="26" HLASY="4" PROC_HLASU="0.04" />
<HLASY_STRANA KSTRANA="28" HLASY="2" PROC_HLASU="0.02" />
<HLASY_STRANA KSTRANA="30" HLASY="2284" PROC_HLASU="28.31" />
<HLASY_STRANA KSTRANA="31" HLASY="19" PROC_HLASU="0.23" />
<HLASY_STRANA KSTRANA="32" HLASY="136" PROC_HLASU="1.68" />
<HLASY_STRANA KSTRANA="37" HLASY="583" PROC_HLASU="7.22" />
<HLASY_STRANA KSTRANA="41" HLASY="5" PROC_HLASU="0.06" />
<HLASY_STRANA KSTRANA="43" HLASY="238" PROC_HLASU="2.95" />
<HLASY_STRANA KSTRANA="45" HLASY="16" PROC_HLASU="0.19" />
<HLASY_STRANA KSTRANA="46" HLASY="76" PROC_HLASU="0.94" />
<HLASY_STRANA KSTRANA="47" HLASY="237" PROC_HLASU="2.93" />
<HLASY_STRANA KSTRANA="52" HLASY="46" PROC_HLASU="0.57" />
<HLASY_STRANA KSTRANA="65" HLASY="108" PROC_HLASU="1.33" />
<HLASY_STRANA KSTRANA="67" HLASY="25" PROC_HLASU="0.30" />
<HLASY_STRANA KSTRANA="68" HLASY="102" PROC_HLASU="1.26" />
<HLASY_STRANA KSTRANA="70" HLASY="15" PROC_HLASU="0.18" />
<HLASY_STRANA KSTRANA="75" HLASY="53" PROC_HLASU="0.65" />
<HLASY_STRANA KSTRANA="78" HLASY="449" PROC_HLASU="5.56" />
<HLASY_STRANA KSTRANA="81" HLASY="9" PROC_HLASU="0.11" />
<HLASY_STRANA KSTRANA="82" HLASY="191" PROC_HLASU="2.36" />
</OBEC>
</VYSLEDKY_OKRES>
